Workbook

Sheet 📋 НАВИГАЦИЯ
A1: ФИНАНСОВАЯ МОДЕЛЬ — КОФЕЙНЯ: КОФЕ С СОБОЙ
A2: Город: Актобе | Горизонт: 36 месяцев (3 года) | Дата: 04.04.2026
B3: СОДЕРЖАНИЕ
A5: 1 | B5: 📖 КАК ЧИТАТЬ МОДЕЛЬ | C5: Объяснение модели для начинающих
A6: 2 | B6: ⚙️ ПАРАМЕТРЫ | C6: Все ваши входные данные (жёлтые ячейки)
A7: 3 | B7: 📊 ДОПУЩЕНИЯ | C7: Сезонность, инфляция, налоговый каскад
A8: 4 | B8: 🎯 ДАШБОРД | C8: Ключевые показатели + автодиагностика
A9: 5 | B9: 📈 P&L | C9: Помесячный отчёт о прибылях и убытках
A10: 6 | B10: 💰 CASH FLOW | C10: Движение денежных средств
A11: 7 | B11: 📋 КРЕДИТ | C11: График погашения кредита
A12: 8 | B12: 📑 БАЛАНС | C12: Квартальный баланс
A13: 9 | B13: 🔄 СЦЕНАРИИ | C13: 5 сценариев чувствительности
A14: 10 | B14: ✅ ПРОВЕРКА | C14: 10 автоматических проверок
A15: 11 | B15: 🔥 СТРЕСС-ТЕСТ
B16: ИНСТРУКЦИЯ
A17: 1 | B17: Откройте ⚙️ ПАРАМЕТРЫ — введите данные в жёлтые ячейки
A18: 2 | B18: Настройте 📊 ДОПУЩЕНИЯ — сезонность под ваш регион
A19: 3 | B19: Результаты на 🎯 ДАШБОРДЕ — автоматически
A20: 4 | B20: 📈 P&L и 💰 CASH FLOW — помесячная детализация
A21: 5 | B21: 🔄 ЧУВСТВИТЕЛЬНОСТЬ — стресс-тест параметров
A22: 6 | B22: ✅ ПРОВЕРКА — все формулы должны показать OK
A23: 7 | B23: 🔥 СТРЕСС-ТЕСТ — 4 сценария стресс-тестирования
B26: Сформировано: ZEREK — аналитика для предпринимателей КЗ | 04.04.2026 | @zerekai_bot

Sheet 📖 КАК ЧИТАТЬ МОДЕЛЬ
B1: КАК ПОЛЬЗОВАТЬСЯ ЭТОЙ МОДЕЛЬЮ
B2: 📌 Модель полностью автоматическая. Вам нужно только заполнить жёлтые ячейки — всё остальное пересчитается.
A4: 1️⃣ | B4: ЗАПОЛНИТЕ ⚙️ ПАРАМЕТРЫ
B5: Все жёлтые ячейки — это ваши данные. Средний чек, аренда, зарплаты, стартовые вложения. Меняйте их под свой бизнес.
A7: 2️⃣ | B7: НАСТРОЙТЕ 📊 ДОПУЩЕНИЯ
B8: Сезонность и ramp-up (выход на мощность). Если не уверены — оставьте как есть, значения по умолчанию реалистичны.
A10: 3️⃣ | B10: СМОТРИТЕ 🎯 ДАШБОРД
B11: Главные цифры: окупаемость, прибыль, риски. Всё пересчитывается автоматически при изменении параметров.
A13: 4️⃣ | B13: ЧТО ОЗНАЧАЮТ ПОКАЗАТЕЛИ
B14: • NPV > 0 → проект создаёт стоимость (хорошо)
B15: • IRR > 20% → доходность выше банковского депозита (отлично)
B16: • Окупаемость < 18 мес → быстро вернёте вложения
B17: • Точка безубыточности → минимум клиентов, чтобы не работать в убыток
B18: • Запас прочности → на сколько % может упасть выручка, прежде чем убытки
A20: 5️⃣ | B20: СТРЕСС-ТЕСТ 🔥
B21: Показывает, что будет если дела пойдут хуже ожиданий.
B22: Если даже в «жёстком» сценарии бизнес прибыльный — вы в безопасности.
A24: 6️⃣ | B24: ДИСКЛЕЙМЕР
B25: Модель — аналитический инструмент, не гарантия результата.
B26: Реальные цифры могут отличаться от прогноза. ZEREK не несёт ответственности за бизнес-решения.
B28: ZEREK Financial Model | @zerekai_bot | zerek.cc

Sheet ⚙️ ПАРАМЕТРЫ
A1: ПАРАМЕТРЫ МОДЕЛИ — КОФЕЙНЯ: КОФЕ С СОБОЙ
A2: 📌 Правило: меняйте только жёлтые ячейки. Синий текст = введённое число. Чёрный текст = формула (не трогать). Все листы пересчитываются автоматически.
A3: 0. ОБЩИЕ ПАРАМЕТРЫ
B4: Параметр | C4: Значение | D4: Ед. | E4: Пояснение (дисклеймер)
B5: Форма собственности | C5: ИП | E5: 💡 ИП: свободный вывод. ТОО: дивиденды (5% ИПН)
B6: Налоговый режим | C6: УСН | E6: 💡 УСН: 2-4% от оборота. Порог: 600 000 МРП
B7: Плательщик НДС | C7: Нет | E7: 💡 Автоматически «Да» при выручке > 10 000 МРП
B8: Ставка налога (маслихат) | C8: 0.03 | D8: % | E8: 💡 Ставка маслихата. Актобе: 3%
B9: Горизонт модели | C9: 36 | D9: мес | E9: 💡 36 мес = 3 года. Стандарт для МСБ
A10: 1. ВЫРУЧКА
B11: Параметр | C11: Значение | D11: Ед. | E11: Пояснение (дисклеймер)
B12: Средний чек (корзина) | C12: 1400 | D12: ₸ | E12: 💡 Вся покупка 1 клиента целиком
B13: Клиентов в день (на полной мощности) | C13: 70 | D13: чел/день | E13: 💡 Трафик после ramp-up
B14: Рабочих дней в месяце | C14: 30 | D14: дней | E14: 💡 Общепит = 30, офис = 22
B15: Рост трафика в год | C15: 0.07 | D15: % | E15: 💡 5-10% для МСБ
B16: Рост среднего чека в год | C16: 0.08 | D16: % | E16: 💡 Инфляция + допродажи ≈ 8%
A17: 2. ПРЯМЫЕ РАСХОДЫ
B18: Параметр | C18: Значение | D18: Ед. | E18: Пояснение (дисклеймер)
B19: Себестоимость (% от выручки) | C19: 0.35 | D19: % | E19: 💡 Общепит: 30-40%, услуги: 5-15%
B20: Потери и списания (% от выручки) | C20: 0.03 | D20: % | E20: 💡 Брак, просрочка. Общепит: 3-5%
A21: 3. ПОСТОЯННЫЕ РАСХОДЫ
B22: Параметр | C22: Значение | D22: Ед. | E22: Пояснение (дисклеймер)
B23: Аренда помещения | C23: 70000 | D23: ₸/мес | E23: 💡 Актобе: ~3000-5000 ₸/м²
B24: Площадь помещения | C24: 6 | D24: м² | E24: 💡 Типовая площадь для формата
B25: ФОТ Gross (оклад сотрудников) | C25: 200000 | D25: ₸/мес | E25: 💡 Gross = до удержаний
B26: Количество сотрудников | C26: 2 | D26: чел | E26: 💡 Штат на полную мощность
B27: Коммунальные | C27: 15000 | D27: ₸/мес | E27: 💡 Свет, вода, отопление
B28: Маркетинг | C28: 50000 | D28: ₸/мес | E28: 💡 Instagram, 2ГИС, акции
B29: Расходники | C29: 3500 | D29: ₸/мес | E29: 💡 Мелочи вне себестоимости
B30: Софт / касса / CRM | C30: 5000 | D30: ₸/мес | E30: 💡 Kaspi касса, iiko, Poster
B31: Прочие расходы | C31: 10000 | D31: ₸/мес | E31: 💡 Транспорт, связь, непредвиденные
B32: Рост аренды в год | C32: ='📊 ДОПУЩЕНИЯ'!C9 -> 0.1 | D32: % | E32: 💡 ← Ссылка на ДОПУЩЕНИЯ. Меняйте там.
B33: Рост ФОТ в год | C33: ='📊 ДОПУЩЕНИЯ'!C10 -> 0.08 | D33: % | E33: 💡 ← Ссылка на ДОПУЩЕНИЯ. Меняйте там.
B34: Инфляция прочих расходов | C34: ='📊 ДОПУЩЕНИЯ'!C12 -> 0.08 | D34: % | E34: 💡 ← Ссылка на ДОПУЩЕНИЯ. Меняйте там.
A35: 4. СТАРТОВЫЕ ИНВЕСТИЦИИ
B36: Параметр | C36: Значение | D36: Ед. | E36: Пояснение (дисклеймер)
B37: CAPEX (оборудование + ремонт) | C37: 1500000 | D37: ₸ | E37: 💡 Оборудование + ремонт + мебель
B38: Депозит за аренду | C38: 2 | D38: мес | E38: 💡 Залог. Обычно 2-3 мес
B39: Оборотный капитал (резерв) | C39: 1000000 | D39: ₸ | E39: 💡 Резерв на 2-3 мес расходов
B40: Срок амортизации | C40: 7 | D40: лет | E40: 💡 Линейная. Оборудование: 5-7 лет
B41: ИТОГО ИНВЕСТИЦИИ | C41: =C37+C23*C38+C39 -> 2640000 | D41: ₸ | E41: 💡 Сумма: CAPEX + депозит аренды + оборотный капитал. Это ваши полные начальные вложения.
B42: Амортизация в месяц | C42: =ROUND(C37/C40/12,0) -> 17857 | D42: ₸/мес | E42: 💡 Ежемесячное списание стоимости оборудования. Не денежный расход, но влияет на прибыль.
B43: Налоги работодателя от ФОТ | C43: ='📊 ДОПУЩЕНИЯ'!C61 -> 40000 | D43: ₸/мес | E43: 💡 ОСМС(3%) + ОПВР(3.5%) + СО(3.5%) + СН(зависит от режима). Ложатся сверху на ФОТ.
A44: 5. КРЕДИТ (опционально)
B45: Параметр | C45: Значение | D45: Ед. | E45: Пояснение (дисклеймер)
B46: Сумма кредита | C46: 1000000 | D46: ₸ | E46: 💡 0 = без кредита
B47: Годовая ставка | C47: 0.22 | D47: % | E47: 💡 МСБ КЗ: 18-24%. Льготные: 6-14%
B48: Срок кредита | C48: 36 | D48: мес | E48: 💡 Стандарт: 24-60 мес
B49: Ежемесячный платёж (аннуитет) | C49: =IF(C46=0,0,PMT(C47/12,C48,-C46)) -> 38190.453 | D49: ₸/мес | E49: 💡 Аннуитетный платёж: фиксированная сумма каждый месяц (тело + проценты).
A50: 6. ДИСКОНТИРОВАНИЕ
B51: Параметр | C51: Значение | D51: Ед. | E51: Пояснение (дисклеймер)
B52: Ставка дисконтирования (WACC) | C52: 0.2 | D52: % | E52: 💡 МСБ КЗ: 18-25%. Не знаете → 20%
B55: ZEREK Financial Model | 04.04.2026 | @zerekai_bot

Sheet 📊 ДОПУЩЕНИЯ
A1: ДОПУЩЕНИЯ МОДЕЛИ
A2: 📌 Сезонные коэффициенты: 1.00 = норма, 1.10 = на 10% выше, 0.85 = на 15% ниже. Казахстан — резко континентальный климат: жаркое лето, холодная зима.
A3: СЕЗОННОСТЬ ТРАФИКА
B4: Месяц | C4: Янв | D4: Фев | E4: Мар | F4: Апр | G4: Май | H4: Июн | I4: Июл | J4: Авг | K4: Сен | L4: Окт | M4: Ноя | N4: Дек
B5: Коэффициент | C5: 0.85 | D5: 0.85 | E5: 0.9 | F5: 1 | G5: 1.05 | H5: 1.1 | I5: 1.1 | J5: 1.05 | K5: 1 | L5: 0.95 | M5: 0.95 | N5: 1.2
B6: 💡 Коэффициенты умножаются на базовый трафик. 1.15 в декабре = праздничный спрос +15%. 0.85 зимой = холод, меньше пешеходов.
A7: ИНФЛЯЦИЯ ПО СТАТЬЯМ
B8: Статья | C8: Рост/год | D8: Пояснение
B9: Аренда | C9: 0.1 | D9: 💡 Арендодатели КЗ индексируют ежегодно. Зависит от договора
B10: ФОТ | C10: 0.08 | D10: 💡 Рост зарплат. В КЗ ~8% в год
B11: Продукты/материалы | C11: 0.12 | D11: 💡 Продовольственная инфляция в КЗ выше общей: 10-15%
B12: Коммунальные | C12: 0.08 | D12: 💡 Тарифы регулируются, растут медленнее
B13: Маркетинг | C13: 0.05 | D13: 💡 Цифровая реклама дорожает медленнее
A15: RAMP-UP (ВЫХОД НА МОЩНОСТЬ)
B16: Месяц модели | C16: М1 | D16: М2 | E16: М3 | F16: М4 | G16: М5 | H16: М6 | I16: М7 | J16: М8 | K16: М9 | L16: М10 | M16: М11 | N16: М12
B17: Год 1 (% от мощности) | C17: 0.4 | D17: 0.7 | E17: 1 | F17: 1 | G17: 1 | H17: 1 | I17: 1 | J17: 1 | K17: 1 | L17: 1 | M17: 1 | N17: 1
B18: Год 2 (% от мощности) | C18: 1 | D18: 1 | E18: 1 | F18: 1 | G18: 1 | H18: 1 | I18: 1 | J18: 1 | K18: 1 | L18: 1 | M18: 1 | N18: 1
B19: Год 3 (% от мощности) | C19: 1 | D19: 1 | E19: 1 | F19: 1 | G19: 1 | H19: 1 | I19: 1 | J19: 1 | K19: 1 | L19: 1 | M19: 1 | N19: 1
B20: 💡 Ramp-up = % от полной мощности. М1=40% → 28 клиентов из 70 возможных. 100% = полная мощность. Год 2-3 можно оставить 100% или задать плавный рост.
A23: НАЛОГОВАЯ СИСТЕМА РК (2026)
A24: СПРАВОЧНЫЕ ДАННЫЕ
B25: Параметр | C25: Значение | D25: Ед. | E25: Примечание
B26: МРП (2026) | C26: 4325 | D26: ₸ | E26: Месячный расчётный показатель (Закон о бюджете)
B27: Порог НДС | C27: =C26*10000 -> 43250000 | D27: ₸ | E27: = 10 000 × МРП. ОУР: превышение → обязат. НДС
B28: Лимит выручки УСН | C28: =C26*600000 -> 2595000000 | D28: ₸ | E28: = 600 000 × МРП. Макс. оборот для УСН
B29: Порог прогр. шкалы ИПН | C29: =C26*230000 -> 994750000 | D29: ₸ | E29: = 230 000 × МРП. До порога 10%, свыше 15%
A31: ЗАРПЛАТНЫЕ НАЛОГИ И ОТЧИСЛЕНИЯ
B32: Удержания с работника (внутри Gross)
B33: ИПН | C33: 0.1 | E33: 10% от оклада (ст. 320 НК РК)
B34: ОПВ | C34: 0.1 | E34: 10% от оклада в ЕНПФ
B35: ВОСМС | C35: 0.02 | E35: 2% от оклада
B36: Налоги работодателя (сверх оклада)
B37: ОСМС | C37: 0.03 | E37: 3% от оклада
B38: ОПВР | C38: 0.035 | E38: 3.5% от оклада (с 2024)
B39: СО | C39: 0.035 | E39: 3.5% от оклада
B40: СН | C40: 0.095 | E40: 9.5% − СО при ОУР. На УСН = 0
A42: КОРПОРАТИВНЫЕ НАЛОГИ
B43: Ставка УСН (НК макс.) | C43: 0.04 | E43: 4% от оборота (ст. 687)
B44: Ставка НДС | C44: 0.16 | E44: 16% с 2025 (ст. 422 НК)
B45: КПН (ТОО на ОУР) | C45: 0.2 | E45: 20% от дохода (ст. 313 НК)
B46: ИПН базовая (ИП ОУР) | C46: 0.1 | E46: 10% от дохода до порога
B47: ИПН повышенная (ИП ОУР) | C47: 0.15 | E47: 15% от суммы превышения
B48: Налог на дивиденды (ТОО) | C48: 0.05 | E48: ИПН с дивидендов 5%
A50: КАСКАДНАЯ ЛОГИКА ВЫБОРА РЕЖИМА
B51: Параметр | C51: Значение | D51: Ед. | E51: Примечание
B52: Плательщик НДС (← из Параметров) | C52: ='⚙️ ПАРАМЕТРЫ'!C7 -> Нет | E52: Ссылка на C7 в Параметрах
B53: Годовая выручка (макс. 12 мес) | C53: =SUM('📈 P&L'!C12:N12) -> 32676000 | D53: ₸ | E53: Макс. 12-мес. выручка из P&L
B54: Слетает с УСН? | C54: =IF('⚙️ ПАРАМЕТРЫ'!C6="УСН",IF(C53>C28,"Да","Нет"),"—") -> Нет | E54: Если режим УСН и выручка > лимита → ОУР
B55: ИТОГО: Налоговый режим | C55: =IF(AND('⚙️ ПАРАМЕТРЫ'!C6="УСН",C54="Нет"),"УСН","ОУР") -> УСН | E55: Если УСН и в пределах лимита → УСН, иначе ОУР
B56: Превышает порог НДС? | C56: =IF(C55="ОУР",IF(C53>C27,"Да","Нет"),"Нет") -> Нет | E56: Только на ОУР: если выручка > 10 000 МРП
B57: ИТОГО: Статус НДС | C57: =IF(OR('⚙️ ПАРАМЕТРЫ'!C7="Да",C56="Да"),"Да","Нет") -> Нет | E57: «Да» если добровольно или по порогу
B58: Итоговая ставка УСН | C58: =IF('⚙️ ПАРАМЕТРЫ'!C8>0,'⚙️ ПАРАМЕТРЫ'!C8,C43) -> 0.03 | D58: % | E58: Маслихат если задан, иначе 4%
B59: Эффект. ставка корп. налога | C59: =IF(C55="УСН",C58,IF('⚙️ ПАРАМЕТРЫ'!C5="ТОО",C45,C46)) -> 0.03 | D59: % | E59: УСН: ставка маслихата. ИП ОУР: ИПН. ТОО ОУР: КПН
B60: Итого % налогов работодателя | C60: =IF(C55="УСН",C37+C38+C39,C37+C38+C39+MAX(C40-C39,0)) -> 0.1 | D60: % | E60: ОУР: ОСМС+ОПВР+СО+(СН−СО). УСН: ОСМС+ОПВР+СО
B61: Налоги работодателя, ₸/мес | C61: =ROUND('⚙️ ПАРАМЕТРЫ'!C25*'⚙️ ПАРАМЕТРЫ'!C26*C60,0) -> 40000 | D61: ₸/мес | E61: = ФОТ Gross × итого %
B62: ИТОГО расход на персонал | C62: ='⚙️ ПАРАМЕТРЫ'!C25*'⚙️ ПАРАМЕТРЫ'!C26+C61 -> 440000 | D62: ₸/мес | E62: = ФОТ Gross + налоги работодателя
A63: 💡 Ставки НК РК 2026. Не изменяйте без обновления законодательства.
A65: ИСТОЧНИКИ И ОГРАНИЧЕНИЯ МОДЕЛИ
A67: Какие цифры вводит пользователь:
A68: → Средний чек, трафик, аренда, ФОТ, CAPEX, кредит
A70: Какие параметры типовые (ZEREK):
A71: → Сезонность, инфляция по статьям, налоговые ставки, ramp-up
A73: Ориентиры:
A74: → Данные БНС РК, маслихатные решения, бенчмарки базы ZEREK
A76: Что НЕ является гарантией:
A77: → Все цифры модели — прогноз, основанный на допущениях.
A78: → Реальные результаты зависят от исполнения, рынка, конкуренции.
A79: → ZEREK не несёт ответственности за бизнес-решения.

Sheet 🎯 ДАШБОРД
A1: ДАШБОРД — КОФЕЙНЯ: КОФЕ С СОБОЙ (Актобе)
A2: Дата: 04.04.2026 | Горизонт: 36 мес | Все показатели обновляются автоматически
A3: КЛЮЧЕВЫЕ ИНВЕСТИЦИОННЫЕ ПОКАЗАТЕЛИ
B4: NPV | C4: IRR | D4: Окупаемость | E4: ROI
B5: =NPV('⚙️ ПАРАМЕТРЫ'!C52/12,'💰 CASH FLOW'!C25:AL25)+'💰 CASH FLOW'!B25 -> 31863328 | C5: =IFERROR(IRR('💰 CASH FLOW'!B25:AL25),0) -> 0.31820615 | D5: {=IFERROR(MATCH(1,('💰 CASH FLOW'!C26:AL26>=0)*1,0),">36")} -> 4 | E5: =IFERROR(SUM('💰 CASH FLOW'!C25:AL25)/(-'💰 CASH FLOW'!B25),0) -> 18.025752
B6: Чистая приведённая стоимость проекта. NPV > 0 → проект выгоден | C6: Месячная доходность проекта. Сравните с WACC/12 (1.7%/мес) | D6: Через сколько месяцев вернёте вложения (все инвестиции) | E6: Прибыль за 3 года / все инвестиции. >100% = вложения вернулись
A8: СВОДНЫЙ P&L ЗА 3 ГОДА
B9: Показатель | C9: Итого 36 мес | D9: ₸/мес (средн.) | E9: % от выручки
B10: Выручка | C10: =SUM('📈 P&L'!C12:AL12) -> 120485040 | D10: =IFERROR(C10/36,"") -> 3346806.7 | E10: =IFERROR(C10/SUM('📈 P&L'!C12:AL12),"") -> 1
B11: ▸ Себестоимость | C11: =SUM('📈 P&L'!C14:AL14) -> 42169764 | D11: =IFERROR(C11/36,"") -> 1171382.3 | E11: =IFERROR(C11/SUM('📈 P&L'!C12:AL12),"") -> 0.35
B12: ▸ Потери | C12: =SUM('📈 P&L'!C15:AL15) -> 3614553 | D12: =IFERROR(C12/36,"") -> 100404.25 | E12: =IFERROR(C12/SUM('📈 P&L'!C12:AL12),"") -> 0.030000015
B13: Валовая прибыль | C13: =SUM('📈 P&L'!C16:AL16) -> 74700723 | D13: =IFERROR(C13/36,"") -> 2075020.1 | E13: =IFERROR(C13/SUM('📈 P&L'!C12:AL12),"") -> 0.61999999
B14: ▸ ФОТ | C14: =SUM('📈 P&L'!C18:AL18) -> 15582720 | D14: =IFERROR(C14/36,"") -> 432853.33 | E14: =IFERROR(C14/SUM('📈 P&L'!C12:AL12),"") -> 0.12933324
B15: ▸ Аренда | C15: =SUM('📈 P&L'!C24:AL24) -> 2780400 | D15: =IFERROR(C15/36,"") -> 77233.333 | E15: =IFERROR(C15/SUM('📈 P&L'!C12:AL12),"") -> 0.023076724
B16: ▸ Прочие пост. | C16: =SUM('📈 P&L'!C25:AL25)+SUM('📈 P&L'!C26:AL26)+SUM('📈 P&L'!C27:AL27)+SUM('📈 P&L'!C28:AL28)+SUM('📈 P&L'!C29:AL29) -> 3201924 | D16: =IFERROR(C16/36,"") -> 88942.333 | E16: =IFERROR(C16/SUM('📈 P&L'!C12:AL12),"") -> 0.026575283
B17: EBITDA | C17: =SUM('📈 P&L'!C31:AL31) -> 51577395 | D17: =IFERROR(C17/36,"") -> 1432705.4 | E17: =IFERROR(C17/SUM('📈 P&L'!C12:AL12),"") -> 0.42808132
B18: Налог | C18: =SUM('📈 P&L'!C35:AL35) -> 3614553 | D18: =IFERROR(C18/36,"") -> 100404.25 | E18: =IFERROR(C18/SUM('📈 P&L'!C12:AL12),"") -> 0.030000015
B19: ЧИСТАЯ ПРИБЫЛЬ | C19: =SUM('📈 P&L'!C38:AL38) -> 46945134 | D19: =IFERROR(C19/36,"") -> 1304031.5 | E19: =IFERROR(C19/SUM('📈 P&L'!C12:AL12),"") -> 0.38963454
A21: АВТОМАТИЧЕСКИЙ ВЫВОД
B22: =IF(B5>0,"✅ NPV положительный — проект создаёт стоимость.","❌ NPV отрицательный — проект разрушает стоимость.") -> ✅ NPV положительный — проект создаёт стоимость.
B23: =IF(C5>'⚙️ ПАРАМЕТРЫ'!C52/12,"✅ IRR выше WACC — проект привлекателен для инвестора.","⚠️ IRR ниже WACC — доходность не покрывает риски.") -> ✅ IRR выше WACC — проект привлекателен для инвестора.
B24: =IF(D5<=18,"✅ Окупаемость до 18 мес — отличный показатель.",IF(D5<=30,"⚠️ Окупаемость 18-30 мес — приемлемо.","❌ Окупаемость >30 мес — высокий риск.")) -> ✅ Окупаемость до 18 мес — отличный показатель.
A26: ДОПОЛНИТЕЛЬНЫЕ МЕТРИКИ
B27: Стартовые вложения (ИТОГО) | C27: ='⚙️ ПАРАМЕТРЫ'!C41 -> 2640000 | D27: ₸
B28: Точка безубыточности | C28: ='🔥 СТРЕСС-ТЕСТ'!C59 -> 26 | D28: клиентов/день
B29: Запас ликвидности (мин. ДС) | C29: =MIN('💰 CASH FLOW'!C22:AL22) -> -1577850.5 | D29: ₸
B30: Кассовый разрыв? | C30: =IF(MIN('💰 CASH FLOW'!C22:AL22)<0,"ДА 🔴","НЕТ ✅") -> ДА 🔴
B31: Главный риск (макс. негативный фактор) | C31: =INDEX('🔥 СТРЕСС-ТЕСТ'!B46:B50,MATCH(MIN('🔥 СТРЕСС-ТЕСТ'!E46:E50),'🔥 СТРЕСС-ТЕСТ'!E46:E50,0)) -> Трафик − 20%
B32: Главный драйвер роста | C32: =INDEX('🔥 СТРЕСС-ТЕСТ'!B46:B50,MATCH(MAX('🔥 СТРЕСС-ТЕСТ'!E46:E50),'🔥 СТРЕСС-ТЕСТ'!E46:E50,0)) -> Аренда + 20%
A34: ДИАГНОЗ МОДЕЛИ
B35: =IF(AND(B5>0,D5<=24,C30="НЕТ ✅"),"✅ Проект жизнеспособен. NPV+, окупаемость в норме, разрывов нет.","❌ Есть зоны риска — см. ниже.") -> ❌ Есть зоны риска — см. ниже.
B36: =IF(D5>30,"❌ Окупаемость > 30 мес → снизьте CAPEX или поднимите чек.",IF(D5>18,"⚠️ Окупаемость "&D5&" мес → ищите допродажи и лояльность.","✅ Окупаемость "&D5&" мес — норма.")) -> ✅ Окупаемость 4 мес — норма.
B37: =IF(IFERROR(AVERAGE('📈 P&L'!O24:Z24)/AVERAGE('📈 P&L'!O12:Z12),0)>0.25,"⚠️ Аренда > 25% выручки → торгуйтесь или меняйте локацию.","✅ Аренда в норме.") -> ✅ Аренда в норме.
B38: =IF(IFERROR(C17/C10,0)<0.1,"⚠️ EBITDA < 10% → режьте постоянные или поднимайте чек.","✅ EBITDA маржа здоровая.") -> ✅ EBITDA маржа здоровая.
B39: =IF(C30="ДА 🔴","❌ Кассовый разрыв! → добавьте "&TEXT(ABS(C29),"# ##0")&" ₸ оборотки.","✅ Разрывов нет. Мин. остаток: "&TEXT(C29,"# ##0")&" ₸.") -> ❌ Кассовый разрыв! → добавьте 1 577 850 ₸ оборотки.
A41: ZEREK | 04.04.2026

Sheet 📈 P&L
A1: ОТЧЁТ О ПРИБЫЛЯХ И УБЫТКАХ — КОФЕЙНЯ: КОФЕ С СОБОЙ (Актобе)
A2: 📌 Помесячно, 36 мес. Формулы → ⚙️ ПАРАМЕТРЫ и 📊 ДОПУЩЕНИЯ.
B3: Статья / Период | C3: М1 | D3: М2 | E3: М3 | F3: М4 | G3: М5 | H3: М6 | I3: М7 | J3: М8 | K3: М9 | L3: М10 | M3: М11 | N3: М12 | O3: М13 | P3: М14 | Q3: М15 | R3: М16 | S3: М17 | T3: М18 | U3: М19 | V3: М20 | W3: М21 | X3: М22 | Y3: М23 | Z3: М24 | AA3: М25 | AB3: М26 | AC3: М27 | AD3: М28 | AE3: М29 | AF3: М30 | AG3: М31 | AH3: М32 | AI3: М33 | AJ3: М34 | AK3: М35 | AL3: М36
B4: Кал. месяц | C4: =MOD(1-1+3,12)+1 -> 4 | D4: =MOD(2-1+3,12)+1 -> 5 | E4: =MOD(3-1+3,12)+1 -> 6 | F4: =MOD(4-1+3,12)+1 -> 7 | G4: =MOD(5-1+3,12)+1 -> 8 | H4: =MOD(6-1+3,12)+1 -> 9 | I4: =MOD(7-1+3,12)+1 -> 10 | J4: =MOD(8-1+3,12)+1 -> 11 | K4: =MOD(9-1+3,12)+1 -> 12 | L4: =MOD(10-1+3,12)+1 -> 1 | M4: =MOD(11-1+3,12)+1 -> 2 | N4: =MOD(12-1+3,12)+1 -> 3 | O4: =MOD(13-1+3,12)+1 -> 4 | P4: =MOD(14-1+3,12)+1 -> 5 | Q4: =MOD(15-1+3,12)+1 -> 6 | R4: =MOD(16-1+3,12)+1 -> 7 | S4: =MOD(17-1+3,12)+1 -> 8 | T4: =MOD(18-1+3,12)+1 -> 9 | U4: =MOD(19-1+3,12)+1 -> 10 | V4: =MOD(20-1+3,12)+1 -> 11 | W4: =MOD(21-1+3,12)+1 -> 12 | X4: =MOD(22-1+3,12)+1 -> 1 | Y4: =MOD(23-1+3,12)+1 -> 2 | Z4: =MOD(24-1+3,12)+1 -> 3 | AA4: =MOD(25-1+3,12)+1 -> 4 | AB4: =MOD(26-1+3,12)+1 -> 5 | AC4: =MOD(27-1+3,12)+1 -> 6 | AD4: =MOD(28-1+3,12)+1 -> 7 | AE4: =MOD(29-1+3,12)+1 -> 8 | AF4: =MOD(30-1+3,12)+1 -> 9 | AG4: =MOD(31-1+3,12)+1 -> 10 | AH4: =MOD(32-1+3,12)+1 -> 11 | AI4: =MOD(33-1+3,12)+1 -> 12 | AJ4: =MOD(34-1+3,12)+1 -> 1 | AK4: =MOD(35-1+3,12)+1 -> 2 | AL4: =MOD(36-1+3,12)+1 -> 3
B5: Сез. коэфф. | C5: =INDEX('📊 ДОПУЩЕНИЯ'!$C$5:$N$5,1,C4) -> 1 | D5: =INDEX('📊 ДОПУЩЕНИЯ'!$C$5:$N$5,1,D4) -> 1.05 | E5: =INDEX('📊 ДОПУЩЕНИЯ'!$C$5:$N$5,1,E4) -> 1.1 | F5: =INDEX('📊 ДОПУЩЕНИЯ'!$C$5:$N$5,1,F4) -> 1.1 | G5: =INDEX('📊 ДОПУЩЕНИЯ'!$C$5:$N$5,1,G4) -> 1.05 | H5: =INDEX('📊 ДОПУЩЕНИЯ'!$C$5:$N$5,1,H4) -> 1 | I5: =INDEX('📊 ДОПУЩЕНИЯ'!$C$5:$N$5,1,I4) -> 0.95 | J5: =INDEX('📊 ДОПУЩЕНИЯ'!$C$5:$N$5,1,J4) -> 0.95 | ... AL5: =INDEX('📊 ДОПУЩЕНИЯ'!$C$5:$N$5,1,AL4) -> 0.9
B6: Ramp-up | C6: {=INDEX('📊 ДОПУЩЕНИЯ'!$C$17:$N$19,INT((COLUMN()-3)/12)+1,MOD(COLUMN()-3,12)+1)} -> 0.4 | D6: {=INDEX('📊 ДОПУЩЕНИЯ'!$C$17:$N$19,INT((COLUMN()-3)/12)+1,MOD(COLUMN()-3,12)+1)} -> 0.7 | E6: {=INDEX('📊 ДОПУЩЕНИЯ'!$C$17:$N$19,INT((COLUMN()-3)/12)+1,MOD(COLUMN()-3,12)+1)} -> 1 | F6: {=INDEX('📊 ДОПУЩЕНИЯ'!$C$17:$N$19,INT((COLUMN()-3)/12)+1,MOD(COLUMN()-3,12)+1)} -> 1 | G6: {=INDEX('📊 ДОПУЩЕНИЯ'!$C$17:$N$19,INT((COLUMN()-3)/12)+1,MOD(COLUMN()-3,12)+1)} -> 1 | H6: {=INDEX('📊 ДОПУЩЕНИЯ'!$C$17:$N$19,INT((COLUMN()-3)/12)+1,MOD(COLUMN()-3,12)+1)} -> 1 | I6: {=INDEX('📊 ДОПУЩЕНИЯ'!$C$17:$N$19,INT((COLUMN()-3)/12)+1,MOD(COLUMN()-3,12)+1)} -> 1 | J6: {=INDEX('📊 ДОПУЩЕНИЯ'!$C$17:$N$19,INT((COLUMN()-3)/12)+1,MOD(COLUMN()-3,12)+1)} -> 1 | ... AL6: {=INDEX('📊 ДОПУЩЕНИЯ'!$C$17:$N$19,INT((COLUMN()-3)/12)+1,MOD(COLUMN()-3,12)+1)} -> 1
B7: ВЫРУЧКА
B8: Множитель роста трафика | C8: =(1+'⚙️ ПАРАМЕТРЫ'!$C$15)^INT((1-1)/12) -> 1 | D8: =(1+'⚙️ ПАРАМЕТРЫ'!$C$15)^INT((2-1)/12) -> 1 | E8: =(1+'⚙️ ПАРАМЕТРЫ'!$C$15)^INT((3-1)/12) -> 1 | F8: =(1+'⚙️ ПАРАМЕТРЫ'!$C$15)^INT((4-1)/12) -> 1 | G8: =(1+'⚙️ ПАРАМЕТРЫ'!$C$15)^INT((5-1)/12) -> 1 | H8: =(1+'⚙️ ПАРАМЕТРЫ'!$C$15)^INT((6-1)/12) -> 1 | I8: =(1+'⚙️ ПАРАМЕТРЫ'!$C$15)^INT((7-1)/12) -> 1 | J8: =(1+'⚙️ ПАРАМЕТРЫ'!$C$15)^INT((8-1)/12) -> 1 | K8: =(1+'⚙️ ПАРАМЕТРЫ'!$C$15)^INT((9-1)/12) -> 1 | L8: =(1+'⚙️ ПАРАМЕТРЫ'!$C$15)^INT((10-1)/12) -> 1 | M8: =(1+'⚙️ ПАРАМЕТРЫ'!$C$15)^INT((11-1)/12) -> 1 | N8: =(1+'⚙️ ПАРАМЕТРЫ'!$C$15)^INT((12-1)/12) -> 1 | O8: =(1+'⚙️ ПАРАМЕТРЫ'!$C$15)^INT((13-1)/12) -> 1.07 | P8: =(1+'⚙️ ПАРАМЕТРЫ'!$C$15)^INT((14-1)/12) -> 1.07 | Q8: =(1+'⚙️ ПАРАМЕТРЫ'!$C$15)^INT((15-1)/12) -> 1.07 | R8: =(1+'⚙️ ПАРАМЕТРЫ'!$C$15)^INT((16-1)/12) -> 1.07 | S8: =(1+'⚙️ ПАРАМЕТРЫ'!$C$15)^INT((17-1)/12) -> 1.07 | T8: =(1+'⚙️ ПАРАМЕТРЫ'!$C$15)^INT((18-1)/12) -> 1.07 | U8: =(1+'⚙️ ПАРАМЕТРЫ'!$C$15)^INT((19-1)/12) -> 1.07 | V8: =(1+'⚙️ ПАРАМЕТРЫ'!$C$15)^INT((20-1)/12) -> 1.07 | W8: =(1+'⚙️ ПАРАМЕТРЫ'!$C$15)^INT((21-1)/12) -> 1.07 | X8: =(1+'⚙️ ПАРАМЕТРЫ'!$C$15)^INT((22-1)/12) -> 1.07 | Y8: =(1+'⚙️ ПАРАМЕТРЫ'!$C$15)^INT((23-1)/12) -> 1.07 | Z8: =(1+'⚙️ ПАРАМЕТРЫ'!$C$15)^INT((24-1)/12) -> 1.07 | AA8: =(1+'⚙️ ПАРАМЕТРЫ'!$C$15)^INT((25-1)/12) -> 1.1449 | AB8: =(1+'⚙️ ПАРАМЕТРЫ'!$C$15)^INT((26-1)/12) -> 1.1449 | AC8: =(1+'⚙️ ПАРАМЕТРЫ'!$C$15)^INT((27-1)/12) -> 1.1449 | AD8: =(1+'⚙️ ПАРАМЕТРЫ'!$C$15)^INT((28-1)/12) -> 1.1449 | AE8: =(1+'⚙️ ПАРАМЕТРЫ'!$C$15)^INT((29-1)/12) -> 1.1449 | AF8: =(1+'⚙️ ПАРАМЕТРЫ'!$C$15)^INT((30-1)/12) -> 1.1449 | AG8: =(1+'⚙️ ПАРАМЕТРЫ'!$C$15)^INT((31-1)/12) -> 1.1449 | AH8: =(1+'⚙️ ПАРАМЕТРЫ'!$C$15)^INT((32-1)/12) -> 1.1449 | AI8: =(1+'⚙️ ПАРАМЕТРЫ'!$C$15)^INT((33-1)/12) -> 1.1449 | AJ8: =(1+'⚙️ ПАРАМЕТРЫ'!$C$15)^INT((34-1)/12) -> 1.1449 | AK8: =(1+'⚙️ ПАРАМЕТРЫ'!$C$15)^INT((35-1)/12) -> 1.1449 | AL8: =(1+'⚙️ ПАРАМЕТРЫ'!$C$15)^INT((36-1)/12) -> 1.1449
B9: Множитель роста чека | C9: =(1+'⚙️ ПАРАМЕТРЫ'!$C$16)^INT((1-1)/12) -> 1 | D9: =(1+'⚙️ ПАРАМЕТРЫ'!$C$16)^INT((2-1)/12) -> 1 | E9: =(1+'⚙️ ПАРАМЕТРЫ'!$C$16)^INT((3-1)/12) -> 1 | F9: =(1+'⚙️ ПАРАМЕТРЫ'!$C$16)^INT((4-1)/12) -> 1 | G9: =(1+'⚙️ ПАРАМЕТРЫ'!$C$16)^INT((5-1)/12) -> 1 | H9: =(1+'⚙️ ПАРАМЕТРЫ'!$C$16)^INT((6-1)/12) -> 1 | I9: =(1+'⚙️ ПАРАМЕТРЫ'!$C$16)^INT((7-1)/12) -> 1 | J9: =(1+'⚙️ ПАРАМЕТРЫ'!$C$16)^INT((8-1)/12) -> 1 | K9: =(1+'⚙️ ПАРАМЕТРЫ'!$C$16)^INT((9-1)/12) -> 1 | L9: =(1+'⚙️ ПАРАМЕТРЫ'!$C$16)^INT((10-1)/12) -> 1 | M9: =(1+'⚙️ ПАРАМЕТРЫ'!$C$16)^INT((11-1)/12) -> 1 | N9: =(1+'⚙️ ПАРАМЕТРЫ'!$C$16)^INT((12-1)/12) -> 1 | O9: =(1+'⚙️ ПАРАМЕТРЫ'!$C$16)^INT((13-1)/12) -> 1.08 | P9: =(1+'⚙️ ПАРАМЕТРЫ'!$C$16)^INT((14-1)/12) -> 1.08 | Q9: =(1+'⚙️ ПАРАМЕТРЫ'!$C$16)^INT((15-1)/12) -> 1.08 | R9: =(1+'⚙️ ПАРАМЕТРЫ'!$C$16)^INT((16-1)/12) -> 1.08 | S9: =(1+'⚙️ ПАРАМЕТРЫ'!$C$16)^INT((17-1)/12) -> 1.08 | T9: =(1+'⚙️ ПАРАМЕТРЫ'!$C$16)^INT((18-1)/12) -> 1.08 | U9: =(1+'⚙️ ПАРАМЕТРЫ'!$C$16)^INT((19-1)/12) -> 1.08 | V9: =(1+'⚙️ ПАРАМЕТРЫ'!$C$16)^INT((20-1)/12) -> 1.08 | W9: =(1+'⚙️ ПАРАМЕТРЫ'!$C$16)^INT((21-1)/12) -> 1.08 | X9: =(1+'⚙️ ПАРАМЕТРЫ'!$C$16)^INT((22-1)/12) -> 1.08 | Y9: =(1+'⚙️ ПАРАМЕТРЫ'!$C$16)^INT((23-1)/12) -> 1.08 | Z9: =(1+'⚙️ ПАРАМЕТРЫ'!$C$16)^INT((24-1)/12) -> 1.08 | AA9: =(1+'⚙️ ПАРАМЕТРЫ'!$C$16)^INT((25-1)/12) -> 1.1664 | AB9: =(1+'⚙️ ПАРАМЕТРЫ'!$C$16)^INT((26-1)/12) -> 1.1664 | AC9: =(1+'⚙️ ПАРАМЕТРЫ'!$C$16)^INT((27-1)/12) -> 1.1664 | AD9: =(1+'⚙️ ПАРАМЕТРЫ'!$C$16)^INT((28-1)/12) -> 1.1664 | AE9: =(1+'⚙️ ПАРАМЕТРЫ'!$C$16)^INT((29-1)/12) -> 1.1664 | AF9: =(1+'⚙️ ПАРАМЕТРЫ'!$C$16)^INT((30-1)/12) -> 1.1664 | AG9: =(1+'⚙️ ПАРАМЕТРЫ'!$C$16)^INT((31-1)/12) -> 1.1664 | AH9: =(1+'⚙️ ПАРАМЕТРЫ'!$C$16)^INT((32-1)/12) -> 1.1664 | AI9: =(1+'⚙️ ПАРАМЕТРЫ'!$C$16)^INT((33-1)/12) -> 1.1664 | AJ9: =(1+'⚙️ ПАРАМЕТРЫ'!$C$16)^INT((34-1)/12) -> 1.1664 | AK9: =(1+'⚙️ ПАРАМЕТРЫ'!$C$16)^INT((35-1)/12) -> 1.1664 | AL9: =(1+'⚙️ ПАРАМЕТРЫ'!$C$16)^INT((36-1)/12) -> 1.1664
B10: Клиентов/день | C10: =ROUND('⚙️ ПАРАМЕТРЫ'!$C$13*C5*C6*C8,0) -> 28 | D10: =ROUND('⚙️ ПАРАМЕТРЫ'!$C$13*D5*D6*D8,0) -> 51 | E10: =ROUND('⚙️ ПАРАМЕТРЫ'!$C$13*E5*E6*E8,0) -> 77 | F10: =ROUND('⚙️ ПАРАМЕТРЫ'!$C$13*F5*F6*F8,0) -> 77 | G10: =ROUND('⚙️ ПАРАМЕТРЫ'!$C$13*G5*G6*G8,0) -> 74 | H10: =ROUND('⚙️ ПАРАМЕТРЫ'!$C$13*H5*H6*H8,0) -> 70 | I10: =ROUND('⚙️ ПАРАМЕТРЫ'!$C$13*I5*I6*I8,0) -> 67 | J10: =ROUND('⚙️ ПАРАМЕТРЫ'!$C$13*J5*J6*J8,0) -> 67 | ... AL10: =ROUND('⚙️ ПАРАМЕТРЫ'!$C$13*AL5*AL6*AL8,0) -> 72
B11: Средний чек | C11: =ROUND('⚙️ ПАРАМЕТРЫ'!$C$12*C9,0) -> 1400 | D11: =ROUND('⚙️ ПАРАМЕТРЫ'!$C$12*D9,0) -> 1400 | E11: =ROUND('⚙️ ПАРАМЕТРЫ'!$C$12*E9,0) -> 1400 | F11: =ROUND('⚙️ ПАРАМЕТРЫ'!$C$12*F9,0) -> 1400 | G11: =ROUND('⚙️ ПАРАМЕТРЫ'!$C$12*G9,0) -> 1400 | H11: =ROUND('⚙️ ПАРАМЕТРЫ'!$C$12*H9,0) -> 1400 | I11: =ROUND('⚙️ ПАРАМЕТРЫ'!$C$12*I9,0) -> 1400 | J11: =ROUND('⚙️ ПАРАМЕТРЫ'!$C$12*J9,0) -> 1400 | ... AL11: =ROUND('⚙️ ПАРАМЕТРЫ'!$C$12*AL9,0) -> 1633
B12: ВЫРУЧКА | C12: =C10*C11*'⚙️ ПАРАМЕТРЫ'!$C$14 -> 1176000 | D12: =D10*D11*'⚙️ ПАРАМЕТРЫ'!$C$14 -> 2142000 | E12: =E10*E11*'⚙️ ПАРАМЕТРЫ'!$C$14 -> 3234000 | F12: =F10*F11*'⚙️ ПАРАМЕТРЫ'!$C$14 -> 3234000 | G12: =G10*G11*'⚙️ ПАРАМЕТРЫ'!$C$14 -> 3108000 | H12: =H10*H11*'⚙️ ПАРАМЕТРЫ'!$C$14 -> 2940000 | I12: =I10*I11*'⚙️ ПАРАМЕТРЫ'!$C$14 -> 2814000 | J12: =J10*J11*'⚙️ ПАРАМЕТРЫ'!$C$14 -> 2814000 | ... AL12: =AL10*AL11*'⚙️ ПАРАМЕТРЫ'!$C$14 -> 3527280
B13: ПРЯМЫЕ РАСХОДЫ
B14: Себестоимость | C14: =ROUND(C12*'⚙️ ПАРАМЕТРЫ'!$C$19,0) -> 411600 | D14: =ROUND(D12*'⚙️ ПАРАМЕТРЫ'!$C$19,0) -> 749700 | E14: =ROUND(E12*'⚙️ ПАРАМЕТРЫ'!$C$19,0) -> 1131900 | F14: =ROUND(F12*'⚙️ ПАРАМЕТРЫ'!$C$19,0) -> 1131900 | G14: =ROUND(G12*'⚙️ ПАРАМЕТРЫ'!$C$19,0) -> 1087800 | H14: =ROUND(H12*'⚙️ ПАРАМЕТРЫ'!$C$19,0) -> 1029000 | I14: =ROUND(I12*'⚙️ ПАРАМЕТРЫ'!$C$19,0) -> 984900 | J14: =ROUND(J12*'⚙️ ПАРАМЕТРЫ'!$C$19,0) -> 984900 | ... AL14: =ROUND(AL12*'⚙️ ПАРАМЕТРЫ'!$C$19,0) -> 1234548
B15: Потери/списания | C15: =ROUND(C12*'⚙️ ПАРАМЕТРЫ'!$C$20,0) -> 35280 | D15: =ROUND(D12*'⚙️ ПАРАМЕТРЫ'!$C$20,0) -> 64260 | E15: =ROUND(E12*'⚙️ ПАРАМЕТРЫ'!$C$20,0) -> 97020 | F15: =ROUND(F12*'⚙️ ПАРАМЕТРЫ'!$C$20,0) -> 97020 | G15: =ROUND(G12*'⚙️ ПАРАМЕТРЫ'!$C$20,0) -> 93240 | H15: =ROUND(H12*'⚙️ ПАРАМЕТРЫ'!$C$20,0) -> 88200 | I15: =ROUND(I12*'⚙️ ПАРАМЕТРЫ'!$C$20,0) -> 84420 | J15: =ROUND(J12*'⚙️ ПАРАМЕТРЫ'!$C$20,0) -> 84420 | ... AL15: =ROUND(AL12*'⚙️ ПАРАМЕТРЫ'!$C$20,0) -> 105818
B16: ВАЛОВАЯ ПРИБЫЛЬ | C16: =C12-C14-C15 -> 729120 | D16: =D12-D14-D15 -> 1328040 | E16: =E12-E14-E15 -> 2005080 | F16: =F12-F14-F15 -> 2005080 | G16: =G12-G14-G15 -> 1926960 | H16: =H12-H14-H15 -> 1822800 | I16: =I12-I14-I15 -> 1744680 | J16: =J12-J14-J15 -> 1744680 | ... AL16: =AL12-AL14-AL15 -> 2186914
B17: ПОСТОЯННЫЕ РАСХОДЫ
B18: ФОТ (Gross оклад) | C18: =ROUND('⚙️ ПАРАМЕТРЫ'!$C$25*'⚙️ ПАРАМЕТРЫ'!$C$26*(1+'📊 ДОПУЩЕНИЯ'!$C$10)^INT((1-1)/12),0) -> 400000 | D18: =ROUND('⚙️ ПАРАМЕТРЫ'!$C$25*'⚙️ ПАРАМЕТРЫ'!$C$26*(1+'📊 ДОПУЩЕНИЯ'!$C$10)^INT((2-1)/12),0) -> 400000 | E18: =ROUND('⚙️ ПАРАМЕТРЫ'!$C$25*'⚙️ ПАРАМЕТРЫ'!$C$26*(1+'📊 ДОПУЩЕНИЯ'!$C$10)^INT((3-1)/12),0) -> 400000 | F18: =ROUND('⚙️ ПАРАМЕТРЫ'!$C$25*'⚙️ ПАРАМЕТРЫ'!$C$26*(1+'📊 ДОПУЩЕНИЯ'!$C$10)^INT((4-1)/12),0) -> 400000 | G18: =ROUND('⚙️ ПАРАМЕТРЫ'!$C$25*'⚙️ ПАРАМЕТРЫ'!$C$26*(1+'📊 ДОПУЩЕНИЯ'!$C$10)^INT((5-1)/12),0) -> 400000 | H18: =ROUND('⚙️ ПАРАМЕТРЫ'!$C$25*'⚙️ ПАРАМЕТРЫ'!$C$26*(1+'📊 ДОПУЩЕНИЯ'!$C$10)^INT((6-1)/12),0) -> 400000 | I18: =ROUND('⚙️ ПАРАМЕТРЫ'!$C$25*'⚙️ ПАРАМЕТРЫ'!$C$26*(1+'📊 ДОПУЩЕНИЯ'!$C$10)^INT((7-1)/12),0) -> 400000 | J18: =ROUND('⚙️ ПАРАМЕТРЫ'!$C$25*'⚙️ ПАРАМЕТРЫ'!$C$26*(1+'📊 ДОПУЩЕНИЯ'!$C$10)^INT((8-1)/12),0) -> 400000 | K18: =ROUND('⚙️ ПАРАМЕТРЫ'!$C$25*'⚙️ ПАРАМЕТРЫ'!$C$26*(1+'📊 ДОПУЩЕНИЯ'!$C$10)^INT((9-1)/12),0) -> 400000 | L18: =ROUND('⚙️ ПАРАМЕТРЫ'!$C$25*'⚙️ ПАРАМЕТРЫ'!$C$26*(1+'📊 ДОПУЩЕНИЯ'!$C$10)^INT((10-1)/12),0) -> 400000 | M18: =ROUND('⚙️ ПАРАМЕТРЫ'!$C$25*'⚙️ ПАРАМЕТРЫ'!$C$26*(1+'📊 ДОПУЩЕНИЯ'!$C$10)^INT((11-1)/12),0) -> 400000 | N18: =ROUND('⚙️ ПАРАМЕТРЫ'!$C$25*'⚙️ ПАРАМЕТРЫ'!$C$26*(1+'📊 ДОПУЩЕНИЯ'!$C$10)^INT((12-1)/12),0) -> 400000 | O18: =ROUND('⚙️ ПАРАМЕТРЫ'!$C$25*'⚙️ ПАРАМЕТРЫ'!$C$26*(1+'📊 ДОПУЩЕНИЯ'!$C$10)^INT((13-1)/12),0) -> 432000 | P18: =ROUND('⚙️ ПАРАМЕТРЫ'!$C$25*'⚙️ ПАРАМЕТРЫ'!$C$26*(1+'📊 ДОПУЩЕНИЯ'!$C$10)^INT((14-1)/12),0) -> 432000 | Q18: =ROUND('⚙️ ПАРАМЕТРЫ'!$C$25*'⚙️ ПАРАМЕТРЫ'!$C$26*(1+'📊 ДОПУЩЕНИЯ'!$C$10)^INT((15-1)/12),0) -> 432000 | R18: =ROUND('⚙️ ПАРАМЕТРЫ'!$C$25*'⚙️ ПАРАМЕТРЫ'!$C$26*(1+'📊 ДОПУЩЕНИЯ'!$C$10)^INT((16-1)/12),0) -> 432000 | S18: =ROUND('⚙️ ПАРАМЕТРЫ'!$C$25*'⚙️ ПАРАМЕТРЫ'!$C$26*(1+'📊 ДОПУЩЕНИЯ'!$C$10)^INT((17-1)/12),0) -> 432000 | T18: =ROUND('⚙️ ПАРАМЕТРЫ'!$C$25*'⚙️ ПАРАМЕТРЫ'!$C$26*(1+'📊 ДОПУЩЕНИЯ'!$C$10)^INT((18-1)/12),0) -> 432000 | U18: =ROUND('⚙️ ПАРАМЕТРЫ'!$C$25*'⚙️ ПАРАМЕТРЫ'!$C$26*(1+'📊 ДОПУЩЕНИЯ'!$C$10)^INT((19-1)/12),0) -> 432000 | V18: =ROUND('⚙️ ПАРАМЕТРЫ'!$C$25*'⚙️ ПАРАМЕТРЫ'!$C$26*(1+'📊 ДОПУЩЕНИЯ'!$C$10)^INT((20-1)/12),0) -> 432000 | W18: =ROUND('⚙️ ПАРАМЕТРЫ'!$C$25*'⚙️ ПАРАМЕТРЫ'!$C$26*(1+'📊 ДОПУЩЕНИЯ'!$C$10)^INT((21-1)/12),0) -> 432000 | X18: =ROUND('⚙️ ПАРАМЕТРЫ'!$C$25*'⚙️ ПАРАМЕТРЫ'!$C$26*(1+'📊 ДОПУЩЕНИЯ'!$C$10)^INT((22-1)/12),0) -> 432000 | Y18: =ROUND('⚙️ ПАРАМЕТРЫ'!$C$25*'⚙️ ПАРАМЕТРЫ'!$C$26*(1+'📊 ДОПУЩЕНИЯ'!$C$10)^INT((23-1)/12),0) -> 432000 | Z18: =ROUND('⚙️ ПАРАМЕТРЫ'!$C$25*'⚙️ ПАРАМЕТРЫ'!$C$26*(1+'📊 ДОПУЩЕНИЯ'!$C$10)^INT((24-1)/12),0) -> 432000 | AA18: =ROUND('⚙️ ПАРАМЕТРЫ'!$C$25*'⚙️ ПАРАМЕТРЫ'!$C$26*(1+'📊 ДОПУЩЕНИЯ'!$C$10)^INT((25-1)/12),0) -> 466560 | AB18: =ROUND('⚙️ ПАРАМЕТРЫ'!$C$25*'⚙️ ПАРАМЕТРЫ'!$C$26*(1+'📊 ДОПУЩЕНИЯ'!$C$10)^INT((26-1)/12),0) -> 466560 | AC18: =ROUND('⚙️ ПАРАМЕТРЫ'!$C$25*'⚙️ ПАРАМЕТРЫ'!$C$26*(1+'📊 ДОПУЩЕНИЯ'!$C$10)^INT((27-1)/12),0) -> 466560 | AD18: =ROUND('⚙️ ПАРАМЕТРЫ'!$C$25*'⚙️ ПАРАМЕТРЫ'!$C$26*(1+'📊 ДОПУЩЕНИЯ'!$C$10)^INT((28-1)/12),0) -> 466560 | AE18: =ROUND('⚙️ ПАРАМЕТРЫ'!$C$25*'⚙️ ПАРАМЕТРЫ'!$C$26*(1+'📊 ДОПУЩЕНИЯ'!$C$10)^INT((29-1)/12),0) -> 466560 | AF18: =ROUND('⚙️ ПАРАМЕТРЫ'!$C$25*'⚙️ ПАРАМЕТРЫ'!$C$26*(1+'📊 ДОПУЩЕНИЯ'!$C$10)^INT((30-1)/12),0) -> 466560 | AG18: =ROUND('⚙️ ПАРАМЕТРЫ'!$C$25*'⚙️ ПАРАМЕТРЫ'!$C$26*(1+'📊 ДОПУЩЕНИЯ'!$C$10)^INT((31-1)/12),0) -> 466560 | AH18: =ROUND('⚙️ ПАРАМЕТРЫ'!$C$25*'⚙️ ПАРАМЕТРЫ'!$C$26*(1+'📊 ДОПУЩЕНИЯ'!$C$10)^INT((32-1)/12),0) -> 466560 | AI18: =ROUND('⚙️ ПАРАМЕТРЫ'!$C$25*'⚙️ ПАРАМЕТРЫ'!$C$26*(1+'📊 ДОПУЩЕНИЯ'!$C$10)^INT((33-1)/12),0) -> 466560 | AJ18: =ROUND('⚙️ ПАРАМЕТРЫ'!$C$25*'⚙️ ПАРАМЕТРЫ'!$C$26*(1+'📊 ДОПУЩЕНИЯ'!$C$10)^INT((34-1)/12),0) -> 466560 | AK18: =ROUND('⚙️ ПАРАМЕТРЫ'!$C$25*'⚙️ ПАРАМЕТРЫ'!$C$26*(1+'📊 ДОПУЩЕНИЯ'!$C$10)^INT((35-1)/12),0) -> 466560 | AL18: =ROUND('⚙️ ПАРАМЕТРЫ'!$C$25*'⚙️ ПАРАМЕТРЫ'!$C$26*(1+'📊 ДОПУЩЕНИЯ'!$C$10)^INT((36-1)/12),0) -> 466560
B19: ОСМС (3%) | C19: =ROUND(C18*'📊 ДОПУЩЕНИЯ'!$C$37,0) -> 12000 | D19: =ROUND(D18*'📊 ДОПУЩЕНИЯ'!$C$37,0) -> 12000 | E19: =ROUND(E18*'📊 ДОПУЩЕНИЯ'!$C$37,0) -> 12000 | F19: =ROUND(F18*'📊 ДОПУЩЕНИЯ'!$C$37,0) -> 12000 | G19: =ROUND(G18*'📊 ДОПУЩЕНИЯ'!$C$37,0) -> 12000 | H19: =ROUND(H18*'📊 ДОПУЩЕНИЯ'!$C$37,0) -> 12000 | I19: =ROUND(I18*'📊 ДОПУЩЕНИЯ'!$C$37,0) -> 12000 | J19: =ROUND(J18*'📊 ДОПУЩЕНИЯ'!$C$37,0) -> 12000 | ... AL19: =ROUND(AL18*'📊 ДОПУЩЕНИЯ'!$C$37,0) -> 13997
B20: ОПВР (3.5%) | C20: =ROUND(C18*'📊 ДОПУЩЕНИЯ'!$C$38,0) -> 14000 | D20: =ROUND(D18*'📊 ДОПУЩЕНИЯ'!$C$38,0) -> 14000 | E20: =ROUND(E18*'📊 ДОПУЩЕНИЯ'!$C$38,0) -> 14000 | F20: =ROUND(F18*'📊 ДОПУЩЕНИЯ'!$C$38,0) -> 14000 | G20: =ROUND(G18*'📊 ДОПУЩЕНИЯ'!$C$38,0) -> 14000 | H20: =ROUND(H18*'📊 ДОПУЩЕНИЯ'!$C$38,0) -> 14000 | I20: =ROUND(I18*'📊 ДОПУЩЕНИЯ'!$C$38,0) -> 14000 | J20: =ROUND(J18*'📊 ДОПУЩЕНИЯ'!$C$38,0) -> 14000 | ... AL20: =ROUND(AL18*'📊 ДОПУЩЕНИЯ'!$C$38,0) -> 16330
B21: СО (3.5%) | C21: =ROUND(C18*'📊 ДОПУЩЕНИЯ'!$C$39,0) -> 14000 | D21: =ROUND(D18*'📊 ДОПУЩЕНИЯ'!$C$39,0) -> 14000 | E21: =ROUND(E18*'📊 ДОПУЩЕНИЯ'!$C$39,0) -> 14000 | F21: =ROUND(F18*'📊 ДОПУЩЕНИЯ'!$C$39,0) -> 14000 | G21: =ROUND(G18*'📊 ДОПУЩЕНИЯ'!$C$39,0) -> 14000 | H21: =ROUND(H18*'📊 ДОПУЩЕНИЯ'!$C$39,0) -> 14000 | I21: =ROUND(I18*'📊 ДОПУЩЕНИЯ'!$C$39,0) -> 14000 | J21: =ROUND(J18*'📊 ДОПУЩЕНИЯ'!$C$39,0) -> 14000 | ... AL21: =ROUND(AL18*'📊 ДОПУЩЕНИЯ'!$C$39,0) -> 16330
B22: СН (9.5%−СО) | C22: =IF('📊 ДОПУЩЕНИЯ'!$C$55="УСН",0,ROUND(C18*MAX('📊 ДОПУЩЕНИЯ'!$C$40-'📊 ДОПУЩЕНИЯ'!$C$39,0),0)) -> 0 | D22: =IF('📊 ДОПУЩЕНИЯ'!$C$55="УСН",0,ROUND(D18*MAX('📊 ДОПУЩЕНИЯ'!$C$40-'📊 ДОПУЩЕНИЯ'!$C$39,0),0)) -> 0 | E22: =IF('📊 ДОПУЩЕНИЯ'!$C$55="УСН",0,ROUND(E18*MAX('📊 ДОПУЩЕНИЯ'!$C$40-'📊 ДОПУЩЕНИЯ'!$C$39,0),0)) -> 0 | F22: =IF('📊 ДОПУЩЕНИЯ'!$C$55="УСН",0,ROUND(F18*MAX('📊 ДОПУЩЕНИЯ'!$C$40-'📊 ДОПУЩЕНИЯ'!$C$39,0),0)) -> 0 | G22: =IF('📊 ДОПУЩЕНИЯ'!$C$55="УСН",0,ROUND(G18*MAX('📊 ДОПУЩЕНИЯ'!$C$40-'📊 ДОПУЩЕНИЯ'!$C$39,0),0)) -> 0 | H22: =IF('📊 ДОПУЩЕНИЯ'!$C$55="УСН",0,ROUND(H18*MAX('📊 ДОПУЩЕНИЯ'!$C$40-'📊 ДОПУЩЕНИЯ'!$C$39,0),0)) -> 0 | I22: =IF('📊 ДОПУЩЕНИЯ'!$C$55="УСН",0,ROUND(I18*MAX('📊 ДОПУЩЕНИЯ'!$C$40-'📊 ДОПУЩЕНИЯ'!$C$39,0),0)) -> 0 | J22: =IF('📊 ДОПУЩЕНИЯ'!$C$55="УСН",0,ROUND(J18*MAX('📊 ДОПУЩЕНИЯ'!$C$40-'📊 ДОПУЩЕНИЯ'!$C$39,0),0)) -> 0 | ... AL22: =IF('📊 ДОПУЩЕНИЯ'!$C$55="УСН",0,ROUND(AL18*MAX('📊 ДОПУЩЕНИЯ'!$C$40-'📊 ДОПУЩЕНИЯ'!$C$39,0),0)) -> 0
B23: Итого налоги работодателя | C23: =C19+C20+C21+C22 -> 40000 | D23: =D19+D20+D21+D22 -> 40000 | E23: =E19+E20+E21+E22 -> 40000 | F23: =F19+F20+F21+F22 -> 40000 | G23: =G19+G20+G21+G22 -> 40000 | H23: =H19+H20+H21+H22 -> 40000 | I23: =I19+I20+I21+I22 -> 40000 | J23: =J19+J20+J21+J22 -> 40000 | ... AL23: =AL19+AL20+AL21+AL22 -> 46657
B24: Аренда | C24: =ROUND('⚙️ ПАРАМЕТРЫ'!$C$23*(1+'📊 ДОПУЩЕНИЯ'!$C$9)^INT((1-1)/12),0) -> 70000 | D24: =ROUND('⚙️ ПАРАМЕТРЫ'!$C$23*(1+'📊 ДОПУЩЕНИЯ'!$C$9)^INT((2-1)/12),0) -> 70000 | E24: =ROUND('⚙️ ПАРАМЕТРЫ'!$C$23*(1+'📊 ДОПУЩЕНИЯ'!$C$9)^INT((3-1)/12),0) -> 70000 | F24: =ROUND('⚙️ ПАРАМЕТРЫ'!$C$23*(1+'📊 ДОПУЩЕНИЯ'!$C$9)^INT((4-1)/12),0) -> 70000 | G24: =ROUND('⚙️ ПАРАМЕТРЫ'!$C$23*(1+'📊 ДОПУЩЕНИЯ'!$C$9)^INT((5-1)/12),0) -> 70000 | H24: =ROUND('⚙️ ПАРАМЕТРЫ'!$C$23*(1+'📊 ДОПУЩЕНИЯ'!$C$9)^INT((6-1)/12),0) -> 70000 | I24: =ROUND('⚙️ ПАРАМЕТРЫ'!$C$23*(1+'📊 ДОПУЩЕНИЯ'!$C$9)^INT((7-1)/12),0) -> 70000 | J24: =ROUND('⚙️ ПАРАМЕТРЫ'!$C$23*(1+'📊 ДОПУЩЕНИЯ'!$C$9)^INT((8-1)/12),0) -> 70000 | K24: =ROUND('⚙️ ПАРАМЕТРЫ'!$C$23*(1+'📊 ДОПУЩЕНИЯ'!$C$9)^INT((9-1)/12),0) -> 70000 | L24: =ROUND('⚙️ ПАРАМЕТРЫ'!$C$23*(1+'📊 ДОПУЩЕНИЯ'!$C$9)^INT((10-1)/12),0) -> 70000 | M24: =ROUND('⚙️ ПАРАМЕТРЫ'!$C$23*(1+'📊 ДОПУЩЕНИЯ'!$C$9)^INT((11-1)/12),0) -> 70000 | N24: =ROUND('⚙️ ПАРАМЕТРЫ'!$C$23*(1+'📊 ДОПУЩЕНИЯ'!$C$9)^INT((12-1)/12),0) -> 70000 | O24: =ROUND('⚙️ ПАРАМЕТРЫ'!$C$23*(1+'📊 ДОПУЩЕНИЯ'!$C$9)^INT((13-1)/12),0) -> 77000 | P24: =ROUND('⚙️ ПАРАМЕТРЫ'!$C$23*(1+'📊 ДОПУЩЕНИЯ'!$C$9)^INT((14-1)/12),0) -> 77000 | Q24: =ROUND('⚙️ ПАРАМЕТРЫ'!$C$23*(1+'📊 ДОПУЩЕНИЯ'!$C$9)^INT((15-1)/12),0) -> 77000 | R24: =ROUND('⚙️ ПАРАМЕТРЫ'!$C$23*(1+'📊 ДОПУЩЕНИЯ'!$C$9)^INT((16-1)/12),0) -> 77000 | S24: =ROUND('⚙️ ПАРАМЕТРЫ'!$C$23*(1+'📊 ДОПУЩЕНИЯ'!$C$9)^INT((17-1)/12),0) -> 77000 | T24: =ROUND('⚙️ ПАРАМЕТРЫ'!$C$23*(1+'📊 ДОПУЩЕНИЯ'!$C$9)^INT((18-1)/12),0) -> 77000 | U24: =ROUND('⚙️ ПАРАМЕТРЫ'!$C$23*(1+'📊 ДОПУЩЕНИЯ'!$C$9)^INT((19-1)/12),0) -> 77000 | V24: =ROUND('⚙️ ПАРАМЕТРЫ'!$C$23*(1+'📊 ДОПУЩЕНИЯ'!$C$9)^INT((20-1)/12),0) -> 77000 | W24: =ROUND('⚙️ ПАРАМЕТРЫ'!$C$23*(1+'📊 ДОПУЩЕНИЯ'!$C$9)^INT((21-1)/12),0) -> 77000 | X24: =ROUND('⚙️ ПАРАМЕТРЫ'!$C$23*(1+'📊 ДОПУЩЕНИЯ'!$C$9)^INT((22-1)/12),0) -> 77000 | Y24: =ROUND('⚙️ ПАРАМЕТРЫ'!$C$23*(1+'📊 ДОПУЩЕНИЯ'!$C$9)^INT((23-1)/12),0) -> 77000 | Z24: =ROUND('⚙️ ПАРАМЕТРЫ'!$C$23*(1+'📊 ДОПУЩЕНИЯ'!$C$9)^INT((24-1)/12),0) -> 77000 | AA24: =ROUND('⚙️ ПАРАМЕТРЫ'!$C$23*(1+'📊 ДОПУЩЕНИЯ'!$C$9)^INT((25-1)/12),0) -> 84700 | AB24: =ROUND('⚙️ ПАРАМЕТРЫ'!$C$23*(1+'📊 ДОПУЩЕНИЯ'!$C$9)^INT((26-1)/12),0) -> 84700 | AC24: =ROUND('⚙️ ПАРАМЕТРЫ'!$C$23*(1+'📊 ДОПУЩЕНИЯ'!$C$9)^INT((27-1)/12),0) -> 84700 | AD24: =ROUND('⚙️ ПАРАМЕТРЫ'!$C$23*(1+'📊 ДОПУЩЕНИЯ'!$C$9)^INT((28-1)/12),0) -> 84700 | AE24: =ROUND('⚙️ ПАРАМЕТРЫ'!$C$23*(1+'📊 ДОПУЩЕНИЯ'!$C$9)^INT((29-1)/12),0) -> 84700 | AF24: =ROUND('⚙️ ПАРАМЕТРЫ'!$C$23*(1+'📊 ДОПУЩЕНИЯ'!$C$9)^INT((30-1)/12),0) -> 84700 | AG24: =ROUND('⚙️ ПАРАМЕТРЫ'!$C$23*(1+'📊 ДОПУЩЕНИЯ'!$C$9)^INT((31-1)/12),0) -> 84700 | AH24: =ROUND('⚙️ ПАРАМЕТРЫ'!$C$23*(1+'📊 ДОПУЩЕНИЯ'!$C$9)^INT((32-1)/12),0) -> 84700 | AI24: =ROUND('⚙️ ПАРАМЕТРЫ'!$C$23*(1+'📊 ДОПУЩЕНИЯ'!$C$9)^INT((33-1)/12),0) -> 84700 | AJ24: =ROUND('⚙️ ПАРАМЕТРЫ'!$C$23*(1+'📊 ДОПУЩЕНИЯ'!$C$9)^INT((34-1)/12),0) -> 84700 | AK24: =ROUND('⚙️ ПАРАМЕТРЫ'!$C$23*(1+'📊 ДОПУЩЕНИЯ'!$C$9)^INT((35-1)/12),0) -> 84700 | AL24: =ROUND('⚙️ ПАРАМЕТРЫ'!$C$23*(1+'📊 ДОПУЩЕНИЯ'!$C$9)^INT((36-1)/12),0) -> 84700
B25: Коммунальные | C25: =ROUND('⚙️ ПАРАМЕТРЫ'!$C$27*(1+'📊 ДОПУЩЕНИЯ'!$C$12)^INT((1-1)/12),0) -> 15000 | D25: =ROUND('⚙️ ПАРАМЕТРЫ'!$C$27*(1+'📊 ДОПУЩЕНИЯ'!$C$12)^INT((2-1)/12),0) -> 15000 | E25: =ROUND('⚙️ ПАРАМЕТРЫ'!$C$27*(1+'📊 ДОПУЩЕНИЯ'!$C$12)^INT((3-1)/12),0) -> 15000 | F25: =ROUND('⚙️ ПАРАМЕТРЫ'!$C$27*(1+'📊 ДОПУЩЕНИЯ'!$C$12)^INT((4-1)/12),0) -> 15000 | G25: =ROUND('⚙️ ПАРАМЕТРЫ'!$C$27*(1+'📊 ДОПУЩЕНИЯ'!$C$12)^INT((5-1)/12),0) -> 15000 | H25: =ROUND('⚙️ ПАРАМЕТРЫ'!$C$27*(1+'📊 ДОПУЩЕНИЯ'!$C$12)^INT((6-1)/12),0) -> 15000 | I25: =ROUND('⚙️ ПАРАМЕТРЫ'!$C$27*(1+'📊 ДОПУЩЕНИЯ'!$C$12)^INT((7-1)/12),0) -> 15000 | J25: =ROUND('⚙️ ПАРАМЕТРЫ'!$C$27*(1+'📊 ДОПУЩЕНИЯ'!$C$12)^INT((8-1)/12),0) -> 15000 | K25: =ROUND('⚙️ ПАРАМЕТРЫ'!$C$27*(1+'📊 ДОПУЩЕНИЯ'!$C$12)^INT((9-1)/12),0) -> 15000 | L25: =ROUND('⚙️ ПАРАМЕТРЫ'!$C$27*(1+'📊 ДОПУЩЕНИЯ'!$C$12)^INT((10-1)/12),0) -> 15000 | M25: =ROUND('⚙️ ПАРАМЕТРЫ'!$C$27*(1+'📊 ДОПУЩЕНИЯ'!$C$12)^INT((11-1)/12),0) -> 15000 | N25: =ROUND('⚙️ ПАРАМЕТРЫ'!$C$27*(1+'📊 ДОПУЩЕНИЯ'!$C$12)^INT((12-1)/12),0) -> 15000 | O25: =ROUND('⚙️ ПАРАМЕТРЫ'!$C$27*(1+'📊 ДОПУЩЕНИЯ'!$C$12)^INT((13-1)/12),0) -> 16200 | P25: =ROUND('⚙️ ПАРАМЕТРЫ'!$C$27*(1+'📊 ДОПУЩЕНИЯ'!$C$12)^INT((14-1)/12),0) -> 16200 | Q25: =ROUND('⚙️ ПАРАМЕТРЫ'!$C$27*(1+'📊 ДОПУЩЕНИЯ'!$C$12)^INT((15-1)/12),0) -> 16200 | R25: =ROUND('⚙️ ПАРАМЕТРЫ'!$C$27*(1+'📊 ДОПУЩЕНИЯ'!$C$12)^INT((16-1)/12),0) -> 16200 | S25: =ROUND('⚙️ ПАРАМЕТРЫ'!$C$27*(1+'📊 ДОПУЩЕНИЯ'!$C$12)^INT((17-1)/12),0) -> 16200 | T25: =ROUND('⚙️ ПАРАМЕТРЫ'!$C$27*(1+'📊 ДОПУЩЕНИЯ'!$C$12)^INT((18-1)/12),0) -> 16200 | U25: =ROUND('⚙️ ПАРАМЕТРЫ'!$C$27*(1+'📊 ДОПУЩЕНИЯ'!$C$12)^INT((19-1)/12),0) -> 16200 | V25: =ROUND('⚙️ ПАРАМЕТРЫ'!$C$27*(1+'📊 ДОПУЩЕНИЯ'!$C$12)^INT((20-1)/12),0) -> 16200 | W25: =ROUND('⚙️ ПАРАМЕТРЫ'!$C$27*(1+'📊 ДОПУЩЕНИЯ'!$C$12)^INT((21-1)/12),0) -> 16200 | X25: =ROUND('⚙️ ПАРАМЕТРЫ'!$C$27*(1+'📊 ДОПУЩЕНИЯ'!$C$12)^INT((22-1)/12),0) -> 16200 | Y25: =ROUND('⚙️ ПАРАМЕТРЫ'!$C$27*(1+'📊 ДОПУЩЕНИЯ'!$C$12)^INT((23-1)/12),0) -> 16200 | Z25: =ROUND('⚙️ ПАРАМЕТРЫ'!$C$27*(1+'📊 ДОПУЩЕНИЯ'!$C$12)^INT((24-1)/12),0) -> 16200 | AA25: =ROUND('⚙️ ПАРАМЕТРЫ'!$C$27*(1+'📊 ДОПУЩЕНИЯ'!$C$12)^INT((25-1)/12),0) -> 17496 | AB25: =ROUND('⚙️ ПАРАМЕТРЫ'!$C$27*(1+'📊 ДОПУЩЕНИЯ'!$C$12)^INT((26-1)/12),0) -> 17496 | AC25: =ROUND('⚙️ ПАРАМЕТРЫ'!$C$27*(1+'📊 ДОПУЩЕНИЯ'!$C$12)^INT((27-1)/12),0) -> 17496 | AD25: =ROUND('⚙️ ПАРАМЕТРЫ'!$C$27*(1+'📊 ДОПУЩЕНИЯ'!$C$12)^INT((28-1)/12),0) -> 17496 | AE25: =ROUND('⚙️ ПАРАМЕТРЫ'!$C$27*(1+'📊 ДОПУЩЕНИЯ'!$C$12)^INT((29-1)/12),0) -> 17496 | AF25: =ROUND('⚙️ ПАРАМЕТРЫ'!$C$27*(1+'📊 ДОПУЩЕНИЯ'!$C$12)^INT((30-1)/12),0) -> 17496 | AG25: =ROUND('⚙️ ПАРАМЕТРЫ'!$C$27*(1+'📊 ДОПУЩЕНИЯ'!$C$12)^INT((31-1)/12),0) -> 17496 | AH25: =ROUND('⚙️ ПАРАМЕТРЫ'!$C$27*(1+'📊 ДОПУЩЕНИЯ'!$C$12)^INT((32-1)/12),0) -> 17496 | AI25: =ROUND('⚙️ ПАРАМЕТРЫ'!$C$27*(1+'📊 ДОПУЩЕНИЯ'!$C$12)^INT((33-1)/12),0) -> 17496 | AJ25: =ROUND('⚙️ ПАРАМЕТРЫ'!$C$27*(1+'📊 ДОПУЩЕНИЯ'!$C$12)^INT((34-1)/12),0) -> 17496 | AK25: =ROUND('⚙️ ПАРАМЕТРЫ'!$C$27*(1+'📊 ДОПУЩЕНИЯ'!$C$12)^INT((35-1)/12),0) -> 17496 | AL25: =ROUND('⚙️ ПАРАМЕТРЫ'!$C$27*(1+'📊 ДОПУЩЕНИЯ'!$C$12)^INT((36-1)/12),0) -> 17496
B26: Маркетинг | C26: =ROUND('⚙️ ПАРАМЕТРЫ'!$C$28*(1+'📊 ДОПУЩЕНИЯ'!$C$13)^INT((1-1)/12),0) -> 50000 | D26: =ROUND('⚙️ ПАРАМЕТРЫ'!$C$28*(1+'📊 ДОПУЩЕНИЯ'!$C$13)^INT((2-1)/12),0) -> 50000 | E26: =ROUND('⚙️ ПАРАМЕТРЫ'!$C$28*(1+'📊 ДОПУЩЕНИЯ'!$C$13)^INT((3-1)/12),0) -> 50000 | F26: =ROUND('⚙️ ПАРАМЕТРЫ'!$C$28*(1+'📊 ДОПУЩЕНИЯ'!$C$13)^INT((4-1)/12),0) -> 50000 | G26: =ROUND('⚙️ ПАРАМЕТРЫ'!$C$28*(1+'📊 ДОПУЩЕНИЯ'!$C$13)^INT((5-1)/12),0) -> 50000 | H26: =ROUND('⚙️ ПАРАМЕТРЫ'!$C$28*(1+'📊 ДОПУЩЕНИЯ'!$C$13)^INT((6-1)/12),0) -> 50000 | I26: =ROUND('⚙️ ПАРАМЕТРЫ'!$C$28*(1+'📊 ДОПУЩЕНИЯ'!$C$13)^INT((7-1)/12),0) -> 50000 | J26: =ROUND('⚙️ ПАРАМЕТРЫ'!$C$28*(1+'📊 ДОПУЩЕНИЯ'!$C$13)^INT((8-1)/12),0) -> 50000 | K26: =ROUND('⚙️ ПАРАМЕТРЫ'!$C$28*(1+'📊 ДОПУЩЕНИЯ'!$C$13)^INT((9-1)/12),0) -> 50000 | L26: =ROUND('⚙️ ПАРАМЕТРЫ'!$C$28*(1+'📊 ДОПУЩЕНИЯ'!$C$13)^INT((10-1)/12),0) -> 50000 | M26: =ROUND('⚙️ ПАРАМЕТРЫ'!$C$28*(1+'📊 ДОПУЩЕНИЯ'!$C$13)^INT((11-1)/12),0) -> 50000 | N26: =ROUND('⚙️ ПАРАМЕТРЫ'!$C$28*(1+'📊 ДОПУЩЕНИЯ'!$C$13)^INT((12-1)/12),0) -> 50000 | O26: =ROUND('⚙️ ПАРАМЕТРЫ'!$C$28*(1+'📊 ДОПУЩЕНИЯ'!$C$13)^INT((13-1)/12),0) -> 52500 | P26: =ROUND('⚙️ ПАРАМЕТРЫ'!$C$28*(1+'📊 ДОПУЩЕНИЯ'!$C$13)^INT((14-1)/12),0) -> 52500 | Q26: =ROUND('⚙️ ПАРАМЕТРЫ'!$C$28*(1+'📊 ДОПУЩЕНИЯ'!$C$13)^INT((15-1)/12),0) -> 52500 | R26: =ROUND('⚙️ ПАРАМЕТРЫ'!$C$28*(1+'📊 ДОПУЩЕНИЯ'!$C$13)^INT((16-1)/12),0) -> 52500 | S26: =ROUND('⚙️ ПАРАМЕТРЫ'!$C$28*(1+'📊 ДОПУЩЕНИЯ'!$C$13)^INT((17-1)/12),0) -> 52500 | T26: =ROUND('⚙️ ПАРАМЕТРЫ'!$C$28*(1+'📊 ДОПУЩЕНИЯ'!$C$13)^INT((18-1)/12),0) -> 52500 | U26: =ROUND('⚙️ ПАРАМЕТРЫ'!$C$28*(1+'📊 ДОПУЩЕНИЯ'!$C$13)^INT((19-1)/12),0) -> 52500 | V26: =ROUND('⚙️ ПАРАМЕТРЫ'!$C$28*(1+'📊 ДОПУЩЕНИЯ'!$C$13)^INT((20-1)/12),0) -> 52500 | W26: =ROUND('⚙️ ПАРАМЕТРЫ'!$C$28*(1+'📊 ДОПУЩЕНИЯ'!$C$13)^INT((21-1)/12),0) -> 52500 | X26: =ROUND('⚙️ ПАРАМЕТРЫ'!$C$28*(1+'📊 ДОПУЩЕНИЯ'!$C$13)^INT((22-1)/12),0) -> 52500 | Y26: =ROUND('⚙️ ПАРАМЕТРЫ'!$C$28*(1+'📊 ДОПУЩЕНИЯ'!$C$13)^INT((23-1)/12),0) -> 52500 | Z26: =ROUND('⚙️ ПАРАМЕТРЫ'!$C$28*(1+'📊 ДОПУЩЕНИЯ'!$C$13)^INT((24-1)/12),0) -> 52500 | AA26: =ROUND('⚙️ ПАРАМЕТРЫ'!$C$28*(1+'📊 ДОПУЩЕНИЯ'!$C$13)^INT((25-1)/12),0) -> 55125 | AB26: =ROUND('⚙️ ПАРАМЕТРЫ'!$C$28*(1+'📊 ДОПУЩЕНИЯ'!$C$13)^INT((26-1)/12),0) -> 55125 | AC26: =ROUND('⚙️ ПАРАМЕТРЫ'!$C$28*(1+'📊 ДОПУЩЕНИЯ'!$C$13)^INT((27-1)/12),0) -> 55125 | AD26: =ROUND('⚙️ ПАРАМЕТРЫ'!$C$28*(1+'📊 ДОПУЩЕНИЯ'!$C$13)^INT((28-1)/12),0) -> 55125 | AE26: =ROUND('⚙️ ПАРАМЕТРЫ'!$C$28*(1+'📊 ДОПУЩЕНИЯ'!$C$13)^INT((29-1)/12),0) -> 55125 | AF26: =ROUND('⚙️ ПАРАМЕТРЫ'!$C$28*(1+'📊 ДОПУЩЕНИЯ'!$C$13)^INT((30-1)/12),0) -> 55125 | AG26: =ROUND('⚙️ ПАРАМЕТРЫ'!$C$28*(1+'📊 ДОПУЩЕНИЯ'!$C$13)^INT((31-1)/12),0) -> 55125 | AH26: =ROUND('⚙️ ПАРАМЕТРЫ'!$C$28*(1+'📊 ДОПУЩЕНИЯ'!$C$13)^INT((32-1)/12),0) -> 55125 | AI26: =ROUND('⚙️ ПАРАМЕТРЫ'!$C$28*(1+'📊 ДОПУЩЕНИЯ'!$C$13)^INT((33-1)/12),0) -> 55125 | AJ26: =ROUND('⚙️ ПАРАМЕТРЫ'!$C$28*(1+'📊 ДОПУЩЕНИЯ'!$C$13)^INT((34-1)/12),0) -> 55125 | AK26: =ROUND('⚙️ ПАРАМЕТРЫ'!$C$28*(1+'📊 ДОПУЩЕНИЯ'!$C$13)^INT((35-1)/12),0) -> 55125 | AL26: =ROUND('⚙️ ПАРАМЕТРЫ'!$C$28*(1+'📊 ДОПУЩЕНИЯ'!$C$13)^INT((36-1)/12),0) -> 55125
B27: Расходники | C27: =ROUND('⚙️ ПАРАМЕТРЫ'!$C$29*(1+'📊 ДОПУЩЕНИЯ'!$C$11)^INT((1-1)/12),0) -> 3500 | D27: =ROUND('⚙️ ПАРАМЕТРЫ'!$C$29*(1+'📊 ДОПУЩЕНИЯ'!$C$11)^INT((2-1)/12),0) -> 3500 | E27: =ROUND('⚙️ ПАРАМЕТРЫ'!$C$29*(1+'📊 ДОПУЩЕНИЯ'!$C$11)^INT((3-1)/12),0) -> 3500 | F27: =ROUND('⚙️ ПАРАМЕТРЫ'!$C$29*(1+'📊 ДОПУЩЕНИЯ'!$C$11)^INT((4-1)/12),0) -> 3500 | G27: =ROUND('⚙️ ПАРАМЕТРЫ'!$C$29*(1+'📊 ДОПУЩЕНИЯ'!$C$11)^INT((5-1)/12),0) -> 3500 | H27: =ROUND('⚙️ ПАРАМЕТРЫ'!$C$29*(1+'📊 ДОПУЩЕНИЯ'!$C$11)^INT((6-1)/12),0) -> 3500 | I27: =ROUND('⚙️ ПАРАМЕТРЫ'!$C$29*(1+'📊 ДОПУЩЕНИЯ'!$C$11)^INT((7-1)/12),0) -> 3500 | J27: =ROUND('⚙️ ПАРАМЕТРЫ'!$C$29*(1+'📊 ДОПУЩЕНИЯ'!$C$11)^INT((8-1)/12),0) -> 3500 | K27: =ROUND('⚙️ ПАРАМЕТРЫ'!$C$29*(1+'📊 ДОПУЩЕНИЯ'!$C$11)^INT((9-1)/12),0) -> 3500 | L27: =ROUND('⚙️ ПАРАМЕТРЫ'!$C$29*(1+'📊 ДОПУЩЕНИЯ'!$C$11)^INT((10-1)/12),0) -> 3500 | M27: =ROUND('⚙️ ПАРАМЕТРЫ'!$C$29*(1+'📊 ДОПУЩЕНИЯ'!$C$11)^INT((11-1)/12),0) -> 3500 | N27: =ROUND('⚙️ ПАРАМЕТРЫ'!$C$29*(1+'📊 ДОПУЩЕНИЯ'!$C$11)^INT((12-1)/12),0) -> 3500 | O27: =ROUND('⚙️ ПАРАМЕТРЫ'!$C$29*(1+'📊 ДОПУЩЕНИЯ'!$C$11)^INT((13-1)/12),0) -> 3920 | P27: =ROUND('⚙️ ПАРАМЕТРЫ'!$C$29*(1+'📊 ДОПУЩЕНИЯ'!$C$11)^INT((14-1)/12),0) -> 3920 | Q27: =ROUND('⚙️ ПАРАМЕТРЫ'!$C$29*(1+'📊 ДОПУЩЕНИЯ'!$C$11)^INT((15-1)/12),0) -> 3920 | R27: =ROUND('⚙️ ПАРАМЕТРЫ'!$C$29*(1+'📊 ДОПУЩЕНИЯ'!$C$11)^INT((16-1)/12),0) -> 3920 | S27: =ROUND('⚙️ ПАРАМЕТРЫ'!$C$29*(1+'📊 ДОПУЩЕНИЯ'!$C$11)^INT((17-1)/12),0) -> 3920 | T27: =ROUND('⚙️ ПАРАМЕТРЫ'!$C$29*(1+'📊 ДОПУЩЕНИЯ'!$C$11)^INT((18-1)/12),0) -> 3920 | U27: =ROUND('⚙️ ПАРАМЕТРЫ'!$C$29*(1+'📊 ДОПУЩЕНИЯ'!$C$11)^INT((19-1)/12),0) -> 3920 | V27: =ROUND('⚙️ ПАРАМЕТРЫ'!$C$29*(1+'📊 ДОПУЩЕНИЯ'!$C$11)^INT((20-1)/12),0) -> 3920 | W27: =ROUND('⚙️ ПАРАМЕТРЫ'!$C$29*(1+'📊 ДОПУЩЕНИЯ'!$C$11)^INT((21-1)/12),0) -> 3920 | X27: =ROUND('⚙️ ПАРАМЕТРЫ'!$C$29*(1+'📊 ДОПУЩЕНИЯ'!$C$11)^INT((22-1)/12),0) -> 3920 | Y27: =ROUND('⚙️ ПАРАМЕТРЫ'!$C$29*(1+'📊 ДОПУЩЕНИЯ'!$C$11)^INT((23-1)/12),0) -> 3920 | Z27: =ROUND('⚙️ ПАРАМЕТРЫ'!$C$29*(1+'📊 ДОПУЩЕНИЯ'!$C$11)^INT((24-1)/12),0) -> 3920 | AA27: =ROUND('⚙️ ПАРАМЕТРЫ'!$C$29*(1+'📊 ДОПУЩЕНИЯ'!$C$11)^INT((25-1)/12),0) -> 4390 | AB27: =ROUND('⚙️ ПАРАМЕТРЫ'!$C$29*(1+'📊 ДОПУЩЕНИЯ'!$C$11)^INT((26-1)/12),0) -> 4390 | AC27: =ROUND('⚙️ ПАРАМЕТРЫ'!$C$29*(1+'📊 ДОПУЩЕНИЯ'!$C$11)^INT((27-1)/12),0) -> 4390 | AD27: =ROUND('⚙️ ПАРАМЕТРЫ'!$C$29*(1+'📊 ДОПУЩЕНИЯ'!$C$11)^INT((28-1)/12),0) -> 4390 | AE27: =ROUND('⚙️ ПАРАМЕТРЫ'!$C$29*(1+'📊 ДОПУЩЕНИЯ'!$C$11)^INT((29-1)/12),0) -> 4390 | AF27: =ROUND('⚙️ ПАРАМЕТРЫ'!$C$29*(1+'📊 ДОПУЩЕНИЯ'!$C$11)^INT((30-1)/12),0) -> 4390 | AG27: =ROUND('⚙️ ПАРАМЕТРЫ'!$C$29*(1+'📊 ДОПУЩЕНИЯ'!$C$11)^INT((31-1)/12),0) -> 4390 | AH27: =ROUND('⚙️ ПАРАМЕТРЫ'!$C$29*(1+'📊 ДОПУЩЕНИЯ'!$C$11)^INT((32-1)/12),0) -> 4390 | AI27: =ROUND('⚙️ ПАРАМЕТРЫ'!$C$29*(1+'📊 ДОПУЩЕНИЯ'!$C$11)^INT((33-1)/12),0) -> 4390 | AJ27: =ROUND('⚙️ ПАРАМЕТРЫ'!$C$29*(1+'📊 ДОПУЩЕНИЯ'!$C$11)^INT((34-1)/12),0) -> 4390 | AK27: =ROUND('⚙️ ПАРАМЕТРЫ'!$C$29*(1+'📊 ДОПУЩЕНИЯ'!$C$11)^INT((35-1)/12),0) -> 4390 | AL27: =ROUND('⚙️ ПАРАМЕТРЫ'!$C$29*(1+'📊 ДОПУЩЕНИЯ'!$C$11)^INT((36-1)/12),0) -> 4390
B28: Софт/касса | C28: =ROUND('⚙️ ПАРАМЕТРЫ'!$C$30*(1+'📊 ДОПУЩЕНИЯ'!$C$12)^INT((1-1)/12),0) -> 5000 | D28: =ROUND('⚙️ ПАРАМЕТРЫ'!$C$30*(1+'📊 ДОПУЩЕНИЯ'!$C$12)^INT((2-1)/12),0) -> 5000 | E28: =ROUND('⚙️ ПАРАМЕТРЫ'!$C$30*(1+'📊 ДОПУЩЕНИЯ'!$C$12)^INT((3-1)/12),0) -> 5000 | F28: =ROUND('⚙️ ПАРАМЕТРЫ'!$C$30*(1+'📊 ДОПУЩЕНИЯ'!$C$12)^INT((4-1)/12),0) -> 5000 | G28: =ROUND('⚙️ ПАРАМЕТРЫ'!$C$30*(1+'📊 ДОПУЩЕНИЯ'!$C$12)^INT((5-1)/12),0) -> 5000 | H28: =ROUND('⚙️ ПАРАМЕТРЫ'!$C$30*(1+'📊 ДОПУЩЕНИЯ'!$C$12)^INT((6-1)/12),0) -> 5000 | I28: =ROUND('⚙️ ПАРАМЕТРЫ'!$C$30*(1+'📊 ДОПУЩЕНИЯ'!$C$12)^INT((7-1)/12),0) -> 5000 | J28: =ROUND('⚙️ ПАРАМЕТРЫ'!$C$30*(1+'📊 ДОПУЩЕНИЯ'!$C$12)^INT((8-1)/12),0) -> 5000 | K28: =ROUND('⚙️ ПАРАМЕТРЫ'!$C$30*(1+'📊 ДОПУЩЕНИЯ'!$C$12)^INT((9-1)/12),0) -> 5000 | L28: =ROUND('⚙️ ПАРАМЕТРЫ'!$C$30*(1+'📊 ДОПУЩЕНИЯ'!$C$12)^INT((10-1)/12),0) -> 5000 | M28: =ROUND('⚙️ ПАРАМЕТРЫ'!$C$30*(1+'📊 ДОПУЩЕНИЯ'!$C$12)^INT((11-1)/12),0) -> 5000 | N28: =ROUND('⚙️ ПАРАМЕТРЫ'!$C$30*(1+'📊 ДОПУЩЕНИЯ'!$C$12)^INT((12-1)/12),0) -> 5000 | O28: =ROUND('⚙️ ПАРАМЕТРЫ'!$C$30*(1+'📊 ДОПУЩЕНИЯ'!$C$12)^INT((13-1)/12),0) -> 5400 | P28: =ROUND('⚙️ ПАРАМЕТРЫ'!$C$30*(1+'📊 ДОПУЩЕНИЯ'!$C$12)^INT((14-1)/12),0) -> 5400 | Q28: =ROUND('⚙️ ПАРАМЕТРЫ'!$C$30*(1+'📊 ДОПУЩЕНИЯ'!$C$12)^INT((15-1)/12),0) -> 5400 | R28: =ROUND('⚙️ ПАРАМЕТРЫ'!$C$30*(1+'📊 ДОПУЩЕНИЯ'!$C$12)^INT((16-1)/12),0) -> 5400 | S28: =ROUND('⚙️ ПАРАМЕТРЫ'!$C$30*(1+'📊 ДОПУЩЕНИЯ'!$C$12)^INT((17-1)/12),0) -> 5400 | T28: =ROUND('⚙️ ПАРАМЕТРЫ'!$C$30*(1+'📊 ДОПУЩЕНИЯ'!$C$12)^INT((18-1)/12),0) -> 5400 | U28: =ROUND('⚙️ ПАРАМЕТРЫ'!$C$30*(1+'📊 ДОПУЩЕНИЯ'!$C$12)^INT((19-1)/12),0) -> 5400 | V28: =ROUND('⚙️ ПАРАМЕТРЫ'!$C$30*(1+'📊 ДОПУЩЕНИЯ'!$C$12)^INT((20-1)/12),0) -> 5400 | W28: =ROUND('⚙️ ПАРАМЕТРЫ'!$C$30*(1+'📊 ДОПУЩЕНИЯ'!$C$12)^INT((21-1)/12),0) -> 5400 | X28: =ROUND('⚙️ ПАРАМЕТРЫ'!$C$30*(1+'📊 ДОПУЩЕНИЯ'!$C$12)^INT((22-1)/12),0) -> 5400 | Y28: =ROUND('⚙️ ПАРАМЕТРЫ'!$C$30*(1+'📊 ДОПУЩЕНИЯ'!$C$12)^INT((23-1)/12),0) -> 5400 | Z28: =ROUND('⚙️ ПАРАМЕТРЫ'!$C$30*(1+'📊 ДОПУЩЕНИЯ'!$C$12)^INT((24-1)/12),0) -> 5400 | AA28: =ROUND('⚙️ ПАРАМЕТРЫ'!$C$30*(1+'📊 ДОПУЩЕНИЯ'!$C$12)^INT((25-1)/12),0) -> 5832 | AB28: =ROUND('⚙️ ПАРАМЕТРЫ'!$C$30*(1+'📊 ДОПУЩЕНИЯ'!$C$12)^INT((26-1)/12),0) -> 5832 | AC28: =ROUND('⚙️ ПАРАМЕТРЫ'!$C$30*(1+'📊 ДОПУЩЕНИЯ'!$C$12)^INT((27-1)/12),0) -> 5832 | AD28: =ROUND('⚙️ ПАРАМЕТРЫ'!$C$30*(1+'📊 ДОПУЩЕНИЯ'!$C$12)^INT((28-1)/12),0) -> 5832 | AE28: =ROUND('⚙️ ПАРАМЕТРЫ'!$C$30*(1+'📊 ДОПУЩЕНИЯ'!$C$12)^INT((29-1)/12),0) -> 5832 | AF28: =ROUND('⚙️ ПАРАМЕТРЫ'!$C$30*(1+'📊 ДОПУЩЕНИЯ'!$C$12)^INT((30-1)/12),0) -> 5832 | AG28: =ROUND('⚙️ ПАРАМЕТРЫ'!$C$30*(1+'📊 ДОПУЩЕНИЯ'!$C$12)^INT((31-1)/12),0) -> 5832 | AH28: =ROUND('⚙️ ПАРАМЕТРЫ'!$C$30*(1+'📊 ДОПУЩЕНИЯ'!$C$12)^INT((32-1)/12),0) -> 5832 | AI28: =ROUND('⚙️ ПАРАМЕТРЫ'!$C$30*(1+'📊 ДОПУЩЕНИЯ'!$C$12)^INT((33-1)/12),0) -> 5832 | AJ28: =ROUND('⚙️ ПАРАМЕТРЫ'!$C$30*(1+'📊 ДОПУЩЕНИЯ'!$C$12)^INT((34-1)/12),0) -> 5832 | AK28: =ROUND('⚙️ ПАРАМЕТРЫ'!$C$30*(1+'📊 ДОПУЩЕНИЯ'!$C$12)^INT((35-1)/12),0) -> 5832 | AL28: =ROUND('⚙️ ПАРАМЕТРЫ'!$C$30*(1+'📊 ДОПУЩЕНИЯ'!$C$12)^INT((36-1)/12),0) -> 5832
B29: Прочие | C29: =ROUND('⚙️ ПАРАМЕТРЫ'!$C$31*(1+'📊 ДОПУЩЕНИЯ'!$C$12)^INT((1-1)/12),0) -> 10000 | D29: =ROUND('⚙️ ПАРАМЕТРЫ'!$C$31*(1+'📊 ДОПУЩЕНИЯ'!$C$12)^INT((2-1)/12),0) -> 10000 | E29: =ROUND('⚙️ ПАРАМЕТРЫ'!$C$31*(1+'📊 ДОПУЩЕНИЯ'!$C$12)^INT((3-1)/12),0) -> 10000 | F29: =ROUND('⚙️ ПАРАМЕТРЫ'!$C$31*(1+'📊 ДОПУЩЕНИЯ'!$C$12)^INT((4-1)/12),0) -> 10000 | G29: =ROUND('⚙️ ПАРАМЕТРЫ'!$C$31*(1+'📊 ДОПУЩЕНИЯ'!$C$12)^INT((5-1)/12),0) -> 10000 | H29: =ROUND('⚙️ ПАРАМЕТРЫ'!$C$31*(1+'📊 ДОПУЩЕНИЯ'!$C$12)^INT((6-1)/12),0) -> 10000 | I29: =ROUND('⚙️ ПАРАМЕТРЫ'!$C$31*(1+'📊 ДОПУЩЕНИЯ'!$C$12)^INT((7-1)/12),0) -> 10000 | J29: =ROUND('⚙️ ПАРАМЕТРЫ'!$C$31*(1+'📊 ДОПУЩЕНИЯ'!$C$12)^INT((8-1)/12),0) -> 10000 | K29: =ROUND('⚙️ ПАРАМЕТРЫ'!$C$31*(1+'📊 ДОПУЩЕНИЯ'!$C$12)^INT((9-1)/12),0) -> 10000 | L29: =ROUND('⚙️ ПАРАМЕТРЫ'!$C$31*(1+'📊 ДОПУЩЕНИЯ'!$C$12)^INT((10-1)/12),0) -> 10000 | M29: =ROUND('⚙️ ПАРАМЕТРЫ'!$C$31*(1+'📊 ДОПУЩЕНИЯ'!$C$12)^INT((11-1)/12),0) -> 10000 | N29: =ROUND('⚙️ ПАРАМЕТРЫ'!$C$31*(1+'📊 ДОПУЩЕНИЯ'!$C$12)^INT((12-1)/12),0) -> 10000 | O29: =ROUND('⚙️ ПАРАМЕТРЫ'!$C$31*(1+'📊 ДОПУЩЕНИЯ'!$C$12)^INT((13-1)/12),0) -> 10800 | P29: =ROUND('⚙️ ПАРАМЕТРЫ'!$C$31*(1+'📊 ДОПУЩЕНИЯ'!$C$12)^INT((14-1)/12),0) -> 10800 | Q29: =ROUND('⚙️ ПАРАМЕТРЫ'!$C$31*(1+'📊 ДОПУЩЕНИЯ'!$C$12)^INT((15-1)/12),0) -> 10800 | R29: =ROUND('⚙️ ПАРАМЕТРЫ'!$C$31*(1+'📊 ДОПУЩЕНИЯ'!$C$12)^INT((16-1)/12),0) -> 10800 | S29: =ROUND('⚙️ ПАРАМЕТРЫ'!$C$31*(1+'📊 ДОПУЩЕНИЯ'!$C$12)^INT((17-1)/12),0) -> 10800 | T29: =ROUND('⚙️ ПАРАМЕТРЫ'!$C$31*(1+'📊 ДОПУЩЕНИЯ'!$C$12)^INT((18-1)/12),0) -> 10800 | U29: =ROUND('⚙️ ПАРАМЕТРЫ'!$C$31*(1+'📊 ДОПУЩЕНИЯ'!$C$12)^INT((19-1)/12),0) -> 10800 | V29: =ROUND('⚙️ ПАРАМЕТРЫ'!$C$31*(1+'📊 ДОПУЩЕНИЯ'!$C$12)^INT((20-1)/12),0) -> 10800 | W29: =ROUND('⚙️ ПАРАМЕТРЫ'!$C$31*(1+'📊 ДОПУЩЕНИЯ'!$C$12)^INT((21-1)/12),0) -> 10800 | X29: =ROUND('⚙️ ПАРАМЕТРЫ'!$C$31*(1+'📊 ДОПУЩЕНИЯ'!$C$12)^INT((22-1)/12),0) -> 10800 | Y29: =ROUND('⚙️ ПАРАМЕТРЫ'!$C$31*(1+'📊 ДОПУЩЕНИЯ'!$C$12)^INT((23-1)/12),0) -> 10800 | Z29: =ROUND('⚙️ ПАРАМЕТРЫ'!$C$31*(1+'📊 ДОПУЩЕНИЯ'!$C$12)^INT((24-1)/12),0) -> 10800 | AA29: =ROUND('⚙️ ПАРАМЕТРЫ'!$C$31*(1+'📊 ДОПУЩЕНИЯ'!$C$12)^INT((25-1)/12),0) -> 11664 | AB29: =ROUND('⚙️ ПАРАМЕТРЫ'!$C$31*(1+'📊 ДОПУЩЕНИЯ'!$C$12)^INT((26-1)/12),0) -> 11664 | AC29: =ROUND('⚙️ ПАРАМЕТРЫ'!$C$31*(1+'📊 ДОПУЩЕНИЯ'!$C$12)^INT((27-1)/12),0) -> 11664 | AD29: =ROUND('⚙️ ПАРАМЕТРЫ'!$C$31*(1+'📊 ДОПУЩЕНИЯ'!$C$12)^INT((28-1)/12),0) -> 11664 | AE29: =ROUND('⚙️ ПАРАМЕТРЫ'!$C$31*(1+'📊 ДОПУЩЕНИЯ'!$C$12)^INT((29-1)/12),0) -> 11664 | AF29: =ROUND('⚙️ ПАРАМЕТРЫ'!$C$31*(1+'📊 ДОПУЩЕНИЯ'!$C$12)^INT((30-1)/12),0) -> 11664 | AG29: =ROUND('⚙️ ПАРАМЕТРЫ'!$C$31*(1+'📊 ДОПУЩЕНИЯ'!$C$12)^INT((31-1)/12),0) -> 11664 | AH29: =ROUND('⚙️ ПАРАМЕТРЫ'!$C$31*(1+'📊 ДОПУЩЕНИЯ'!$C$12)^INT((32-1)/12),0) -> 11664 | AI29: =ROUND('⚙️ ПАРАМЕТРЫ'!$C$31*(1+'📊 ДОПУЩЕНИЯ'!$C$12)^INT((33-1)/12),0) -> 11664 | AJ29: =ROUND('⚙️ ПАРАМЕТРЫ'!$C$31*(1+'📊 ДОПУЩЕНИЯ'!$C$12)^INT((34-1)/12),0) -> 11664 | AK29: =ROUND('⚙️ ПАРАМЕТРЫ'!$C$31*(1+'📊 ДОПУЩЕНИЯ'!$C$12)^INT((35-1)/12),0) -> 11664 | AL29: =ROUND('⚙️ ПАРАМЕТРЫ'!$C$31*(1+'📊 ДОПУЩЕНИЯ'!$C$12)^INT((36-1)/12),0) -> 11664
B30: Итого постоянные | C30: =C18+C23+C24+C25+C26+C27+C28+C29 -> 593500 | D30: =D18+D23+D24+D25+D26+D27+D28+D29 -> 593500 | E30: =E18+E23+E24+E25+E26+E27+E28+E29 -> 593500 | F30: =F18+F23+F24+F25+F26+F27+F28+F29 -> 593500 | G30: =G18+G23+G24+G25+G26+G27+G28+G29 -> 593500 | H30: =H18+H23+H24+H25+H26+H27+H28+H29 -> 593500 | I30: =I18+I23+I24+I25+I26+I27+I28+I29 -> 593500 | J30: =J18+J23+J24+J25+J26+J27+J28+J29 -> 593500 | ... AL30: =AL18+AL23+AL24+AL25+AL26+AL27+AL28+AL29 -> 692424
B31: EBITDA | C31: =C16-C30 -> 135620 | D31: =D16-D30 -> 734540 | E31: =E16-E30 -> 1411580 | F31: =F16-F30 -> 1411580 | G31: =G16-G30 -> 1333460 | H31: =H16-H30 -> 1229300 | I31: =I16-I30 -> 1151180 | J31: =J16-J30 -> 1151180 | ... AL31: =AL16-AL30 -> 1494490
B32: Амортизация | C32: ='⚙️ ПАРАМЕТРЫ'!$C$42 -> 17857 | D32: ='⚙️ ПАРАМЕТРЫ'!$C$42 -> 17857 | E32: ='⚙️ ПАРАМЕТРЫ'!$C$42 -> 17857 | F32: ='⚙️ ПАРАМЕТРЫ'!$C$42 -> 17857 | G32: ='⚙️ ПАРАМЕТРЫ'!$C$42 -> 17857 | H32: ='⚙️ ПАРАМЕТРЫ'!$C$42 -> 17857 | I32: ='⚙️ ПАРАМЕТРЫ'!$C$42 -> 17857 | J32: ='⚙️ ПАРАМЕТРЫ'!$C$42 -> 17857 | ... AL32: ='⚙️ ПАРАМЕТРЫ'!$C$42 -> 17857
B33: EBIT | C33: =C31-C32 -> 117763 | D33: =D31-D32 -> 716683 | E33: =E31-E32 -> 1393723 | F33: =F31-F32 -> 1393723 | G33: =G31-G32 -> 1315603 | H33: =H31-H32 -> 1211443 | I33: =I31-I32 -> 1133323 | J33: =J31-J32 -> 1133323 | ... AL33: =AL31-AL32 -> 1476633
B34: Проценты по кредиту | C34: =IF(1<='⚙️ ПАРАМЕТРЫ'!$C$48,ABS(IPMT('⚙️ ПАРАМЕТРЫ'!$C$47/12,1,'⚙️ ПАРАМЕТРЫ'!$C$48,-'⚙️ ПАРАМЕТРЫ'!$C$46)),0) -> 18333.333 | D34: =IF(2<='⚙️ ПАРАМЕТРЫ'!$C$48,ABS(IPMT('⚙️ ПАРАМЕТРЫ'!$C$47/12,2,'⚙️ ПАРАМЕТРЫ'!$C$48,-'⚙️ ПАРАМЕТРЫ'!$C$46)),0) -> 17969.286 | E34: =IF(3<='⚙️ ПАРАМЕТРЫ'!$C$48,ABS(IPMT('⚙️ ПАРАМЕТРЫ'!$C$47/12,3,'⚙️ ПАРАМЕТРЫ'!$C$48,-'⚙️ ПАРАМЕТРЫ'!$C$46)),0) -> 17598.565 | F34: =IF(4<='⚙️ ПАРАМЕТРЫ'!$C$48,ABS(IPMT('⚙️ ПАРАМЕТРЫ'!$C$47/12,4,'⚙️ ПАРАМЕТРЫ'!$C$48,-'⚙️ ПАРАМЕТРЫ'!$C$46)),0) -> 17221.047 | G34: =IF(5<='⚙️ ПАРАМЕТРЫ'!$C$48,ABS(IPMT('⚙️ ПАРАМЕТРЫ'!$C$47/12,5,'⚙️ ПАРАМЕТРЫ'!$C$48,-'⚙️ ПАРАМЕТРЫ'!$C$46)),0) -> 16836.608 | H34: =IF(6<='⚙️ ПАРАМЕТРЫ'!$C$48,ABS(IPMT('⚙️ ПАРАМЕТРЫ'!$C$47/12,6,'⚙️ ПАРАМЕТРЫ'!$C$48,-'⚙️ ПАРАМЕТРЫ'!$C$46)),0) -> 16445.121 | I34: =IF(7<='⚙️ ПАРАМЕТРЫ'!$C$48,ABS(IPMT('⚙️ ПАРАМЕТРЫ'!$C$47/12,7,'⚙️ ПАРАМЕТРЫ'!$C$48,-'⚙️ ПАРАМЕТРЫ'!$C$46)),0) -> 16046.456 | J34: =IF(8<='⚙️ ПАРАМЕТРЫ'!$C$48,ABS(IPMT('⚙️ ПАРАМЕТРЫ'!$C$47/12,8,'⚙️ ПАРАМЕТРЫ'!$C$48,-'⚙️ ПАРАМЕТРЫ'!$C$46)),0) -> 15640.483 | K34: =IF(9<='⚙️ ПАРАМЕТРЫ'!$C$48,ABS(IPMT('⚙️ ПАРАМЕТРЫ'!$C$47/12,9,'⚙️ ПАРАМЕТРЫ'!$C$48,-'⚙️ ПАРАМЕТРЫ'!$C$46)),0) -> 15227.067 | L34: =IF(10<='⚙️ ПАРАМЕТРЫ'!$C$48,ABS(IPMT('⚙️ ПАРАМЕТРЫ'!$C$47/12,10,'⚙️ ПАРАМЕТРЫ'!$C$48,-'⚙️ ПАРАМЕТРЫ'!$C$46)),0) -> 14806.071 | M34: =IF(11<='⚙️ ПАРАМЕТРЫ'!$C$48,ABS(IPMT('⚙️ ПАРАМЕТРЫ'!$C$47/12,11,'⚙️ ПАРАМЕТРЫ'!$C$48,-'⚙️ ПАРАМЕТРЫ'!$C$46)),0) -> 14377.358 | N34: =IF(12<='⚙️ ПАРАМЕТРЫ'!$C$48,ABS(IPMT('⚙️ ПАРАМЕТРЫ'!$C$47/12,12,'⚙️ ПАРАМЕТРЫ'!$C$48,-'⚙️ ПАРАМЕТРЫ'!$C$46)),0) -> 13940.784 | O34: =IF(13<='⚙️ ПАРАМЕТРЫ'!$C$48,ABS(IPMT('⚙️ ПАРАМЕТРЫ'!$C$47/12,13,'⚙️ ПАРАМЕТРЫ'!$C$48,-'⚙️ ПАРАМЕТРЫ'!$C$46)),0) -> 13496.207 | P34: =IF(14<='⚙️ ПАРАМЕТРЫ'!$C$48,ABS(IPMT('⚙️ ПАРАМЕТРЫ'!$C$47/12,14,'⚙️ ПАРАМЕТРЫ'!$C$48,-'⚙️ ПАРАМЕТРЫ'!$C$46)),0) -> 13043.479 | Q34: =IF(15<='⚙️ ПАРАМЕТРЫ'!$C$48,ABS(IPMT('⚙️ ПАРАМЕТРЫ'!$C$47/12,15,'⚙️ ПАРАМЕТРЫ'!$C$48,-'⚙️ ПАРАМЕТРЫ'!$C$46)),0) -> 12582.451 | R34: =IF(16<='⚙️ ПАРАМЕТРЫ'!$C$48,ABS(IPMT('⚙️ ПАРАМЕТРЫ'!$C$47/12,16,'⚙️ ПАРАМЕТРЫ'!$C$48,-'⚙️ ПАРАМЕТРЫ'!$C$46)),0) -> 12112.971 | S34: =IF(17<='⚙️ ПАРАМЕТРЫ'!$C$48,ABS(IPMT('⚙️ ПАРАМЕТРЫ'!$C$47/12,17,'⚙️ ПАРАМЕТРЫ'!$C$48,-'⚙️ ПАРАМЕТРЫ'!$C$46)),0) -> 11634.884 | T34: =IF(18<='⚙️ ПАРАМЕТРЫ'!$C$48,ABS(IPMT('⚙️ ПАРАМЕТРЫ'!$C$47/12,18,'⚙️ ПАРАМЕТРЫ'!$C$48,-'⚙️ ПАРАМЕТРЫ'!$C$46)),0) -> 11148.032 | U34: =IF(19<='⚙️ ПАРАМЕТРЫ'!$C$48,ABS(IPMT('⚙️ ПАРАМЕТРЫ'!$C$47/12,19,'⚙️ ПАРАМЕТРЫ'!$C$48,-'⚙️ ПАРАМЕТРЫ'!$C$46)),0) -> 10652.254 | V34: =IF(20<='⚙️ ПАРАМЕТРЫ'!$C$48,ABS(IPMT('⚙️ ПАРАМЕТРЫ'!$C$47/12,20,'⚙️ ПАРАМЕТРЫ'!$C$48,-'⚙️ ПАРАМЕТРЫ'!$C$46)),0) -> 10147.387 | W34: =IF(21<='⚙️ ПАРАМЕТРЫ'!$C$48,ABS(IPMT('⚙️ ПАРАМЕТРЫ'!$C$47/12,21,'⚙️ ПАРАМЕТРЫ'!$C$48,-'⚙️ ПАРАМЕТРЫ'!$C$46)),0) -> 9633.2643 | X34: =IF(22<='⚙️ ПАРАМЕТРЫ'!$C$48,ABS(IPMT('⚙️ ПАРАМЕТРЫ'!$C$47/12,22,'⚙️ ПАРАМЕТРЫ'!$C$48,-'⚙️ ПАРАМЕТРЫ'!$C$46)),0) -> 9109.7158 | Y34: =IF(23<='⚙️ ПАРАМЕТРЫ'!$C$48,ABS(IPMT('⚙️ ПАРАМЕТРЫ'!$C$47/12,23,'⚙️ ПАРАМЕТРЫ'!$C$48,-'⚙️ ПАРАМЕТРЫ'!$C$46)),0) -> 8576.569 | Z34: =IF(24<='⚙️ ПАРАМЕТРЫ'!$C$48,ABS(IPMT('⚙️ ПАРАМЕТРЫ'!$C$47/12,24,'⚙️ ПАРАМЕТРЫ'!$C$48,-'⚙️ ПАРАМЕТРЫ'!$C$46)),0) -> 8033.6478 | AA34: =IF(25<='⚙️ ПАРАМЕТРЫ'!$C$48,ABS(IPMT('⚙️ ПАРАМЕТРЫ'!$C$47/12,25,'⚙️ ПАРАМЕТРЫ'!$C$48,-'⚙️ ПАРАМЕТРЫ'!$C$46)),0) -> 7480.773 | AB34: =IF(26<='⚙️ ПАРАМЕТРЫ'!$C$48,ABS(IPMT('⚙️ ПАРАМЕТРЫ'!$C$47/12,26,'⚙️ ПАРАМЕТРЫ'!$C$48,-'⚙️ ПАРАМЕТРЫ'!$C$46)),0) -> 6917.7622 | AC34: =IF(27<='⚙️ ПАРАМЕТРЫ'!$C$48,ABS(IPMT('⚙️ ПАРАМЕТРЫ'!$C$47/12,27,'⚙️ ПАРАМЕТРЫ'!$C$48,-'⚙️ ПАРАМЕТРЫ'!$C$46)),0) -> 6344.4295 | AD34: =IF(28<='⚙️ ПАРАМЕТРЫ'!$C$48,ABS(IPMT('⚙️ ПАРАМЕТРЫ'!$C$47/12,28,'⚙️ ПАРАМЕТРЫ'!$C$48,-'⚙️ ПАРАМЕТРЫ'!$C$46)),0) -> 5760.5858 | AE34: =IF(29<='⚙️ ПАРАМЕТРЫ'!$C$48,ABS(IPMT('⚙️ ПАРАМЕТРЫ'!$C$47/12,29,'⚙️ ПАРАМЕТРЫ'!$C$48,-'⚙️ ПАРАМЕТРЫ'!$C$46)),0) -> 5166.0382 | AF34: =IF(30<='⚙️ ПАРАМЕТРЫ'!$C$48,ABS(IPMT('⚙️ ПАРАМЕТРЫ'!$C$47/12,30,'⚙️ ПАРАМЕТРЫ'!$C$48,-'⚙️ ПАРАМЕТРЫ'!$C$46)),0) -> 4560.5906 | AG34: =IF(31<='⚙️ ПАРАМЕТРЫ'!$C$48,ABS(IPMT('⚙️ ПАРАМЕТРЫ'!$C$47/12,31,'⚙️ ПАРАМЕТРЫ'!$C$48,-'⚙️ ПАРАМЕТРЫ'!$C$46)),0) -> 3944.0431 | AH34: =IF(32<='⚙️ ПАРАМЕТРЫ'!$C$48,ABS(IPMT('⚙️ ПАРАМЕТРЫ'!$C$47/12,32,'⚙️ ПАРАМЕТРЫ'!$C$48,-'⚙️ ПАРАМЕТРЫ'!$C$46)),0) -> 3316.1923 | AI34: =IF(33<='⚙️ ПАРАМЕТРЫ'!$C$48,ABS(IPMT('⚙️ ПАРАМЕТРЫ'!$C$47/12,33,'⚙️ ПАРАМЕТРЫ'!$C$48,-'⚙️ ПАРАМЕТРЫ'!$C$46)),0) -> 2676.8308 | AJ34: =IF(34<='⚙️ ПАРАМЕТРЫ'!$C$48,ABS(IPMT('⚙️ ПАРАМЕТРЫ'!$C$47/12,34,'⚙️ ПАРАМЕТРЫ'!$C$48,-'⚙️ ПАРАМЕТРЫ'!$C$46)),0) -> 2025.7477 | AK34: =IF(35<='⚙️ ПАРАМЕТРЫ'!$C$48,ABS(IPMT('⚙️ ПАРАМЕТРЫ'!$C$47/12,35,'⚙️ ПАРАМЕТРЫ'!$C$48,-'⚙️ ПАРАМЕТРЫ'!$C$46)),0) -> 1362.7281 | AL34: =IF(36<='⚙️ ПАРАМЕТРЫ'!$C$48,ABS(IPMT('⚙️ ПАРАМЕТРЫ'!$C$47/12,36,'⚙️ ПАРАМЕТРЫ'!$C$48,-'⚙️ ПАРАМЕТРЫ'!$C$46)),0) -> 687.55317
B35: Налог (КПН/ИПН/УСН) | C35: =IF('📊 ДОПУЩЕНИЯ'!$C$55="УСН",ROUND(MAX(C12,0)*'📊 ДОПУЩЕНИЯ'!$C$58,0),IF('⚙️ ПАРАМЕТРЫ'!$C$5="ТОО",ROUND(MAX(C33-C34,0)*'📊 ДОПУЩЕНИЯ'!$C$45,0),ROUND(MAX(C33-C34,0)*'📊 ДОПУЩЕНИЯ'!$C$46,0))) -> 35280 | D35: =IF('📊 ДОПУЩЕНИЯ'!$C$55="УСН",ROUND(MAX(D12,0)*'📊 ДОПУЩЕНИЯ'!$C$58,0),IF('⚙️ ПАРАМЕТРЫ'!$C$5="ТОО",ROUND(MAX(D33-D34,0)*'📊 ДОПУЩЕНИЯ'!$C$45,0),ROUND(MAX(D33-D34,0)*'📊 ДОПУЩЕНИЯ'!$C$46,0))) -> 64260 | E35: =IF('📊 ДОПУЩЕНИЯ'!$C$55="УСН",ROUND(MAX(E12,0)*'📊 ДОПУЩЕНИЯ'!$C$58,0),IF('⚙️ ПАРАМЕТРЫ'!$C$5="ТОО",ROUND(MAX(E33-E34,0)*'📊 ДОПУЩЕНИЯ'!$C$45,0),ROUND(MAX(E33-E34,0)*'📊 ДОПУЩЕНИЯ'!$C$46,0))) -> 97020 | F35: =IF('📊 ДОПУЩЕНИЯ'!$C$55="УСН",ROUND(MAX(F12,0)*'📊 ДОПУЩЕНИЯ'!$C$58,0),IF('⚙️ ПАРАМЕТРЫ'!$C$5="ТОО",ROUND(MAX(F33-F34,0)*'📊 ДОПУЩЕНИЯ'!$C$45,0),ROUND(MAX(F33-F34,0)*'📊 ДОПУЩЕНИЯ'!$C$46,0))) -> 97020 | G35: =IF('📊 ДОПУЩЕНИЯ'!$C$55="УСН",ROUND(MAX(G12,0)*'📊 ДОПУЩЕНИЯ'!$C$58,0),IF('⚙️ ПАРАМЕТРЫ'!$C$5="ТОО",ROUND(MAX(G33-G34,0)*'📊 ДОПУЩЕНИЯ'!$C$45,0),ROUND(MAX(G33-G34,0)*'📊 ДОПУЩЕНИЯ'!$C$46,0))) -> 93240 | H35: =IF('📊 ДОПУЩЕНИЯ'!$C$55="УСН",ROUND(MAX(H12,0)*'📊 ДОПУЩЕНИЯ'!$C$58,0),IF('⚙️ ПАРАМЕТРЫ'!$C$5="ТОО",ROUND(MAX(H33-H34,0)*'📊 ДОПУЩЕНИЯ'!$C$45,0),ROUND(MAX(H33-H34,0)*'📊 ДОПУЩЕНИЯ'!$C$46,0))) -> 88200 | I35: =IF('📊 ДОПУЩЕНИЯ'!$C$55="УСН",ROUND(MAX(I12,0)*'📊 ДОПУЩЕНИЯ'!$C$58,0),IF('⚙️ ПАРАМЕТРЫ'!$C$5="ТОО",ROUND(MAX(I33-I34,0)*'📊 ДОПУЩЕНИЯ'!$C$45,0),ROUND(MAX(I33-I34,0)*'📊 ДОПУЩЕНИЯ'!$C$46,0))) -> 84420 | J35: =IF('📊 ДОПУЩЕНИЯ'!$C$55="УСН",ROUND(MAX(J12,0)*'📊 ДОПУЩЕНИЯ'!$C$58,0),IF('⚙️ ПАРАМЕТРЫ'!$C$5="ТОО",ROUND(MAX(J33-J34,0)*'📊 ДОПУЩЕНИЯ'!$C$45,0),ROUND(MAX(J33-J34,0)*'📊 ДОПУЩЕНИЯ'!$C$46,0))) -> 84420 | ... AL35: =IF('📊 ДОПУЩЕНИЯ'!$C$55="УСН",ROUND(MAX(AL12,0)*'📊 ДОПУЩЕНИЯ'!$C$58,0),IF('⚙️ ПАРАМЕТРЫ'!$C$5="ТОО",ROUND(MAX(AL33-AL34,0)*'📊 ДОПУЩЕНИЯ'!$C$45,0),ROUND(MAX(AL33-AL34,0)*'📊 ДОПУЩЕНИЯ'!$C$46,0))) -> 105818
B36: НДС к уплате | C36: =IF('📊 ДОПУЩЕНИЯ'!$C$57="Да",ROUND(MAX(C12-C14,0)*16/116,0),0) -> 0
B37: Налог на дивиденды (ТОО) | C37: =IF('⚙️ ПАРАМЕТРЫ'!$C$5="ТОО",ROUND(MAX(C33-C34-C35,0)*'📊 ДОПУЩЕНИЯ'!$C$48,0),0) -> 0 | D37: =IF('⚙️ ПАРАМЕТРЫ'!$C$5="ТОО",ROUND(MAX(D33-D34-D35,0)*'📊 ДОПУЩЕНИЯ'!$C$48,0),0) -> 0 | E37: =IF('⚙️ ПАРАМЕТРЫ'!$C$5="ТОО",ROUND(MAX(E33-E34-E35,0)*'📊 ДОПУЩЕНИЯ'!$C$48,0),0) -> 0 | F37: =IF('⚙️ ПАРАМЕТРЫ'!$C$5="ТОО",ROUND(MAX(F33-F34-F35,0)*'📊 ДОПУЩЕНИЯ'!$C$48,0),0) -> 0 | G37: =IF('⚙️ ПАРАМЕТРЫ'!$C$5="ТОО",ROUND(MAX(G33-G34-G35,0)*'📊 ДОПУЩЕНИЯ'!$C$48,0),0) -> 0 | H37: =IF('⚙️ ПАРАМЕТРЫ'!$C$5="ТОО",ROUND(MAX(H33-H34-H35,0)*'📊 ДОПУЩЕНИЯ'!$C$48,0),0) -> 0 | I37: =IF('⚙️ ПАРАМЕТРЫ'!$C$5="ТОО",ROUND(MAX(I33-I34-I35,0)*'📊 ДОПУЩЕНИЯ'!$C$48,0),0) -> 0 | J37: =IF('⚙️ ПАРАМЕТРЫ'!$C$5="ТОО",ROUND(MAX(J33-J34-J35,0)*'📊 ДОПУЩЕНИЯ'!$C$48,0),0) -> 0 | ... AL37: =IF('⚙️ ПАРАМЕТРЫ'!$C$5="ТОО",ROUND(MAX(AL33-AL34-AL35,0)*'📊 ДОПУЩЕНИЯ'!$C$48,0),0) -> 0
B38: ЧИСТАЯ ПРИБЫЛЬ | C38: =C33-C34-C35-C37 -> 64149.667 | D38: =D33-D34-D35-D37 -> 634453.71 | E38: =E33-E34-E35-E37 -> 1279104.4 | F38: =F33-F34-F35-F37 -> 1279482 | G38: =G33-G34-G35-G37 -> 1205526.4 | H38: =H33-H34-H35-H37 -> 1106797.9 | I38: =I33-I34-I35-I37 -> 1032856.5 | J38: =J33-J34-J35-J37 -> 1033262.5 | ... AL38: =AL33-AL34-AL35-AL37 -> 1370127.4
B39: Рентабельность | C39: =IFERROR(C38/C12,0) -> 0.054549036 | D39: =IFERROR(D38/D12,0) -> 0.29619688 | E39: =IFERROR(E38/E12,0) -> 0.39551776 | F39: =IFERROR(F38/F12,0) -> 0.39563449 | G39: =IFERROR(G38/G12,0) -> 0.3878785 | H39: =IFERROR(H38/H12,0) -> 0.37646186 | I39: =IFERROR(I38/I12,0) -> 0.36704213 | J39: =IFERROR(J38/J12,0) -> 0.3671864 | ... AL39: =IFERROR(AL38/AL12,0) -> 0.38843739
B41: 💡 IPMT = проценты (P&L). PPMT = тело (Cash Flow).

Sheet 💰 CASH FLOW
A1: ДВИЖЕНИЕ ДЕНЕЖНЫХ СРЕДСТВ — КОФЕЙНЯ: КОФЕ С СОБОЙ
A2: 📌 М0 = инвестиции. М1-36 = операционная деятельность.
B4: М0 | C4: М1 | D4: М2 | E4: М3 | F4: М4 | G4: М5 | H4: М6 | I4: М7 | J4: М8 | K4: М9 | L4: М10 | M4: М11 | N4: М12 | O4: М13 | P4: М14 | Q4: М15 | R4: М16 | S4: М17 | T4: М18 | U4: М19 | V4: М20 | W4: М21 | X4: М22 | Y4: М23 | Z4: М24 | AA4: М25 | AB4: М26 | AC4: М27 | AD4: М28 | AE4: М29 | AF4: М30 | AG4: М31 | AH4: М32 | AI4: М33 | AJ4: М34 | AK4: М35 | AL4: М36
B5: ИНВЕСТИЦИОННАЯ ДЕЯТЕЛЬНОСТЬ
B6: =-'⚙️ ПАРАМЕТРЫ'!C37 -> -1500000
B7: =-'⚙️ ПАРАМЕТРЫ'!C23*'⚙️ ПАРАМЕТРЫ'!C38 -> -140000
B8: =-'⚙️ ПАРАМЕТРЫ'!C39 -> -1000000
B9: =B6+B7+B8 -> -2640000
B10: ФИНАНСОВАЯ ДЕЯТЕЛЬНОСТЬ
B11: Получение кредита | C11: ='⚙️ ПАРАМЕТРЫ'!C46 -> 1000000 | D11: 💡 Кредит поступает в М1. Если кредит = 0 — строка нулевая.
B12: Погашение тела кредита (PPMT) | C12: =IF(1<='⚙️ ПАРАМЕТРЫ'!$C$48,-ABS(PPMT('⚙️ ПАРАМЕТРЫ'!$C$47/12,1,'⚙️ ПАРАМЕТРЫ'!$C$48,-'⚙️ ПАРАМЕТРЫ'!$C$46)),0) -> -19857.12 | D12: =IF(2<='⚙️ ПАРАМЕТРЫ'!$C$48,-ABS(PPMT('⚙️ ПАРАМЕТРЫ'!$C$47/12,2,'⚙️ ПАРАМЕТРЫ'!$C$48,-'⚙️ ПАРАМЕТРЫ'!$C$46)),0) -> -20221.167 | E12: =IF(3<='⚙️ ПАРАМЕТРЫ'!$C$48,-ABS(PPMT('⚙️ ПАРАМЕТРЫ'!$C$47/12,3,'⚙️ ПАРАМЕТРЫ'!$C$48,-'⚙️ ПАРАМЕТРЫ'!$C$46)),0) -> -20591.888 | F12: =IF(4<='⚙️ ПАРАМЕТРЫ'!$C$48,-ABS(PPMT('⚙️ ПАРАМЕТРЫ'!$C$47/12,4,'⚙️ ПАРАМЕТРЫ'!$C$48,-'⚙️ ПАРАМЕТРЫ'!$C$46)),0) -> -20969.406 | G12: =IF(5<='⚙️ ПАРАМЕТРЫ'!$C$48,-ABS(PPMT('⚙️ ПАРАМЕТРЫ'!$C$47/12,5,'⚙️ ПАРАМЕТРЫ'!$C$48,-'⚙️ ПАРАМЕТРЫ'!$C$46)),0) -> -21353.846 | H12: =IF(6<='⚙️ ПАРАМЕТРЫ'!$C$48,-ABS(PPMT('⚙️ ПАРАМЕТРЫ'!$C$47/12,6,'⚙️ ПАРАМЕТРЫ'!$C$48,-'⚙️ ПАРАМЕТРЫ'!$C$46)),0) -> -21745.333 | I12: =IF(7<='⚙️ ПАРАМЕТРЫ'!$C$48,-ABS(PPMT('⚙️ ПАРАМЕТРЫ'!$C$47/12,7,'⚙️ ПАРАМЕТРЫ'!$C$48,-'⚙️ ПАРАМЕТРЫ'!$C$46)),0) -> -22143.997 | J12: =IF(8<='⚙️ ПАРАМЕТРЫ'!$C$48,-ABS(PPMT('⚙️ ПАРАМЕТРЫ'!$C$47/12,8,'⚙️ ПАРАМЕТРЫ'!$C$48,-'⚙️ ПАРАМЕТРЫ'!$C$46)),0) -> -22549.97 | K12: =IF(9<='⚙️ ПАРАМЕТРЫ'!$C$48,-ABS(PPMT('⚙️ ПАРАМЕТРЫ'!$C$47/12,9,'⚙️ ПАРАМЕТРЫ'!$C$48,-'⚙️ ПАРАМЕТРЫ'!$C$46)),0) -> -22963.387 | L12: =IF(10<='⚙️ ПАРАМЕТРЫ'!$C$48,-ABS(PPMT('⚙️ ПАРАМЕТРЫ'!$C$47/12,10,'⚙️ ПАРАМЕТРЫ'!$C$48,-'⚙️ ПАРАМЕТРЫ'!$C$46)),0) -> -23384.382 | M12: =IF(11<='⚙️ ПАРАМЕТРЫ'!$C$48,-ABS(PPMT('⚙️ ПАРАМЕТРЫ'!$C$47/12,11,'⚙️ ПАРАМЕТРЫ'!$C$48,-'⚙️ ПАРАМЕТРЫ'!$C$46)),0) -> -23813.096 | N12: =IF(12<='⚙️ ПАРАМЕТРЫ'!$C$48,-ABS(PPMT('⚙️ ПАРАМЕТРЫ'!$C$47/12,12,'⚙️ ПАРАМЕТРЫ'!$C$48,-'⚙️ ПАРАМЕТРЫ'!$C$46)),0) -> -24249.669 | O12: =IF(13<='⚙️ ПАРАМЕТРЫ'!$C$48,-ABS(PPMT('⚙️ ПАРАМЕТРЫ'!$C$47/12,13,'⚙️ ПАРАМЕТРЫ'!$C$48,-'⚙️ ПАРАМЕТРЫ'!$C$46)),0) -> -24694.246 | P12: =IF(14<='⚙️ ПАРАМЕТРЫ'!$C$48,-ABS(PPMT('⚙️ ПАРАМЕТРЫ'!$C$47/12,14,'⚙️ ПАРАМЕТРЫ'!$C$48,-'⚙️ ПАРАМЕТРЫ'!$C$46)),0) -> -25146.974 | Q12: =IF(15<='⚙️ ПАРАМЕТРЫ'!$C$48,-ABS(PPMT('⚙️ ПАРАМЕТРЫ'!$C$47/12,15,'⚙️ ПАРАМЕТРЫ'!$C$48,-'⚙️ ПАРАМЕТРЫ'!$C$46)),0) -> -25608.002 | R12: =IF(16<='⚙️ ПАРАМЕТРЫ'!$C$48,-ABS(PPMT('⚙️ ПАРАМЕТРЫ'!$C$47/12,16,'⚙️ ПАРАМЕТРЫ'!$C$48,-'⚙️ ПАРАМЕТРЫ'!$C$46)),0) -> -26077.482 | S12: =IF(17<='⚙️ ПАРАМЕТРЫ'!$C$48,-ABS(PPMT('⚙️ ПАРАМЕТРЫ'!$C$47/12,17,'⚙️ ПАРАМЕТРЫ'!$C$48,-'⚙️ ПАРАМЕТРЫ'!$C$46)),0) -> -26555.569 | T12: =IF(18<='⚙️ ПАРАМЕТРЫ'!$C$48,-ABS(PPMT('⚙️ ПАРАМЕТРЫ'!$C$47/12,18,'⚙️ ПАРАМЕТРЫ'!$C$48,-'⚙️ ПАРАМЕТРЫ'!$C$46)),0) -> -27042.421 | U12: =IF(19<='⚙️ ПАРАМЕТРЫ'!$C$48,-ABS(PPMT('⚙️ ПАРАМЕТРЫ'!$C$47/12,19,'⚙️ ПАРАМЕТРЫ'!$C$48,-'⚙️ ПАРАМЕТРЫ'!$C$46)),0) -> -27538.199 | V12: =IF(20<='⚙️ ПАРАМЕТРЫ'!$C$48,-ABS(PPMT('⚙️ ПАРАМЕТРЫ'!$C$47/12,20,'⚙️ ПАРАМЕТРЫ'!$C$48,-'⚙️ ПАРАМЕТРЫ'!$C$46)),0) -> -28043.066 | W12: =IF(21<='⚙️ ПАРАМЕТРЫ'!$C$48,-ABS(PPMT('⚙️ ПАРАМЕТРЫ'!$C$47/12,21,'⚙️ ПАРАМЕТРЫ'!$C$48,-'⚙️ ПАРАМЕТРЫ'!$C$46)),0) -> -28557.189 | X12: =IF(22<='⚙️ ПАРАМЕТРЫ'!$C$48,-ABS(PPMT('⚙️ ПАРАМЕТРЫ'!$C$47/12,22,'⚙️ ПАРАМЕТРЫ'!$C$48,-'⚙️ ПАРАМЕТРЫ'!$C$46)),0) -> -29080.737 | Y12: =IF(23<='⚙️ ПАРАМЕТРЫ'!$C$48,-ABS(PPMT('⚙️ ПАРАМЕТРЫ'!$C$47/12,23,'⚙️ ПАРАМЕТРЫ'!$C$48,-'⚙️ ПАРАМЕТРЫ'!$C$46)),0) -> -29613.884 | Z12: =IF(24<='⚙️ ПАРАМЕТРЫ'!$C$48,-ABS(PPMT('⚙️ ПАРАМЕТРЫ'!$C$47/12,24,'⚙️ ПАРАМЕТРЫ'!$C$48,-'⚙️ ПАРАМЕТРЫ'!$C$46)),0) -> -30156.805 | AA12: =IF(25<='⚙️ ПАРАМЕТРЫ'!$C$48,-ABS(PPMT('⚙️ ПАРАМЕТРЫ'!$C$47/12,25,'⚙️ ПАРАМЕТРЫ'!$C$48,-'⚙️ ПАРАМЕТРЫ'!$C$46)),0) -> -30709.68 | AB12: =IF(26<='⚙️ ПАРАМЕТРЫ'!$C$48,-ABS(PPMT('⚙️ ПАРАМЕТРЫ'!$C$47/12,26,'⚙️ ПАРАМЕТРЫ'!$C$48,-'⚙️ ПАРАМЕТРЫ'!$C$46)),0) -> -31272.691 | AC12: =IF(27<='⚙️ ПАРАМЕТРЫ'!$C$48,-ABS(PPMT('⚙️ ПАРАМЕТРЫ'!$C$47/12,27,'⚙️ ПАРАМЕТРЫ'!$C$48,-'⚙️ ПАРАМЕТРЫ'!$C$46)),0) -> -31846.024 | AD12: =IF(28<='⚙️ ПАРАМЕТРЫ'!$C$48,-ABS(PPMT('⚙️ ПАРАМЕТРЫ'!$C$47/12,28,'⚙️ ПАРАМЕТРЫ'!$C$48,-'⚙️ ПАРАМЕТРЫ'!$C$46)),0) -> -32429.867 | AE12: =IF(29<='⚙️ ПАРАМЕТРЫ'!$C$48,-ABS(PPMT('⚙️ ПАРАМЕТРЫ'!$C$47/12,29,'⚙️ ПАРАМЕТРЫ'!$C$48,-'⚙️ ПАРАМЕТРЫ'!$C$46)),0) -> -33024.415 | AF12: =IF(30<='⚙️ ПАРАМЕТРЫ'!$C$48,-ABS(PPMT('⚙️ ПАРАМЕТРЫ'!$C$47/12,30,'⚙️ ПАРАМЕТРЫ'!$C$48,-'⚙️ ПАРАМЕТРЫ'!$C$46)),0) -> -33629.863 | AG12: =IF(31<='⚙️ ПАРАМЕТРЫ'!$C$48,-ABS(PPMT('⚙️ ПАРАМЕТРЫ'!$C$47/12,31,'⚙️ ПАРАМЕТРЫ'!$C$48,-'⚙️ ПАРАМЕТРЫ'!$C$46)),0) -> -34246.41 | AH12: =IF(32<='⚙️ ПАРАМЕТРЫ'!$C$48,-ABS(PPMT('⚙️ ПАРАМЕТРЫ'!$C$47/12,32,'⚙️ ПАРАМЕТРЫ'!$C$48,-'⚙️ ПАРАМЕТРЫ'!$C$46)),0) -> -34874.261 | AI12: =IF(33<='⚙️ ПАРАМЕТРЫ'!$C$48,-ABS(PPMT('⚙️ ПАРАМЕТРЫ'!$C$47/12,33,'⚙️ ПАРАМЕТРЫ'!$C$48,-'⚙️ ПАРАМЕТРЫ'!$C$46)),0) -> -35513.622 | AJ12: =IF(34<='⚙️ ПАРАМЕТРЫ'!$C$48,-ABS(PPMT('⚙️ ПАРАМЕТРЫ'!$C$47/12,34,'⚙️ ПАРАМЕТРЫ'!$C$48,-'⚙️ ПАРАМЕТРЫ'!$C$46)),0) -> -36164.705 | AK12: =IF(35<='⚙️ ПАРАМЕТРЫ'!$C$48,-ABS(PPMT('⚙️ ПАРАМЕТРЫ'!$C$47/12,35,'⚙️ ПАРАМЕТРЫ'!$C$48,-'⚙️ ПАРАМЕТРЫ'!$C$46)),0) -> -36827.725 | AL12: =IF(36<='⚙️ ПАРАМЕТРЫ'!$C$48,-ABS(PPMT('⚙️ ПАРАМЕТРЫ'!$C$47/12,36,'⚙️ ПАРАМЕТРЫ'!$C$48,-'⚙️ ПАРАМЕТРЫ'!$C$46)),0) -> -37502.9
B13: 💡 PPMT = тело долга. IPMT → P&L.
B14: ОПЕРАЦИОННАЯ ДЕЯТЕЛЬНОСТЬ
B15: Чистая прибыль (из P&L) | C15: ='📈 P&L'!C38 -> 64149.667 | D15: ='📈 P&L'!D38 -> 634453.71 | E15: ='📈 P&L'!E38 -> 1279104.4 | F15: ='📈 P&L'!F38 -> 1279482 | G15: ='📈 P&L'!G38 -> 1205526.4 | H15: ='📈 P&L'!H38 -> 1106797.9 | I15: ='📈 P&L'!I38 -> 1032856.5 | J15: ='📈 P&L'!J38 -> 1033262.5 | ... AL15: ='📈 P&L'!AL38 -> 1370127.4
B16: + Амортизация (неденежный расход) | C16: ='📈 P&L'!C32 -> 17857 | D16: ='📈 P&L'!D32 -> 17857 | E16: ='📈 P&L'!E32 -> 17857 | F16: ='📈 P&L'!F32 -> 17857 | G16: ='📈 P&L'!G32 -> 17857 | H16: ='📈 P&L'!H32 -> 17857 | I16: ='📈 P&L'!I32 -> 17857 | J16: ='📈 P&L'!J32 -> 17857 | ... AL16: ='📈 P&L'!AL32 -> 17857
B17: 💡 Амортизация — не платёж, возвращаем в CF.
B18: Операционный денежный поток (OCF) | C18: =C15+C16 -> 82006.667 | D18: =D15+D16 -> 652310.71 | E18: =E15+E16 -> 1296961.4 | F18: =F15+F16 -> 1297339 | G18: =G15+G16 -> 1223383.4 | H18: =H15+H16 -> 1124654.9 | I18: =I15+I16 -> 1050713.5 | J18: =J15+J16 -> 1051119.5 | ... AL18: =AL15+AL16 -> 1387984.4
B20: ИТОГО
B21: =B9 -> -2640000 | C21: =C18+C11+C12 -> 1062149.5 | D21: =D18+D12 -> 632089.55 | E21: =E18+E12 -> 1276369.5 | F21: =F18+F12 -> 1276369.5 | G21: =G18+G12 -> 1202029.5 | H21: =H18+H12 -> 1102909.5 | I21: =I18+I12 -> 1028569.5 | J21: =J18+J12 -> 1028569.5 | K21: =K18+K12 -> 1449829.5 | ... AL21: =AL18+AL12 -> 1350481.5
B22: =B21 -> -2640000 | C22: =B22+C21 -> -1577850.5 | D22: =C22+D21 -> -945760.91 | E22: =D22+E21 -> 330608.64 | F22: =E22+F21 -> 1606978.2 | G22: =F22+G21 -> 2809007.7 | H22: =G22+H21 -> 3911917.3 | I22: =H22+I21 -> 4940486.8 | J22: =I22+J21 -> 5969056.4 | ... AL22: =AK22+AL21 -> 44947986
B23: 💡 Нарастающий ≥ 0 = окупаемость.
B24: ПРОЕКТНЫЙ CF (для IRR/NPV без кредитного рычага)
B25: =-'⚙️ ПАРАМЕТРЫ'!C41 -> -2640000 | C25: =C18 -> 82006.667 | D25: =D18 -> 652310.71 | E25: =E18 -> 1296961.4 | F25: =F18 -> 1297339 | G25: =G18 -> 1223383.4 | H25: =H18 -> 1124654.9 | I25: =I18 -> 1050713.5 | J25: =J18 -> 1051119.5 | ... AL25: =AL18 -> 1387984.4
B26: =B25 -> -2640000 | C26: =B26+C25 -> -2557993.3 | D26: =C26+D25 -> -1905682.6 | E26: =D26+E25 -> -608721.18 | F26: =E26+F25 -> 688617.77 | G26: =F26+G25 -> 1912001.2 | H26: =G26+H25 -> 3036656 | I26: =H26+I25 -> 4087369.6 | J26: =I26+J25 -> 5138489.1 | ... AL26: =AK26+AL25 -> 44947986
B28: КОНТРОЛЬНЫЕ ПОКАЗАТЕЛИ
B29: =0 -> 0 | C29: =C22+('⚙️ ПАРАМЕТРЫ'!$C$41-'⚙️ ПАРАМЕТРЫ'!$C$46) -> 62149.547 | D29: =D22+('⚙️ ПАРАМЕТРЫ'!$C$41-'⚙️ ПАРАМЕТРЫ'!$C$46) -> 694239.09 | E29: =E22+('⚙️ ПАРАМЕТРЫ'!$C$41-'⚙️ ПАРАМЕТРЫ'!$C$46) -> 1970608.6 | F29: =F22+('⚙️ ПАРАМЕТРЫ'!$C$41-'⚙️ ПАРАМЕТРЫ'!$C$46) -> 3246978.2 | G29: =G22+('⚙️ ПАРАМЕТРЫ'!$C$41-'⚙️ ПАРАМЕТРЫ'!$C$46) -> 4449007.7 | H29: =H22+('⚙️ ПАРАМЕТРЫ'!$C$41-'⚙️ ПАРАМЕТРЫ'!$C$46) -> 5551917.3 | I29: =I22+('⚙️ ПАРАМЕТРЫ'!$C$41-'⚙️ ПАРАМЕТРЫ'!$C$46) -> 6580486.8 | J29: =J22+('⚙️ ПАРАМЕТРЫ'!$C$41-'⚙️ ПАРАМЕТРЫ'!$C$46) -> 7609056.4 | ... AL29: =AL22+('⚙️ ПАРАМЕТРЫ'!$C$41-'⚙️ ПАРАМЕТРЫ'!$C$46) -> 46587986
B30: 💡 Если значение < 0 — у вас кассовый разрыв. Нужны дополнительные средства или кредитная линия.
B31: Месяц окупаемости | C31: {=IFERROR(MATCH(1,(C26:AL26>=0)*1,0),">36")} -> 4 | D31: 💡 Номер месяца, когда нарастающий CF впервые стал ≥ 0.
B33: ZEREK Financial Model | @zerekai_bot

Sheet 📋 КРЕДИТ
A1: ГРАФИК ПОГАШЕНИЯ КРЕДИТА — КОФЕЙНЯ: КОФЕ С СОБОЙ
A2: 📌 Аннуитетный платёж. Если сумма кредита = 0, таблица показывает нули.
A4: Месяц | B4: Платёж (аннуитет) | C4: Проценты (IPMT) | D4: Тело долга (PPMT) | E4: Остаток долга
A5: 1 | B5: =IF(AND('⚙️ ПАРАМЕТРЫ'!$C$46>0,1<='⚙️ ПАРАМЕТРЫ'!$C$48),ABS(PMT('⚙️ ПАРАМЕТРЫ'!$C$47/12,'⚙️ ПАРАМЕТРЫ'!$C$48,-'⚙️ ПАРАМЕТРЫ'!$C$46)),0) -> 38190.453 | C5: =IF(AND('⚙️ ПАРАМЕТРЫ'!$C$46>0,1<='⚙️ ПАРАМЕТРЫ'!$C$48),ABS(IPMT('⚙️ ПАРАМЕТРЫ'!$C$47/12,1,'⚙️ ПАРАМЕТРЫ'!$C$48,-'⚙️ ПАРАМЕТРЫ'!$C$46)),0) -> 18333.333 | D5: =IF(AND('⚙️ ПАРАМЕТРЫ'!$C$46>0,1<='⚙️ ПАРАМЕТРЫ'!$C$48),ABS(PPMT('⚙️ ПАРАМЕТРЫ'!$C$47/12,1,'⚙️ ПАРАМЕТРЫ'!$C$48,-'⚙️ ПАРАМЕТРЫ'!$C$46)),0) -> 19857.12 | E5: =IF('⚙️ ПАРАМЕТРЫ'!$C$46>0,'⚙️ ПАРАМЕТРЫ'!$C$46-D5,0) -> 980142.88
A6: 2 | B6: =IF(AND('⚙️ ПАРАМЕТРЫ'!$C$46>0,2<='⚙️ ПАРАМЕТРЫ'!$C$48),ABS(PMT('⚙️ ПАРАМЕТРЫ'!$C$47/12,'⚙️ ПАРАМЕТРЫ'!$C$48,-'⚙️ ПАРАМЕТРЫ'!$C$46)),0) -> 38190.453 | C6: =IF(AND('⚙️ ПАРАМЕТРЫ'!$C$46>0,2<='⚙️ ПАРАМЕТРЫ'!$C$48),ABS(IPMT('⚙️ ПАРАМЕТРЫ'!$C$47/12,2,'⚙️ ПАРАМЕТРЫ'!$C$48,-'⚙️ ПАРАМЕТРЫ'!$C$46)),0) -> 17969.286 | D6: =IF(AND('⚙️ ПАРАМЕТРЫ'!$C$46>0,2<='⚙️ ПАРАМЕТРЫ'!$C$48),ABS(PPMT('⚙️ ПАРАМЕТРЫ'!$C$47/12,2,'⚙️ ПАРАМЕТРЫ'!$C$48,-'⚙️ ПАРАМЕТРЫ'!$C$46)),0) -> 20221.167 | E6: =IF('⚙️ ПАРАМЕТРЫ'!$C$46>0,E5-D6,0) -> 959921.71
A7: 3 | B7: =IF(AND('⚙️ ПАРАМЕТРЫ'!$C$46>0,3<='⚙️ ПАРАМЕТРЫ'!$C$48),ABS(PMT('⚙️ ПАРАМЕТРЫ'!$C$47/12,'⚙️ ПАРАМЕТРЫ'!$C$48,-'⚙️ ПАРАМЕТРЫ'!$C$46)),0) -> 38190.453 | C7: =IF(AND('⚙️ ПАРАМЕТРЫ'!$C$46>0,3<='⚙️ ПАРАМЕТРЫ'!$C$48),ABS(IPMT('⚙️ ПАРАМЕТРЫ'!$C$47/12,3,'⚙️ ПАРАМЕТРЫ'!$C$48,-'⚙️ ПАРАМЕТРЫ'!$C$46)),0) -> 17598.565 | D7: =IF(AND('⚙️ ПАРАМЕТРЫ'!$C$46>0,3<='⚙️ ПАРАМЕТРЫ'!$C$48),ABS(PPMT('⚙️ ПАРАМЕТРЫ'!$C$47/12,3,'⚙️ ПАРАМЕТРЫ'!$C$48,-'⚙️ ПАРАМЕТРЫ'!$C$46)),0) -> 20591.888 | E7: =IF('⚙️ ПАРАМЕТРЫ'!$C$46>0,E6-D7,0) -> 939329.82
A8: 4 | B8: =IF(AND('⚙️ ПАРАМЕТРЫ'!$C$46>0,4<='⚙️ ПАРАМЕТРЫ'!$C$48),ABS(PMT('⚙️ ПАРАМЕТРЫ'!$C$47/12,'⚙️ ПАРАМЕТРЫ'!$C$48,-'⚙️ ПАРАМЕТРЫ'!$C$46)),0) -> 38190.453 | C8: =IF(AND('⚙️ ПАРАМЕТРЫ'!$C$46>0,4<='⚙️ ПАРАМЕТРЫ'!$C$48),ABS(IPMT('⚙️ ПАРАМЕТРЫ'!$C$47/12,4,'⚙️ ПАРАМЕТРЫ'!$C$48,-'⚙️ ПАРАМЕТРЫ'!$C$46)),0) -> 17221.047 | D8: =IF(AND('⚙️ ПАРАМЕТРЫ'!$C$46>0,4<='⚙️ ПАРАМЕТРЫ'!$C$48),ABS(PPMT('⚙️ ПАРАМЕТРЫ'!$C$47/12,4,'⚙️ ПАРАМЕТРЫ'!$C$48,-'⚙️ ПАРАМЕТРЫ'!$C$46)),0) -> 20969.406 | E8: =IF('⚙️ ПАРАМЕТРЫ'!$C$46>0,E7-D8,0) -> 918360.42
A9: 5 | B9: =IF(AND('⚙️ ПАРАМЕТРЫ'!$C$46>0,5<='⚙️ ПАРАМЕТРЫ'!$C$48),ABS(PMT('⚙️ ПАРАМЕТРЫ'!$C$47/12,'⚙️ ПАРАМЕТРЫ'!$C$48,-'⚙️ ПАРАМЕТРЫ'!$C$46)),0) -> 38190.453 | C9: =IF(AND('⚙️ ПАРАМЕТРЫ'!$C$46>0,5<='⚙️ ПАРАМЕТРЫ'!$C$48),ABS(IPMT('⚙️ ПАРАМЕТРЫ'!$C$47/12,5,'⚙️ ПАРАМЕТРЫ'!$C$48,-'⚙️ ПАРАМЕТРЫ'!$C$46)),0) -> 16836.608 | D9: =IF(AND('⚙️ ПАРАМЕТРЫ'!$C$46>0,5<='⚙️ ПАРАМЕТРЫ'!$C$48),ABS(PPMT('⚙️ ПАРАМЕТРЫ'!$C$47/12,5,'⚙️ ПАРАМЕТРЫ'!$C$48,-'⚙️ ПАРАМЕТРЫ'!$C$46)),0) -> 21353.846 | E9: =IF('⚙️ ПАРАМЕТРЫ'!$C$46>0,E8-D9,0) -> 897006.57
A10: 6 | B10: =IF(AND('⚙️ ПАРАМЕТРЫ'!$C$46>0,6<='⚙️ ПАРАМЕТРЫ'!$C$48),ABS(PMT('⚙️ ПАРАМЕТРЫ'!$C$47/12,'⚙️ ПАРАМЕТРЫ'!$C$48,-'⚙️ ПАРАМЕТРЫ'!$C$46)),0) -> 38190.453 | C10: =IF(AND('⚙️ ПАРАМЕТРЫ'!$C$46>0,6<='⚙️ ПАРАМЕТРЫ'!$C$48),ABS(IPMT('⚙️ ПАРАМЕТРЫ'!$C$47/12,6,'⚙️ ПАРАМЕТРЫ'!$C$48,-'⚙️ ПАРАМЕТРЫ'!$C$46)),0) -> 16445.121 | D10: =IF(AND('⚙️ ПАРАМЕТРЫ'!$C$46>0,6<='⚙️ ПАРАМЕТРЫ'!$C$48),ABS(PPMT('⚙️ ПАРАМЕТРЫ'!$C$47/12,6,'⚙️ ПАРАМЕТРЫ'!$C$48,-'⚙️ ПАРАМЕТРЫ'!$C$46)),0) -> 21745.333 | E10: =IF('⚙️ ПАРАМЕТРЫ'!$C$46>0,E9-D10,0) -> 875261.24
A11: 7 | B11: =IF(AND('⚙️ ПАРАМЕТРЫ'!$C$46>0,7<='⚙️ ПАРАМЕТРЫ'!$C$48),ABS(PMT('⚙️ ПАРАМЕТРЫ'!$C$47/12,'⚙️ ПАРАМЕТРЫ'!$C$48,-'⚙️ ПАРАМЕТРЫ'!$C$46)),0) -> 38190.453 | C11: =IF(AND('⚙️ ПАРАМЕТРЫ'!$C$46>0,7<='⚙️ ПАРАМЕТРЫ'!$C$48),ABS(IPMT('⚙️ ПАРАМЕТРЫ'!$C$47/12,7,'⚙️ ПАРАМЕТРЫ'!$C$48,-'⚙️ ПАРАМЕТРЫ'!$C$46)),0) -> 16046.456 | D11: =IF(AND('⚙️ ПАРАМЕТРЫ'!$C$46>0,7<='⚙️ ПАРАМЕТРЫ'!$C$48),ABS(PPMT('⚙️ ПАРАМЕТРЫ'!$C$47/12,7,'⚙️ ПАРАМЕТРЫ'!$C$48,-'⚙️ ПАРАМЕТРЫ'!$C$46)),0) -> 22143.997 | E11: =IF('⚙️ ПАРАМЕТРЫ'!$C$46>0,E10-D11,0) -> 853117.24
A12: 8 | B12: =IF(AND('⚙️ ПАРАМЕТРЫ'!$C$46>0,8<='⚙️ ПАРАМЕТРЫ'!$C$48),ABS(PMT('⚙️ ПАРАМЕТРЫ'!$C$47/12,'⚙️ ПАРАМЕТРЫ'!$C$48,-'⚙️ ПАРАМЕТРЫ'!$C$46)),0) -> 38190.453 | C12: =IF(AND('⚙️ ПАРАМЕТРЫ'!$C$46>0,8<='⚙️ ПАРАМЕТРЫ'!$C$48),ABS(IPMT('⚙️ ПАРАМЕТРЫ'!$C$47/12,8,'⚙️ ПАРАМЕТРЫ'!$C$48,-'⚙️ ПАРАМЕТРЫ'!$C$46)),0) -> 15640.483 | D12: =IF(AND('⚙️ ПАРАМЕТРЫ'!$C$46>0,8<='⚙️ ПАРАМЕТРЫ'!$C$48),ABS(PPMT('⚙️ ПАРАМЕТРЫ'!$C$47/12,8,'⚙️ ПАРАМЕТРЫ'!$C$48,-'⚙️ ПАРАМЕТРЫ'!$C$46)),0) -> 22549.97 | E12: =IF('⚙️ ПАРАМЕТРЫ'!$C$46>0,E11-D12,0) -> 830567.27
A13: 9 | B13: =IF(AND('⚙️ ПАРАМЕТРЫ'!$C$46>0,9<='⚙️ ПАРАМЕТРЫ'!$C$48),ABS(PMT('⚙️ ПАРАМЕТРЫ'!$C$47/12,'⚙️ ПАРАМЕТРЫ'!$C$48,-'⚙️ ПАРАМЕТРЫ'!$C$46)),0) -> 38190.453 | C13: =IF(AND('⚙️ ПАРАМЕТРЫ'!$C$46>0,9<='⚙️ ПАРАМЕТРЫ'!$C$48),ABS(IPMT('⚙️ ПАРАМЕТРЫ'!$C$47/12,9,'⚙️ ПАРАМЕТРЫ'!$C$48,-'⚙️ ПАРАМЕТРЫ'!$C$46)),0) -> 15227.067 | D13: =IF(AND('⚙️ ПАРАМЕТРЫ'!$C$46>0,9<='⚙️ ПАРАМЕТРЫ'!$C$48),ABS(PPMT('⚙️ ПАРАМЕТРЫ'!$C$47/12,9,'⚙️ ПАРАМЕТРЫ'!$C$48,-'⚙️ ПАРАМЕТРЫ'!$C$46)),0) -> 22963.387 | E13: =IF('⚙️ ПАРАМЕТРЫ'!$C$46>0,E12-D13,0) -> 807603.89
A14: 10 | B14: =IF(AND('⚙️ ПАРАМЕТРЫ'!$C$46>0,10<='⚙️ ПАРАМЕТРЫ'!$C$48),ABS(PMT('⚙️ ПАРАМЕТРЫ'!$C$47/12,'⚙️ ПАРАМЕТРЫ'!$C$48,-'⚙️ ПАРАМЕТРЫ'!$C$46)),0) -> 38190.453 | C14: =IF(AND('⚙️ ПАРАМЕТРЫ'!$C$46>0,10<='⚙️ ПАРАМЕТРЫ'!$C$48),ABS(IPMT('⚙️ ПАРАМЕТРЫ'!$C$47/12,10,'⚙️ ПАРАМЕТРЫ'!$C$48,-'⚙️ ПАРАМЕТРЫ'!$C$46)),0) -> 14806.071 | D14: =IF(AND('⚙️ ПАРАМЕТРЫ'!$C$46>0,10<='⚙️ ПАРАМЕТРЫ'!$C$48),ABS(PPMT('⚙️ ПАРАМЕТРЫ'!$C$47/12,10,'⚙️ ПАРАМЕТРЫ'!$C$48,-'⚙️ ПАРАМЕТРЫ'!$C$46)),0) -> 23384.382 | E14: =IF('⚙️ ПАРАМЕТРЫ'!$C$46>0,E13-D14,0) -> 784219.5
A15: 11 | B15: =IF(AND('⚙️ ПАРАМЕТРЫ'!$C$46>0,11<='⚙️ ПАРАМЕТРЫ'!$C$48),ABS(PMT('⚙️ ПАРАМЕТРЫ'!$C$47/12,'⚙️ ПАРАМЕТРЫ'!$C$48,-'⚙️ ПАРАМЕТРЫ'!$C$46)),0) -> 38190.453 | C15: =IF(AND('⚙️ ПАРАМЕТРЫ'!$C$46>0,11<='⚙️ ПАРАМЕТРЫ'!$C$48),ABS(IPMT('⚙️ ПАРАМЕТРЫ'!$C$47/12,11,'⚙️ ПАРАМЕТРЫ'!$C$48,-'⚙️ ПАРАМЕТРЫ'!$C$46)),0) -> 14377.358 | D15: =IF(AND('⚙️ ПАРАМЕТРЫ'!$C$46>0,11<='⚙️ ПАРАМЕТРЫ'!$C$48),ABS(PPMT('⚙️ ПАРАМЕТРЫ'!$C$47/12,11,'⚙️ ПАРАМЕТРЫ'!$C$48,-'⚙️ ПАРАМЕТРЫ'!$C$46)),0) -> 23813.096 | E15: =IF('⚙️ ПАРАМЕТРЫ'!$C$46>0,E14-D15,0) -> 760406.41
A16: 12 | B16: =IF(AND('⚙️ ПАРАМЕТРЫ'!$C$46>0,12<='⚙️ ПАРАМЕТРЫ'!$C$48),ABS(PMT('⚙️ ПАРАМЕТРЫ'!$C$47/12,'⚙️ ПАРАМЕТРЫ'!$C$48,-'⚙️ ПАРАМЕТРЫ'!$C$46)),0) -> 38190.453 | C16: =IF(AND('⚙️ ПАРАМЕТРЫ'!$C$46>0,12<='⚙️ ПАРАМЕТРЫ'!$C$48),ABS(IPMT('⚙️ ПАРАМЕТРЫ'!$C$47/12,12,'⚙️ ПАРАМЕТРЫ'!$C$48,-'⚙️ ПАРАМЕТРЫ'!$C$46)),0) -> 13940.784 | D16: =IF(AND('⚙️ ПАРАМЕТРЫ'!$C$46>0,12<='⚙️ ПАРАМЕТРЫ'!$C$48),ABS(PPMT('⚙️ ПАРАМЕТРЫ'!$C$47/12,12,'⚙️ ПАРАМЕТРЫ'!$C$48,-'⚙️ ПАРАМЕТРЫ'!$C$46)),0) -> 24249.669 | E16: =IF('⚙️ ПАРАМЕТРЫ'!$C$46>0,E15-D16,0) -> 736156.74
A17: 13 | B17: =IF(AND('⚙️ ПАРАМЕТРЫ'!$C$46>0,13<='⚙️ ПАРАМЕТРЫ'!$C$48),ABS(PMT('⚙️ ПАРАМЕТРЫ'!$C$47/12,'⚙️ ПАРАМЕТРЫ'!$C$48,-'⚙️ ПАРАМЕТРЫ'!$C$46)),0) -> 38190.453 | C17: =IF(AND('⚙️ ПАРАМЕТРЫ'!$C$46>0,13<='⚙️ ПАРАМЕТРЫ'!$C$48),ABS(IPMT('⚙️ ПАРАМЕТРЫ'!$C$47/12,13,'⚙️ ПАРАМЕТРЫ'!$C$48,-'⚙️ ПАРАМЕТРЫ'!$C$46)),0) -> 13496.207 | D17: =IF(AND('⚙️ ПАРАМЕТРЫ'!$C$46>0,13<='⚙️ ПАРАМЕТРЫ'!$C$48),ABS(PPMT('⚙️ ПАРАМЕТРЫ'!$C$47/12,13,'⚙️ ПАРАМЕТРЫ'!$C$48,-'⚙️ ПАРАМЕТРЫ'!$C$46)),0) -> 24694.246 | E17: =IF('⚙️ ПАРАМЕТРЫ'!$C$46>0,E16-D17,0) -> 711462.49
A18: 14 | B18: =IF(AND('⚙️ ПАРАМЕТРЫ'!$C$46>0,14<='⚙️ ПАРАМЕТРЫ'!$C$48),ABS(PMT('⚙️ ПАРАМЕТРЫ'!$C$47/12,'⚙️ ПАРАМЕТРЫ'!$C$48,-'⚙️ ПАРАМЕТРЫ'!$C$46)),0) -> 38190.453 | C18: =IF(AND('⚙️ ПАРАМЕТРЫ'!$C$46>0,14<='⚙️ ПАРАМЕТРЫ'!$C$48),ABS(IPMT('⚙️ ПАРАМЕТРЫ'!$C$47/12,14,'⚙️ ПАРАМЕТРЫ'!$C$48,-'⚙️ ПАРАМЕТРЫ'!$C$46)),0) -> 13043.479 | D18: =IF(AND('⚙️ ПАРАМЕТРЫ'!$C$46>0,14<='⚙️ ПАРАМЕТРЫ'!$C$48),ABS(PPMT('⚙️ ПАРАМЕТРЫ'!$C$47/12,14,'⚙️ ПАРАМЕТРЫ'!$C$48,-'⚙️ ПАРАМЕТРЫ'!$C$46)),0) -> 25146.974 | E18: =IF('⚙️ ПАРАМЕТРЫ'!$C$46>0,E17-D18,0) -> 686315.52
A19: 15 | B19: =IF(AND('⚙️ ПАРАМЕТРЫ'!$C$46>0,15<='⚙️ ПАРАМЕТРЫ'!$C$48),ABS(PMT('⚙️ ПАРАМЕТРЫ'!$C$47/12,'⚙️ ПАРАМЕТРЫ'!$C$48,-'⚙️ ПАРАМЕТРЫ'!$C$46)),0) -> 38190.453 | C19: =IF(AND('⚙️ ПАРАМЕТРЫ'!$C$46>0,15<='⚙️ ПАРАМЕТРЫ'!$C$48),ABS(IPMT('⚙️ ПАРАМЕТРЫ'!$C$47/12,15,'⚙️ ПАРАМЕТРЫ'!$C$48,-'⚙️ ПАРАМЕТРЫ'!$C$46)),0) -> 12582.451 | D19: =IF(AND('⚙️ ПАРАМЕТРЫ'!$C$46>0,15<='⚙️ ПАРАМЕТРЫ'!$C$48),ABS(PPMT('⚙️ ПАРАМЕТРЫ'!$C$47/12,15,'⚙️ ПАРАМЕТРЫ'!$C$48,-'⚙️ ПАРАМЕТРЫ'!$C$46)),0) -> 25608.002 | E19: =IF('⚙️ ПАРАМЕТРЫ'!$C$46>0,E18-D19,0) -> 660707.52
A20: 16 | B20: =IF(AND('⚙️ ПАРАМЕТРЫ'!$C$46>0,16<='⚙️ ПАРАМЕТРЫ'!$C$48),ABS(PMT('⚙️ ПАРАМЕТРЫ'!$C$47/12,'⚙️ ПАРАМЕТРЫ'!$C$48,-'⚙️ ПАРАМЕТРЫ'!$C$46)),0) -> 38190.453 | C20: =IF(AND('⚙️ ПАРАМЕТРЫ'!$C$46>0,16<='⚙️ ПАРАМЕТРЫ'!$C$48),ABS(IPMT('⚙️ ПАРАМЕТРЫ'!$C$47/12,16,'⚙️ ПАРАМЕТРЫ'!$C$48,-'⚙️ ПАРАМЕТРЫ'!$C$46)),0) -> 12112.971 | D20: =IF(AND('⚙️ ПАРАМЕТРЫ'!$C$46>0,16<='⚙️ ПАРАМЕТРЫ'!$C$48),ABS(PPMT('⚙️ ПАРАМЕТРЫ'!$C$47/12,16,'⚙️ ПАРАМЕТРЫ'!$C$48,-'⚙️ ПАРАМЕТРЫ'!$C$46)),0) -> 26077.482 | E20: =IF('⚙️ ПАРАМЕТРЫ'!$C$46>0,E19-D20,0) -> 634630.04
A21: 17 | B21: =IF(AND('⚙️ ПАРАМЕТРЫ'!$C$46>0,17<='⚙️ ПАРАМЕТРЫ'!$C$48),ABS(PMT('⚙️ ПАРАМЕТРЫ'!$C$47/12,'⚙️ ПАРАМЕТРЫ'!$C$48,-'⚙️ ПАРАМЕТРЫ'!$C$46)),0) -> 38190.453 | C21: =IF(AND('⚙️ ПАРАМЕТРЫ'!$C$46>0,17<='⚙️ ПАРАМЕТРЫ'!$C$48),ABS(IPMT('⚙️ ПАРАМЕТРЫ'!$C$47/12,17,'⚙️ ПАРАМЕТРЫ'!$C$48,-'⚙️ ПАРАМЕТРЫ'!$C$46)),0) -> 11634.884 | D21: =IF(AND('⚙️ ПАРАМЕТРЫ'!$C$46>0,17<='⚙️ ПАРАМЕТРЫ'!$C$48),ABS(PPMT('⚙️ ПАРАМЕТРЫ'!$C$47/12,17,'⚙️ ПАРАМЕТРЫ'!$C$48,-'⚙️ ПАРАМЕТРЫ'!$C$46)),0) -> 26555.569 | E21: =IF('⚙️ ПАРАМЕТРЫ'!$C$46>0,E20-D21,0) -> 608074.47
A22: 18 | B22: =IF(AND('⚙️ ПАРАМЕТРЫ'!$C$46>0,18<='⚙️ ПАРАМЕТРЫ'!$C$48),ABS(PMT('⚙️ ПАРАМЕТРЫ'!$C$47/12,'⚙️ ПАРАМЕТРЫ'!$C$48,-'⚙️ ПАРАМЕТРЫ'!$C$46)),0) -> 38190.453 | C22: =IF(AND('⚙️ ПАРАМЕТРЫ'!$C$46>0,18<='⚙️ ПАРАМЕТРЫ'!$C$48),ABS(IPMT('⚙️ ПАРАМЕТРЫ'!$C$47/12,18,'⚙️ ПАРАМЕТРЫ'!$C$48,-'⚙️ ПАРАМЕТРЫ'!$C$46)),0) -> 11148.032 | D22: =IF(AND('⚙️ ПАРАМЕТРЫ'!$C$46>0,18<='⚙️ ПАРАМЕТРЫ'!$C$48),ABS(PPMT('⚙️ ПАРАМЕТРЫ'!$C$47/12,18,'⚙️ ПАРАМЕТРЫ'!$C$48,-'⚙️ ПАРАМЕТРЫ'!$C$46)),0) -> 27042.421 | E22: =IF('⚙️ ПАРАМЕТРЫ'!$C$46>0,E21-D22,0) -> 581032.04
A23: 19 | B23: =IF(AND('⚙️ ПАРАМЕТРЫ'!$C$46>0,19<='⚙️ ПАРАМЕТРЫ'!$C$48),ABS(PMT('⚙️ ПАРАМЕТРЫ'!$C$47/12,'⚙️ ПАРАМЕТРЫ'!$C$48,-'⚙️ ПАРАМЕТРЫ'!$C$46)),0) -> 38190.453 | C23: =IF(AND('⚙️ ПАРАМЕТРЫ'!$C$46>0,19<='⚙️ ПАРАМЕТРЫ'!$C$48),ABS(IPMT('⚙️ ПАРАМЕТРЫ'!$C$47/12,19,'⚙️ ПАРАМЕТРЫ'!$C$48,-'⚙️ ПАРАМЕТРЫ'!$C$46)),0) -> 10652.254 | D23: =IF(AND('⚙️ ПАРАМЕТРЫ'!$C$46>0,19<='⚙️ ПАРАМЕТРЫ'!$C$48),ABS(PPMT('⚙️ ПАРАМЕТРЫ'!$C$47/12,19,'⚙️ ПАРАМЕТРЫ'!$C$48,-'⚙️ ПАРАМЕТРЫ'!$C$46)),0) -> 27538.199 | E23: =IF('⚙️ ПАРАМЕТРЫ'!$C$46>0,E22-D23,0) -> 553493.85
A24: 20 | B24: =IF(AND('⚙️ ПАРАМЕТРЫ'!$C$46>0,20<='⚙️ ПАРАМЕТРЫ'!$C$48),ABS(PMT('⚙️ ПАРАМЕТРЫ'!$C$47/12,'⚙️ ПАРАМЕТРЫ'!$C$48,-'⚙️ ПАРАМЕТРЫ'!$C$46)),0) -> 38190.453 | C24: =IF(AND('⚙️ ПАРАМЕТРЫ'!$C$46>0,20<='⚙️ ПАРАМЕТРЫ'!$C$48),ABS(IPMT('⚙️ ПАРАМЕТРЫ'!$C$47/12,20,'⚙️ ПАРАМЕТРЫ'!$C$48,-'⚙️ ПАРАМЕТРЫ'!$C$46)),0) -> 10147.387 | D24: =IF(AND('⚙️ ПАРАМЕТРЫ'!$C$46>0,20<='⚙️ ПАРАМЕТРЫ'!$C$48),ABS(PPMT('⚙️ ПАРАМЕТРЫ'!$C$47/12,20,'⚙️ ПАРАМЕТРЫ'!$C$48,-'⚙️ ПАРАМЕТРЫ'!$C$46)),0) -> 28043.066 | E24: =IF('⚙️ ПАРАМЕТРЫ'!$C$46>0,E23-D24,0) -> 525450.78
A25: 21 | B25: =IF(AND('⚙️ ПАРАМЕТРЫ'!$C$46>0,21<='⚙️ ПАРАМЕТРЫ'!$C$48),ABS(PMT('⚙️ ПАРАМЕТРЫ'!$C$47/12,'⚙️ ПАРАМЕТРЫ'!$C$48,-'⚙️ ПАРАМЕТРЫ'!$C$46)),0) -> 38190.453 | C25: =IF(AND('⚙️ ПАРАМЕТРЫ'!$C$46>0,21<='⚙️ ПАРАМЕТРЫ'!$C$48),ABS(IPMT('⚙️ ПАРАМЕТРЫ'!$C$47/12,21,'⚙️ ПАРАМЕТРЫ'!$C$48,-'⚙️ ПАРАМЕТРЫ'!$C$46)),0) -> 9633.2643 | D25: =IF(AND('⚙️ ПАРАМЕТРЫ'!$C$46>0,21<='⚙️ ПАРАМЕТРЫ'!$C$48),ABS(PPMT('⚙️ ПАРАМЕТРЫ'!$C$47/12,21,'⚙️ ПАРАМЕТРЫ'!$C$48,-'⚙️ ПАРАМЕТРЫ'!$C$46)),0) -> 28557.189 | E25: =IF('⚙️ ПАРАМЕТРЫ'!$C$46>0,E24-D25,0) -> 496893.59
A26: 22 | B26: =IF(AND('⚙️ ПАРАМЕТРЫ'!$C$46>0,22<='⚙️ ПАРАМЕТРЫ'!$C$48),ABS(PMT('⚙️ ПАРАМЕТРЫ'!$C$47/12,'⚙️ ПАРАМЕТРЫ'!$C$48,-'⚙️ ПАРАМЕТРЫ'!$C$46)),0) -> 38190.453 | C26: =IF(AND('⚙️ ПАРАМЕТРЫ'!$C$46>0,22<='⚙️ ПАРАМЕТРЫ'!$C$48),ABS(IPMT('⚙️ ПАРАМЕТРЫ'!$C$47/12,22,'⚙️ ПАРАМЕТРЫ'!$C$48,-'⚙️ ПАРАМЕТРЫ'!$C$46)),0) -> 9109.7158 | D26: =IF(AND('⚙️ ПАРАМЕТРЫ'!$C$46>0,22<='⚙️ ПАРАМЕТРЫ'!$C$48),ABS(PPMT('⚙️ ПАРАМЕТРЫ'!$C$47/12,22,'⚙️ ПАРАМЕТРЫ'!$C$48,-'⚙️ ПАРАМЕТРЫ'!$C$46)),0) -> 29080.737 | E26: =IF('⚙️ ПАРАМЕТРЫ'!$C$46>0,E25-D26,0) -> 467812.85
A27: 23 | B27: =IF(AND('⚙️ ПАРАМЕТРЫ'!$C$46>0,23<='⚙️ ПАРАМЕТРЫ'!$C$48),ABS(PMT('⚙️ ПАРАМЕТРЫ'!$C$47/12,'⚙️ ПАРАМЕТРЫ'!$C$48,-'⚙️ ПАРАМЕТРЫ'!$C$46)),0) -> 38190.453 | C27: =IF(AND('⚙️ ПАРАМЕТРЫ'!$C$46>0,23<='⚙️ ПАРАМЕТРЫ'!$C$48),ABS(IPMT('⚙️ ПАРАМЕТРЫ'!$C$47/12,23,'⚙️ ПАРАМЕТРЫ'!$C$48,-'⚙️ ПАРАМЕТРЫ'!$C$46)),0) -> 8576.569 | D27: =IF(AND('⚙️ ПАРАМЕТРЫ'!$C$46>0,23<='⚙️ ПАРАМЕТРЫ'!$C$48),ABS(PPMT('⚙️ ПАРАМЕТРЫ'!$C$47/12,23,'⚙️ ПАРАМЕТРЫ'!$C$48,-'⚙️ ПАРАМЕТРЫ'!$C$46)),0) -> 29613.884 | E27: =IF('⚙️ ПАРАМЕТРЫ'!$C$46>0,E26-D27,0) -> 438198.97
A28: 24 | B28: =IF(AND('⚙️ ПАРАМЕТРЫ'!$C$46>0,24<='⚙️ ПАРАМЕТРЫ'!$C$48),ABS(PMT('⚙️ ПАРАМЕТРЫ'!$C$47/12,'⚙️ ПАРАМЕТРЫ'!$C$48,-'⚙️ ПАРАМЕТРЫ'!$C$46)),0) -> 38190.453 | C28: =IF(AND('⚙️ ПАРАМЕТРЫ'!$C$46>0,24<='⚙️ ПАРАМЕТРЫ'!$C$48),ABS(IPMT('⚙️ ПАРАМЕТРЫ'!$C$47/12,24,'⚙️ ПАРАМЕТРЫ'!$C$48,-'⚙️ ПАРАМЕТРЫ'!$C$46)),0) -> 8033.6478 | D28: =IF(AND('⚙️ ПАРАМЕТРЫ'!$C$46>0,24<='⚙️ ПАРАМЕТРЫ'!$C$48),ABS(PPMT('⚙️ ПАРАМЕТРЫ'!$C$47/12,24,'⚙️ ПАРАМЕТРЫ'!$C$48,-'⚙️ ПАРАМЕТРЫ'!$C$46)),0) -> 30156.805 | E28: =IF('⚙️ ПАРАМЕТРЫ'!$C$46>0,E27-D28,0) -> 408042.16
A29: 25 | B29: =IF(AND('⚙️ ПАРАМЕТРЫ'!$C$46>0,25<='⚙️ ПАРАМЕТРЫ'!$C$48),ABS(PMT('⚙️ ПАРАМЕТРЫ'!$C$47/12,'⚙️ ПАРАМЕТРЫ'!$C$48,-'⚙️ ПАРАМЕТРЫ'!$C$46)),0) -> 38190.453 | C29: =IF(AND('⚙️ ПАРАМЕТРЫ'!$C$46>0,25<='⚙️ ПАРАМЕТРЫ'!$C$48),ABS(IPMT('⚙️ ПАРАМЕТРЫ'!$C$47/12,25,'⚙️ ПАРАМЕТРЫ'!$C$48,-'⚙️ ПАРАМЕТРЫ'!$C$46)),0) -> 7480.773 | D29: =IF(AND('⚙️ ПАРАМЕТРЫ'!$C$46>0,25<='⚙️ ПАРАМЕТРЫ'!$C$48),ABS(PPMT('⚙️ ПАРАМЕТРЫ'!$C$47/12,25,'⚙️ ПАРАМЕТРЫ'!$C$48,-'⚙️ ПАРАМЕТРЫ'!$C$46)),0) -> 30709.68 | E29: =IF('⚙️ ПАРАМЕТРЫ'!$C$46>0,E28-D29,0) -> 377332.48
A30: 26 | B30: =IF(AND('⚙️ ПАРАМЕТРЫ'!$C$46>0,26<='⚙️ ПАРАМЕТРЫ'!$C$48),ABS(PMT('⚙️ ПАРАМЕТРЫ'!$C$47/12,'⚙️ ПАРАМЕТРЫ'!$C$48,-'⚙️ ПАРАМЕТРЫ'!$C$46)),0) -> 38190.453 | C30: =IF(AND('⚙️ ПАРАМЕТРЫ'!$C$46>0,26<='⚙️ ПАРАМЕТРЫ'!$C$48),ABS(IPMT('⚙️ ПАРАМЕТРЫ'!$C$47/12,26,'⚙️ ПАРАМЕТРЫ'!$C$48,-'⚙️ ПАРАМЕТРЫ'!$C$46)),0) -> 6917.7622 | D30: =IF(AND('⚙️ ПАРАМЕТРЫ'!$C$46>0,26<='⚙️ ПАРАМЕТРЫ'!$C$48),ABS(PPMT('⚙️ ПАРАМЕТРЫ'!$C$47/12,26,'⚙️ ПАРАМЕТРЫ'!$C$48,-'⚙️ ПАРАМЕТРЫ'!$C$46)),0) -> 31272.691 | E30: =IF('⚙️ ПАРАМЕТРЫ'!$C$46>0,E29-D30,0) -> 346059.79
A31: 27 | B31: =IF(AND('⚙️ ПАРАМЕТРЫ'!$C$46>0,27<='⚙️ ПАРАМЕТРЫ'!$C$48),ABS(PMT('⚙️ ПАРАМЕТРЫ'!$C$47/12,'⚙️ ПАРАМЕТРЫ'!$C$48,-'⚙️ ПАРАМЕТРЫ'!$C$46)),0) -> 38190.453 | C31: =IF(AND('⚙️ ПАРАМЕТРЫ'!$C$46>0,27<='⚙️ ПАРАМЕТРЫ'!$C$48),ABS(IPMT('⚙️ ПАРАМЕТРЫ'!$C$47/12,27,'⚙️ ПАРАМЕТРЫ'!$C$48,-'⚙️ ПАРАМЕТРЫ'!$C$46)),0) -> 6344.4295 | D31: =IF(AND('⚙️ ПАРАМЕТРЫ'!$C$46>0,27<='⚙️ ПАРАМЕТРЫ'!$C$48),ABS(PPMT('⚙️ ПАРАМЕТРЫ'!$C$47/12,27,'⚙️ ПАРАМЕТРЫ'!$C$48,-'⚙️ ПАРАМЕТРЫ'!$C$46)),0) -> 31846.024 | E31: =IF('⚙️ ПАРАМЕТРЫ'!$C$46>0,E30-D31,0) -> 314213.77
A32: 28 | B32: =IF(AND('⚙️ ПАРАМЕТРЫ'!$C$46>0,28<='⚙️ ПАРАМЕТРЫ'!$C$48),ABS(PMT('⚙️ ПАРАМЕТРЫ'!$C$47/12,'⚙️ ПАРАМЕТРЫ'!$C$48,-'⚙️ ПАРАМЕТРЫ'!$C$46)),0) -> 38190.453 | C32: =IF(AND('⚙️ ПАРАМЕТРЫ'!$C$46>0,28<='⚙️ ПАРАМЕТРЫ'!$C$48),ABS(IPMT('⚙️ ПАРАМЕТРЫ'!$C$47/12,28,'⚙️ ПАРАМЕТРЫ'!$C$48,-'⚙️ ПАРАМЕТРЫ'!$C$46)),0) -> 5760.5858 | D32: =IF(AND('⚙️ ПАРАМЕТРЫ'!$C$46>0,28<='⚙️ ПАРАМЕТРЫ'!$C$48),ABS(PPMT('⚙️ ПАРАМЕТРЫ'!$C$47/12,28,'⚙️ ПАРАМЕТРЫ'!$C$48,-'⚙️ ПАРАМЕТРЫ'!$C$46)),0) -> 32429.867 | E32: =IF('⚙️ ПАРАМЕТРЫ'!$C$46>0,E31-D32,0) -> 281783.9
A33: 29 | B33: =IF(AND('⚙️ ПАРАМЕТРЫ'!$C$46>0,29<='⚙️ ПАРАМЕТРЫ'!$C$48),ABS(PMT('⚙️ ПАРАМЕТРЫ'!$C$47/12,'⚙️ ПАРАМЕТРЫ'!$C$48,-'⚙️ ПАРАМЕТРЫ'!$C$46)),0) -> 38190.453 | C33: =IF(AND('⚙️ ПАРАМЕТРЫ'!$C$46>0,29<='⚙️ ПАРАМЕТРЫ'!$C$48),ABS(IPMT('⚙️ ПАРАМЕТРЫ'!$C$47/12,29,'⚙️ ПАРАМЕТРЫ'!$C$48,-'⚙️ ПАРАМЕТРЫ'!$C$46)),0) -> 5166.0382 | D33: =IF(AND('⚙️ ПАРАМЕТРЫ'!$C$46>0,29<='⚙️ ПАРАМЕТРЫ'!$C$48),ABS(PPMT('⚙️ ПАРАМЕТРЫ'!$C$47/12,29,'⚙️ ПАРАМЕТРЫ'!$C$48,-'⚙️ ПАРАМЕТРЫ'!$C$46)),0) -> 33024.415 | E33: =IF('⚙️ ПАРАМЕТРЫ'!$C$46>0,E32-D33,0) -> 248759.49
A34: 30 | B34: =IF(AND('⚙️ ПАРАМЕТРЫ'!$C$46>0,30<='⚙️ ПАРАМЕТРЫ'!$C$48),ABS(PMT('⚙️ ПАРАМЕТРЫ'!$C$47/12,'⚙️ ПАРАМЕТРЫ'!$C$48,-'⚙️ ПАРАМЕТРЫ'!$C$46)),0) -> 38190.453 | C34: =IF(AND('⚙️ ПАРАМЕТРЫ'!$C$46>0,30<='⚙️ ПАРАМЕТРЫ'!$C$48),ABS(IPMT('⚙️ ПАРАМЕТРЫ'!$C$47/12,30,'⚙️ ПАРАМЕТРЫ'!$C$48,-'⚙️ ПАРАМЕТРЫ'!$C$46)),0) -> 4560.5906 | D34: =IF(AND('⚙️ ПАРАМЕТРЫ'!$C$46>0,30<='⚙️ ПАРАМЕТРЫ'!$C$48),ABS(PPMT('⚙️ ПАРАМЕТРЫ'!$C$47/12,30,'⚙️ ПАРАМЕТРЫ'!$C$48,-'⚙️ ПАРАМЕТРЫ'!$C$46)),0) -> 33629.863 | E34: =IF('⚙️ ПАРАМЕТРЫ'!$C$46>0,E33-D34,0) -> 215129.62
A35: 31 | B35: =IF(AND('⚙️ ПАРАМЕТРЫ'!$C$46>0,31<='⚙️ ПАРАМЕТРЫ'!$C$48),ABS(PMT('⚙️ ПАРАМЕТРЫ'!$C$47/12,'⚙️ ПАРАМЕТРЫ'!$C$48,-'⚙️ ПАРАМЕТРЫ'!$C$46)),0) -> 38190.453 | C35: =IF(AND('⚙️ ПАРАМЕТРЫ'!$C$46>0,31<='⚙️ ПАРАМЕТРЫ'!$C$48),ABS(IPMT('⚙️ ПАРАМЕТРЫ'!$C$47/12,31,'⚙️ ПАРАМЕТРЫ'!$C$48,-'⚙️ ПАРАМЕТРЫ'!$C$46)),0) -> 3944.0431 | D35: =IF(AND('⚙️ ПАРАМЕТРЫ'!$C$46>0,31<='⚙️ ПАРАМЕТРЫ'!$C$48),ABS(PPMT('⚙️ ПАРАМЕТРЫ'!$C$47/12,31,'⚙️ ПАРАМЕТРЫ'!$C$48,-'⚙️ ПАРАМЕТРЫ'!$C$46)),0) -> 34246.41 | E35: =IF('⚙️ ПАРАМЕТРЫ'!$C$46>0,E34-D35,0) -> 180883.21
A36: 32 | B36: =IF(AND('⚙️ ПАРАМЕТРЫ'!$C$46>0,32<='⚙️ ПАРАМЕТРЫ'!$C$48),ABS(PMT('⚙️ ПАРАМЕТРЫ'!$C$47/12,'⚙️ ПАРАМЕТРЫ'!$C$48,-'⚙️ ПАРАМЕТРЫ'!$C$46)),0) -> 38190.453 | C36: =IF(AND('⚙️ ПАРАМЕТРЫ'!$C$46>0,32<='⚙️ ПАРАМЕТРЫ'!$C$48),ABS(IPMT('⚙️ ПАРАМЕТРЫ'!$C$47/12,32,'⚙️ ПАРАМЕТРЫ'!$C$48,-'⚙️ ПАРАМЕТРЫ'!$C$46)),0) -> 3316.1923 | D36: =IF(AND('⚙️ ПАРАМЕТРЫ'!$C$46>0,32<='⚙️ ПАРАМЕТРЫ'!$C$48),ABS(PPMT('⚙️ ПАРАМЕТРЫ'!$C$47/12,32,'⚙️ ПАРАМЕТРЫ'!$C$48,-'⚙️ ПАРАМЕТРЫ'!$C$46)),0) -> 34874.261 | E36: =IF('⚙️ ПАРАМЕТРЫ'!$C$46>0,E35-D36,0) -> 146008.95
A37: 33 | B37: =IF(AND('⚙️ ПАРАМЕТРЫ'!$C$46>0,33<='⚙️ ПАРАМЕТРЫ'!$C$48),ABS(PMT('⚙️ ПАРАМЕТРЫ'!$C$47/12,'⚙️ ПАРАМЕТРЫ'!$C$48,-'⚙️ ПАРАМЕТРЫ'!$C$46)),0) -> 38190.453 | C37: =IF(AND('⚙️ ПАРАМЕТРЫ'!$C$46>0,33<='⚙️ ПАРАМЕТРЫ'!$C$48),ABS(IPMT('⚙️ ПАРАМЕТРЫ'!$C$47/12,33,'⚙️ ПАРАМЕТРЫ'!$C$48,-'⚙️ ПАРАМЕТРЫ'!$C$46)),0) -> 2676.8308 | D37: =IF(AND('⚙️ ПАРАМЕТРЫ'!$C$46>0,33<='⚙️ ПАРАМЕТРЫ'!$C$48),ABS(PPMT('⚙️ ПАРАМЕТРЫ'!$C$47/12,33,'⚙️ ПАРАМЕТРЫ'!$C$48,-'⚙️ ПАРАМЕТРЫ'!$C$46)),0) -> 35513.622 | E37: =IF('⚙️ ПАРАМЕТРЫ'!$C$46>0,E36-D37,0) -> 110495.33
A38: 34 | B38: =IF(AND('⚙️ ПАРАМЕТРЫ'!$C$46>0,34<='⚙️ ПАРАМЕТРЫ'!$C$48),ABS(PMT('⚙️ ПАРАМЕТРЫ'!$C$47/12,'⚙️ ПАРАМЕТРЫ'!$C$48,-'⚙️ ПАРАМЕТРЫ'!$C$46)),0) -> 38190.453 | C38: =IF(AND('⚙️ ПАРАМЕТРЫ'!$C$46>0,34<='⚙️ ПАРАМЕТРЫ'!$C$48),ABS(IPMT('⚙️ ПАРАМЕТРЫ'!$C$47/12,34,'⚙️ ПАРАМЕТРЫ'!$C$48,-'⚙️ ПАРАМЕТРЫ'!$C$46)),0) -> 2025.7477 | D38: =IF(AND('⚙️ ПАРАМЕТРЫ'!$C$46>0,34<='⚙️ ПАРАМЕТРЫ'!$C$48),ABS(PPMT('⚙️ ПАРАМЕТРЫ'!$C$47/12,34,'⚙️ ПАРАМЕТРЫ'!$C$48,-'⚙️ ПАРАМЕТРЫ'!$C$46)),0) -> 36164.705 | E38: =IF('⚙️ ПАРАМЕТРЫ'!$C$46>0,E37-D38,0) -> 74330.625
A39: 35 | B39: =IF(AND('⚙️ ПАРАМЕТРЫ'!$C$46>0,35<='⚙️ ПАРАМЕТРЫ'!$C$48),ABS(PMT('⚙️ ПАРАМЕТРЫ'!$C$47/12,'⚙️ ПАРАМЕТРЫ'!$C$48,-'⚙️ ПАРАМЕТРЫ'!$C$46)),0) -> 38190.453 | C39: =IF(AND('⚙️ ПАРАМЕТРЫ'!$C$46>0,35<='⚙️ ПАРАМЕТРЫ'!$C$48),ABS(IPMT('⚙️ ПАРАМЕТРЫ'!$C$47/12,35,'⚙️ ПАРАМЕТРЫ'!$C$48,-'⚙️ ПАРАМЕТРЫ'!$C$46)),0) -> 1362.7281 | D39: =IF(AND('⚙️ ПАРАМЕТРЫ'!$C$46>0,35<='⚙️ ПАРАМЕТРЫ'!$C$48),ABS(PPMT('⚙️ ПАРАМЕТРЫ'!$C$47/12,35,'⚙️ ПАРАМЕТРЫ'!$C$48,-'⚙️ ПАРАМЕТРЫ'!$C$46)),0) -> 36827.725 | E39: =IF('⚙️ ПАРАМЕТРЫ'!$C$46>0,E38-D39,0) -> 37502.9
A40: 36 | B40: =IF(AND('⚙️ ПАРАМЕТРЫ'!$C$46>0,36<='⚙️ ПАРАМЕТРЫ'!$C$48),ABS(PMT('⚙️ ПАРАМЕТРЫ'!$C$47/12,'⚙️ ПАРАМЕТРЫ'!$C$48,-'⚙️ ПАРАМЕТРЫ'!$C$46)),0) -> 38190.453 | C40: =IF(AND('⚙️ ПАРАМЕТРЫ'!$C$46>0,36<='⚙️ ПАРАМЕТРЫ'!$C$48),ABS(IPMT('⚙️ ПАРАМЕТРЫ'!$C$47/12,36,'⚙️ ПАРАМЕТРЫ'!$C$48,-'⚙️ ПАРАМЕТРЫ'!$C$46)),0) -> 687.55317 | D40: =IF(AND('⚙️ ПАРАМЕТРЫ'!$C$46>0,36<='⚙️ ПАРАМЕТРЫ'!$C$48),ABS(PPMT('⚙️ ПАРАМЕТРЫ'!$C$47/12,36,'⚙️ ПАРАМЕТРЫ'!$C$48,-'⚙️ ПАРАМЕТРЫ'!$C$46)),0) -> 37502.9 | E40: =IF('⚙️ ПАРАМЕТРЫ'!$C$46>0,E39-D40,0) -> -4.3655746e-11

Sheet 📑 БАЛАНС
A1: УПРАВЛЕНЧЕСКИЙ БАЛАНС — КОФЕЙНЯ: КОФЕ С СОБОЙ
A2: 📌 Управленческий баланс — контроль ключевых показателей.
B4: Показатель / Квартал | C4: Q1 | D4: Q2 | E4: Q3 | F4: Q4 | G4: Q5 | H4: Q6 | I4: Q7 | J4: Q8 | K4: Q9 | L4: Q10 | M4: Q11 | N4: Q12
B5: АКТИВЫ
B6: Основные средства (ост. стоимость) | C6: =MAX('⚙️ ПАРАМЕТРЫ'!$C$37-'⚙️ ПАРАМЕТРЫ'!$C$42*3,0) -> 1446429 | D6: =MAX('⚙️ ПАРАМЕТРЫ'!$C$37-'⚙️ ПАРАМЕТРЫ'!$C$42*6,0) -> 1392858 | E6: =MAX('⚙️ ПАРАМЕТРЫ'!$C$37-'⚙️ ПАРАМЕТРЫ'!$C$42*9,0) -> 1339287 | F6: =MAX('⚙️ ПАРАМЕТРЫ'!$C$37-'⚙️ ПАРАМЕТРЫ'!$C$42*12,0) -> 1285716 | G6: =MAX('⚙️ ПАРАМЕТРЫ'!$C$37-'⚙️ ПАРАМЕТРЫ'!$C$42*15,0) -> 1232145 | H6: =MAX('⚙️ ПАРАМЕТРЫ'!$C$37-'⚙️ ПАРАМЕТРЫ'!$C$42*18,0) -> 1178574 | I6: =MAX('⚙️ ПАРАМЕТРЫ'!$C$37-'⚙️ ПАРАМЕТРЫ'!$C$42*21,0) -> 1125003 | J6: =MAX('⚙️ ПАРАМЕТРЫ'!$C$37-'⚙️ ПАРАМЕТРЫ'!$C$42*24,0) -> 1071432 | K6: =MAX('⚙️ ПАРАМЕТРЫ'!$C$37-'⚙️ ПАРАМЕТРЫ'!$C$42*27,0) -> 1017861 | L6: =MAX('⚙️ ПАРАМЕТРЫ'!$C$37-'⚙️ ПАРАМЕТРЫ'!$C$42*30,0) -> 964290 | M6: =MAX('⚙️ ПАРАМЕТРЫ'!$C$37-'⚙️ ПАРАМЕТРЫ'!$C$42*33,0) -> 910719 | N6: =MAX('⚙️ ПАРАМЕТРЫ'!$C$37-'⚙️ ПАРАМЕТРЫ'!$C$42*36,0) -> 857148
B7: 💡 CAPEX − амортизация
B8: Депозит за аренду | C8: ='⚙️ ПАРАМЕТРЫ'!$C$23*'⚙️ ПАРАМЕТРЫ'!$C$38 -> 140000 | D8: ='⚙️ ПАРАМЕТРЫ'!$C$23*'⚙️ ПАРАМЕТРЫ'!$C$38 -> 140000 | E8: ='⚙️ ПАРАМЕТРЫ'!$C$23*'⚙️ ПАРАМЕТРЫ'!$C$38 -> 140000 | F8: ='⚙️ ПАРАМЕТРЫ'!$C$23*'⚙️ ПАРАМЕТРЫ'!$C$38 -> 140000 | G8: ='⚙️ ПАРАМЕТРЫ'!$C$23*'⚙️ ПАРАМЕТРЫ'!$C$38 -> 140000 | H8: ='⚙️ ПАРАМЕТРЫ'!$C$23*'⚙️ ПАРАМЕТРЫ'!$C$38 -> 140000 | I8: ='⚙️ ПАРАМЕТРЫ'!$C$23*'⚙️ ПАРАМЕТРЫ'!$C$38 -> 140000 | J8: ='⚙️ ПАРАМЕТРЫ'!$C$23*'⚙️ ПАРАМЕТРЫ'!$C$38 -> 140000 | ... N8: ='⚙️ ПАРАМЕТРЫ'!$C$23*'⚙️ ПАРАМЕТРЫ'!$C$38 -> 140000
B9: 💡 Залог, возвращается при выходе
B10: Оборотный капитал (начальный) | C10: ='⚙️ ПАРАМЕТРЫ'!$C$39 -> 1000000 | D10: ='⚙️ ПАРАМЕТРЫ'!$C$39 -> 1000000 | E10: ='⚙️ ПАРАМЕТРЫ'!$C$39 -> 1000000 | F10: ='⚙️ ПАРАМЕТРЫ'!$C$39 -> 1000000 | G10: ='⚙️ ПАРАМЕТРЫ'!$C$39 -> 1000000 | H10: ='⚙️ ПАРАМЕТРЫ'!$C$39 -> 1000000 | I10: ='⚙️ ПАРАМЕТРЫ'!$C$39 -> 1000000 | J10: ='⚙️ ПАРАМЕТРЫ'!$C$39 -> 1000000 | ... N10: ='⚙️ ПАРАМЕТРЫ'!$C$39 -> 1000000
B11: 💡 Начальный резерв
B12: Оборотные средства (остаток ДС) | C12: ='💰 CASH FLOW'!E29 -> 1970608.6 | D12: ='💰 CASH FLOW'!H29 -> 5551917.3 | E12: ='💰 CASH FLOW'!K29 -> 9058885.9 | F12: ='💰 CASH FLOW'!N29 -> 11698555 | G12: ='💰 CASH FLOW'!Q29 -> 15976849 | H12: ='💰 CASH FLOW'!T29 -> 20255144 | I12: ='💰 CASH FLOW'!W29 -> 24426388 | J12: ='💰 CASH FLOW'!Z29 -> 27607425 | K12: ='💰 CASH FLOW'!AC29 -> 32699414 | L12: ='💰 CASH FLOW'!AF29 -> 37791402 | M12: ='💰 CASH FLOW'!AI29 -> 42767777 | N12: ='💰 CASH FLOW'!AL29 -> 46587986
B13: 💡 Остаток на счёте. < 0 = разрыв
B14: ИТОГО АКТИВЫ | C14: =C6+C8+C10+C12 -> 4557037.6 | D14: =D6+D8+D10+D12 -> 8084775.3 | E14: =E6+E8+E10+E12 -> 11538173 | F14: =F6+F8+F10+F12 -> 14124271 | G14: =G6+G8+G10+G12 -> 18348994 | H14: =H6+H8+H10+H12 -> 22573718 | I14: =I6+I8+I10+I12 -> 26691391 | J14: =J6+J8+J10+J12 -> 29818857 | ... N14: =N6+N8+N10+N12 -> 48585134
B15: ПАССИВЫ И КАПИТАЛ
B16: Задолженность по кредиту | C16: =IF('⚙️ ПАРАМЕТРЫ'!$C$46=0,0,MAX(ABS(FV('⚙️ ПАРАМЕТРЫ'!$C$47/12,3,'⚙️ ПАРАМЕТРЫ'!$C$49,-'⚙️ ПАРАМЕТРЫ'!$C$46)),0)) -> 939329.82 | D16: =IF('⚙️ ПАРАМЕТРЫ'!$C$46=0,0,MAX(ABS(FV('⚙️ ПАРАМЕТРЫ'!$C$47/12,6,'⚙️ ПАРАМЕТРЫ'!$C$49,-'⚙️ ПАРАМЕТРЫ'!$C$46)),0)) -> 875261.24 | E16: =IF('⚙️ ПАРАМЕТРЫ'!$C$46=0,0,MAX(ABS(FV('⚙️ ПАРАМЕТРЫ'!$C$47/12,9,'⚙️ ПАРАМЕТРЫ'!$C$49,-'⚙️ ПАРАМЕТРЫ'!$C$46)),0)) -> 807603.89 | F16: =IF('⚙️ ПАРАМЕТРЫ'!$C$46=0,0,MAX(ABS(FV('⚙️ ПАРАМЕТРЫ'!$C$47/12,12,'⚙️ ПАРАМЕТРЫ'!$C$49,-'⚙️ ПАРАМЕТРЫ'!$C$46)),0)) -> 736156.74 | G16: =IF('⚙️ ПАРАМЕТРЫ'!$C$46=0,0,MAX(ABS(FV('⚙️ ПАРАМЕТРЫ'!$C$47/12,15,'⚙️ ПАРАМЕТРЫ'!$C$49,-'⚙️ ПАРАМЕТРЫ'!$C$46)),0)) -> 660707.52 | H16: =IF('⚙️ ПАРАМЕТРЫ'!$C$46=0,0,MAX(ABS(FV('⚙️ ПАРАМЕТРЫ'!$C$47/12,18,'⚙️ ПАРАМЕТРЫ'!$C$49,-'⚙️ ПАРАМЕТРЫ'!$C$46)),0)) -> 581032.04 | I16: =IF('⚙️ ПАРАМЕТРЫ'!$C$46=0,0,MAX(ABS(FV('⚙️ ПАРАМЕТРЫ'!$C$47/12,21,'⚙️ ПАРАМЕТРЫ'!$C$49,-'⚙️ ПАРАМЕТРЫ'!$C$46)),0)) -> 496893.59 | J16: =IF('⚙️ ПАРАМЕТРЫ'!$C$46=0,0,MAX(ABS(FV('⚙️ ПАРАМЕТРЫ'!$C$47/12,24,'⚙️ ПАРАМЕТРЫ'!$C$49,-'⚙️ ПАРАМЕТРЫ'!$C$46)),0)) -> 408042.16 | K16: =IF('⚙️ ПАРАМЕТРЫ'!$C$46=0,0,MAX(ABS(FV('⚙️ ПАРАМЕТРЫ'!$C$47/12,27,'⚙️ ПАРАМЕТРЫ'!$C$49,-'⚙️ ПАРАМЕТРЫ'!$C$46)),0)) -> 314213.77 | L16: =IF('⚙️ ПАРАМЕТРЫ'!$C$46=0,0,MAX(ABS(FV('⚙️ ПАРАМЕТРЫ'!$C$47/12,30,'⚙️ ПАРАМЕТРЫ'!$C$49,-'⚙️ ПАРАМЕТРЫ'!$C$46)),0)) -> 215129.62 | M16: =IF('⚙️ ПАРАМЕТРЫ'!$C$46=0,0,MAX(ABS(FV('⚙️ ПАРАМЕТРЫ'!$C$47/12,33,'⚙️ ПАРАМЕТРЫ'!$C$49,-'⚙️ ПАРАМЕТРЫ'!$C$46)),0)) -> 110495.33 | N16: =IF('⚙️ ПАРАМЕТРЫ'!$C$46=0,0,MAX(ABS(FV('⚙️ ПАРАМЕТРЫ'!$C$47/12,36,'⚙️ ПАРАМЕТРЫ'!$C$49,-'⚙️ ПАРАМЕТРЫ'!$C$46)),0)) -> 6.9849193e-10
B17: 💡 Остаток долга
B18: Собственный капитал (инвестиции) | C18: ='⚙️ ПАРАМЕТРЫ'!$C$41-'⚙️ ПАРАМЕТРЫ'!$C$46 -> 1640000 | D18: ='⚙️ ПАРАМЕТРЫ'!$C$41-'⚙️ ПАРАМЕТРЫ'!$C$46 -> 1640000 | E18: ='⚙️ ПАРАМЕТРЫ'!$C$41-'⚙️ ПАРАМЕТРЫ'!$C$46 -> 1640000 | F18: ='⚙️ ПАРАМЕТРЫ'!$C$41-'⚙️ ПАРАМЕТРЫ'!$C$46 -> 1640000 | G18: ='⚙️ ПАРАМЕТРЫ'!$C$41-'⚙️ ПАРАМЕТРЫ'!$C$46 -> 1640000 | H18: ='⚙️ ПАРАМЕТРЫ'!$C$41-'⚙️ ПАРАМЕТРЫ'!$C$46 -> 1640000 | I18: ='⚙️ ПАРАМЕТРЫ'!$C$41-'⚙️ ПАРАМЕТРЫ'!$C$46 -> 1640000 | J18: ='⚙️ ПАРАМЕТРЫ'!$C$41-'⚙️ ПАРАМЕТРЫ'!$C$46 -> 1640000 | ... N18: ='⚙️ ПАРАМЕТРЫ'!$C$41-'⚙️ ПАРАМЕТРЫ'!$C$46 -> 1640000
B19: Нераспределённая прибыль | C19: =SUM('📈 P&L'!C38:E38) -> 1977707.8 | D19: =SUM('📈 P&L'!C38:H38) -> 5569514 | E19: =SUM('📈 P&L'!C38:K38) -> 9090569 | F19: =SUM('📈 P&L'!C38:N38) -> 11748114 | G19: =SUM('📈 P&L'!C38:Q38) -> 16048287 | H19: =SUM('📈 P&L'!C38:T38) -> 20352686 | I19: =SUM('📈 P&L'!C38:W38) -> 24554498 | J19: =SUM('📈 P&L'!C38:Z38) -> 27770815 | K19: =SUM('📈 P&L'!C38:AC38) -> 32903061 | L19: =SUM('📈 P&L'!C38:AF38) -> 38040563 | M19: =SUM('📈 P&L'!C38:AI38) -> 43068001 | N19: =SUM('📈 P&L'!C38:AL38) -> 46945134
B20: 💡 Накопленная ЧП
B21: ИТОГО ПАССИВЫ И КАПИТАЛ | C21: =C16+C18+C19 -> 4557037.6 | D21: =D16+D18+D19 -> 8084775.3 | E21: =E16+E18+E19 -> 11538173 | F21: =F16+F18+F19 -> 14124271 | G21: =G16+G18+G19 -> 18348994 | H21: =H16+H18+H19 -> 22573718 | I21: =I16+I18+I19 -> 26691391 | J21: =J16+J18+J19 -> 29818857 | ... N21: =N16+N18+N19 -> 48585134
B23: КОНТРОЛЬ: Активы - Пассивы | C23: =C14-C21 -> 0 | D23: =D14-D21 -> 0 | E23: =E14-E21 -> 0 | F23: =F14-F21 -> 0 | G23: =G14-G21 -> 0 | H23: =H14-H21 -> 0 | I23: =I14-I21 -> 0 | J23: =J14-J21 -> 0 | ... N23: =N14-N21 -> 0
B24: 💡 = 0 → баланс ОК
B26: 📌 Управленческий баланс. Для бухгалтерской отчётности (НСФО/МСФО) обратитесь к профессиональному бухгалтеру.
B27: ZEREK Financial Model | @zerekai_bot

Sheet 🔄 СЦЕНАРИИ
A1: СЦЕНАРНОЕ ВЛИЯНИЕ КЛЮЧЕВЫХ ФАКТОРОВ
A2: 📌 Как изменится среднемесячная прибыль 2-го года при изменении ОДНОГО параметра. Остальные — фиксированы. Основано на реальных связях модели.
B4: Фактор | C4: -30% | D4: -10% | E4: Базовый | F4: +10% | G4: +30%
B5: Средний чек | C5: =AVERAGE('📈 P&L'!O38:Z38)+AVERAGE('📈 P&L'!O12:Z12)*(-0.3)*(1-'⚙️ ПАРАМЕТРЫ'!$C$19-'⚙️ ПАРАМЕТРЫ'!$C$20-'⚙️ ПАРАМЕТРЫ'!$C$8) -> 733740.15 | D5: =AVERAGE('📈 P&L'!O38:Z38)+AVERAGE('📈 P&L'!O12:Z12)*(-0.1)*(1-'⚙️ ПАРАМЕТРЫ'!$C$19-'⚙️ ПАРАМЕТРЫ'!$C$20-'⚙️ ПАРАМЕТРЫ'!$C$8) -> 1134730.1 | E5: =AVERAGE('📈 P&L'!O38:Z38) -> 1335225.1 | F5: =AVERAGE('📈 P&L'!O38:Z38)+AVERAGE('📈 P&L'!O12:Z12)*(0.1)*(1-'⚙️ ПАРАМЕТРЫ'!$C$19-'⚙️ ПАРАМЕТРЫ'!$C$20-'⚙️ ПАРАМЕТРЫ'!$C$8) -> 1535720.1 | G5: =AVERAGE('📈 P&L'!O38:Z38)+AVERAGE('📈 P&L'!O12:Z12)*(0.3)*(1-'⚙️ ПАРАМЕТРЫ'!$C$19-'⚙️ ПАРАМЕТРЫ'!$C$20-'⚙️ ПАРАМЕТРЫ'!$C$8) -> 1936710
B6: 💡 Чек влияет на выручку напрямую. При падении чека на 30% выручка падает на 30%, но постоянные расходы остаются — прибыль падает сильнее.
B7: Аренда помещения | C7: =AVERAGE('📈 P&L'!O38:Z38)-'⚙️ ПАРАМЕТРЫ'!$C$23*0.3*12 -> 1083225.1 | D7: =AVERAGE('📈 P&L'!O38:Z38)-'⚙️ ПАРАМЕТРЫ'!$C$23*0.1*12 -> 1251225.1 | E7: =AVERAGE('📈 P&L'!O38:Z38) -> 1335225.1 | F7: =AVERAGE('📈 P&L'!O38:Z38)+'⚙️ ПАРАМЕТРЫ'!$C$23*0.1*12 -> 1419225.1 | G7: =AVERAGE('📈 P&L'!O38:Z38)+'⚙️ ПАРАМЕТРЫ'!$C$23*0.3*12 -> 1587225.1
B8: 💡 Аренда — фиксированный расход. Рост аренды на 30% = минус аренда×0.3×12 из прибыли. Прямой линейный эффект.
B9: Себестоимость продукта | C9: =AVERAGE('📈 P&L'!O38:Z38)+AVERAGE('📈 P&L'!O12:Z12)*0.3 -> 2354691.1 | D9: =AVERAGE('📈 P&L'!O38:Z38)+AVERAGE('📈 P&L'!O12:Z12)*0.1 -> 1675047.1 | E9: =AVERAGE('📈 P&L'!O38:Z38) -> 1335225.1 | F9: =AVERAGE('📈 P&L'!O38:Z38)-AVERAGE('📈 P&L'!O12:Z12)*0.1 -> 995403.09 | G9: =AVERAGE('📈 P&L'!O38:Z38)-AVERAGE('📈 P&L'!O12:Z12)*0.3 -> 315759.09
B10: 💡 Рост закупочных цен на 10% напрямую снижает валовую прибыль. Это переменный расход — влияет на каждую единицу проданного товара.
B11: Аренда помещения | C11: =AVERAGE('📈 P&L'!O38:Z38)+'⚙️ ПАРАМЕТРЫ'!$C$23*0.3 -> 1356225.1 | D11: =AVERAGE('📈 P&L'!O38:Z38)+'⚙️ ПАРАМЕТРЫ'!$C$23*0.1 -> 1342225.1 | E11: =AVERAGE('📈 P&L'!O38:Z38) -> 1335225.1 | F11: =AVERAGE('📈 P&L'!O38:Z38)-'⚙️ ПАРАМЕТРЫ'!$C$23*0.1 -> 1328225.1 | G11: =AVERAGE('📈 P&L'!O38:Z38)-'⚙️ ПАРАМЕТРЫ'!$C$23*0.3 -> 1314225.1
B12: 💡 Аренда — фиксированный расход. Рост аренды на X ₸ снижает прибыль ровно на X ₸. Линейная зависимость.
B13: ФОТ (зарплаты) | C13: =AVERAGE('📈 P&L'!O38:Z38)+'⚙️ ПАРАМЕТРЫ'!$C$43*0.3 -> 1347225.1 | D13: =AVERAGE('📈 P&L'!O38:Z38)+'⚙️ ПАРАМЕТРЫ'!$C$43*0.1 -> 1339225.1 | E13: =AVERAGE('📈 P&L'!O38:Z38) -> 1335225.1 | F13: =AVERAGE('📈 P&L'!O38:Z38)-'⚙️ ПАРАМЕТРЫ'!$C$43*0.1 -> 1331225.1 | G13: =AVERAGE('📈 P&L'!O38:Z38)-'⚙️ ПАРАМЕТРЫ'!$C$43*0.3 -> 1323225.1
B14: 💡 ФОТ — фиксированный расход. Дополнительный сотрудник = минус его зарплата × 1.175 из прибыли напрямую.
B16: КАК ЧИТАТЬ ТАБЛИЦУ
B17: Пример: если средний чек упадёт на 30%, ваша среднемесячная прибыль 2-го года составит значение в столбце «-30%». Если вырастет на 10% — значение в столбце «+10%». Базовый столбец = текущий прогноз без изменений.
B19: 💡 Это упрощённый однофакторный анализ. Изменяется один параметр, остальные фиксированы. Для многофакторного анализа используйте Data Table в Excel (Данные → Таблица данных).
B21: ZEREK Financial Model | @zerekai_bot

Sheet ✅ ПРОВЕРКА
A1: ПРОВЕРОЧНЫЙ ЧЕК-ЛИСТ МОДЕЛИ
A2: 📌 Автоматические проверки. Если видите ❌ или ⚠️ — обратите внимание.
A4: Проверка | B4: Формула/Значение | C4: Порог | D4: Статус | E4: Что делать
A5: Кассовый разрыв? | B5: =MIN('💰 CASH FLOW'!C22:AL22) -> -1577850.5 | C5: MIN(ДС) < 0 | D5: =IF(MIN('💰 CASH FLOW'!C22:AL22)<0,"❌ ДА — кассовый разрыв!","✅ НЕТ") -> ❌ ДА — кассовый разрыв! | E5: → Увеличьте оборотный капитал или кредитную линию
A6: Убыток > 6 мес подряд? | B6: =COUNTIF('📈 P&L'!C38:AL38,"<0") -> 0 | C6: > 6 убыточных месяцев | D6: =IF(COUNTIF('📈 P&L'!C38:AL38,"<0")>6,"⚠️ Убыточных мес: "&COUNTIF('📈 P&L'!C38:AL38,"<0"),"✅ OK") -> ✅ OK | E6: → Снизьте постоянные расходы или скорректируйте ramp-up
A7: Себестоимость > 50%? | B7: ='⚙️ ПАРАМЕТРЫ'!C19 -> 0.35 | C7: > 50% | D7: =IF('⚙️ ПАРАМЕТРЫ'!C19>0.5,"⚠️ COGS слишком высокий: "&TEXT('⚙️ ПАРАМЕТРЫ'!C19,"0%"),"✅ OK: "&TEXT('⚙️ ПАРАМЕТРЫ'!C19,"0%")) -> ✅ OK: 35% | E7: → Смените поставщиков или пересмотрите ассортимент
A8: Аренда > 25% выручки (Г2)? | B8: =SUM('📈 P&L'!O24:Z24)/SUM('📈 P&L'!O12:Z12) -> 0.022658921 | C8: > 25% | D8: =IF(SUM('📈 P&L'!O24:Z24)/SUM('📈 P&L'!O12:Z12)>0.25,"⚠️ Доля аренды высока","✅ OK") -> ✅ OK | E8: → Торгуйтесь по аренде или ищите другую локацию
A9: ФОТ > 30% выручки? | B9: =SUM('📈 P&L'!O18:Z18)/SUM('📈 P&L'!O12:Z12) -> 0.12712538 | C9: > 30% | D9: =IF(SUM('📈 P&L'!O18:Z18)/SUM('📈 P&L'!O12:Z12)>0.3,"⚠️ Доля ФОТ высока","✅ OK") -> ✅ OK | E9: → Оптимизируйте штат или повысьте выручку
A10: Ramp-up М1 > 70%? | B10: ='📊 ДОПУЩЕНИЯ'!C17 -> 0.4 | C10: М1 > 70% | D10: =IF('📊 ДОПУЩЕНИЯ'!C17>0.7,"⚠️ Ramp-up М1 слишком оптимистичен: "&TEXT('📊 ДОПУЩЕНИЯ'!C17,"0%"),"✅ OK: "&TEXT('📊 ДОПУЩЕНИЯ'!C17,"0%")) -> ✅ OK: 40% | E10: → Сделайте ramp-up реалистичнее (М1 ≤ 50%)
A11: Формула P&L корректна? | B11: =ABS('📈 P&L'!C12-'📈 P&L'!C10*'📈 P&L'!C11*'⚙️ ПАРАМЕТРЫ'!$C$14) -> 0 | C11: Расхождение > 1 ₸ | D11: =IF(ABS('📈 P&L'!C12-'📈 P&L'!C10*'📈 P&L'!C11*'⚙️ ПАРАМЕТРЫ'!$C$14)>1,"❌ ФОРМУЛА СЛОМАНА","✅ OK") -> ✅ OK | E11: → Пересоберите модель, проверьте исходные данные
A12: Баланс сходится? | B12: {=MAX(ABS('📑 БАЛАНС'!C24:N24))} -> 0 | C12: Расхождение > 100 ₸ | D12: {=IF(MAX(ABS('📑 БАЛАНС'!C24:N24))>100,"❌ БАЛАНС НЕ СХОДИТСЯ","✅ OK")} -> ✅ OK | E12: → Ошибка в Cash Flow или Балансе — проверьте связи
A13: Окупаемость > 36 мес? | B13: ='🎯 ДАШБОРД'!D5 -> 4 | C13: > 36 мес | D13: =IF(ISNUMBER('🎯 ДАШБОРД'!D5),IF('🎯 ДАШБОРД'!D5>36,"⚠️ Не окупается за 3 года","✅ OK: "&'🎯 ДАШБОРД'!D5&" мес"),"⚠️ "&'🎯 ДАШБОРД'!D5) -> ✅ OK: 4 мес | E13: → Снизьте CAPEX, поднимите чек или возьмите кредит
A14: NPV отрицательный? | B14: ='🎯 ДАШБОРД'!B5 -> 31863328 | C14: < 0 | D14: =IF('🎯 ДАШБОРД'!B5<0,"⚠️ NPV отрицательный: "&TEXT('🎯 ДАШБОРД'!B5,"#,##0"),"✅ OK: "&TEXT('🎯 ДАШБОРД'!B5,"#,##0")) -> ✅ OK: 31863327,789 | E14: → Пересмотрите допущения — проект разрушает стоимость
A16: ZEREK Financial Model | @zerekai_bot | zerek.cc

Sheet 🔥 СТРЕСС-ТЕСТ
A1: СТРЕСС-ТЕСТ ФИНАНСОВОЙ МОДЕЛИ — КОФЕЙНЯ
A2: 📌 4 стресс-сценария: как кофейня переживёт снижение трафика, чека, рост аренды и себестоимости. Все формулы — живые, пересчитываются из ⚙️ ПАРАМЕТРЫ.
B4: ПАРАМЕТРЫ СТРЕСС-СЦЕНАРИЕВ | C4: Базовый | D4: Мягкий стресс | E4: Умеренный стресс | F4: Жёсткий стресс | G4: Критический | I4: Описание сценариев
B5: 💡 Мягкий: сезонный спад или мелкие неурядицы. Умеренный: конкурент рядом, рост цен. Жёсткий: кризис + конкуренция. Критический: всё плохо сразу.
B7: Шок трафика (Δ клиентов) | C7: 0 | D7: -0.1 | E7: -0.2 | F7: -0.35 | G7: -0.5 | I7: −10% лёгкий спад → −50% катастрофа
B8: Шок среднего чека (Δ чека) | C8: 0 | D8: -0.05 | E8: -0.1 | F8: -0.2 | G8: -0.3 | I8: Снижение чека из-за конкуренции/кризиса
B9: Рост себестоимости (Δ COGS %) | C9: 0 | D9: 0.03 | E9: 0.05 | F9: 0.08 | G9: 0.12 | I9: Рост закупочных цен на кофе, молоко
B10: Рост аренды (Δ аренда) | C10: 0 | D10: 0.1 | E10: 0.2 | F10: 0.3 | G10: 0.5 | I10: Арендодатель повышает ставку
B11: Рост ФОТ (Δ зарплата) | C11: 0 | D11: 0.05 | E11: 0.1 | F11: 0.15 | G11: 0.25 | I11: Рост зарплат / доп. сотрудник
B13: РАСЧЁТНЫЕ ПАРАМЕТРЫ ПРИ СТРЕССЕ (Год 2, среднемесячно)
B14: Клиентов/день | C14: ='⚙️ ПАРАМЕТРЫ'!C13 -> 70 | D14: =ROUND('⚙️ ПАРАМЕТРЫ'!C13*(1+D7),0) -> 63 | E14: =ROUND('⚙️ ПАРАМЕТРЫ'!C13*(1+E7),0) -> 56 | F14: =ROUND('⚙️ ПАРАМЕТРЫ'!C13*(1+F7),0) -> 46 | G14: =ROUND('⚙️ ПАРАМЕТРЫ'!C13*(1+G7),0) -> 35
B15: Средний чек, ₸ | C15: ='⚙️ ПАРАМЕТРЫ'!C12 -> 1400 | D15: =ROUND('⚙️ ПАРАМЕТРЫ'!C12*(1+D8),0) -> 1330 | E15: =ROUND('⚙️ ПАРАМЕТРЫ'!C12*(1+E8),0) -> 1260 | F15: =ROUND('⚙️ ПАРАМЕТРЫ'!C12*(1+F8),0) -> 1120 | G15: =ROUND('⚙️ ПАРАМЕТРЫ'!C12*(1+G8),0) -> 980
B16: Себестоимость, % | C16: ='⚙️ ПАРАМЕТРЫ'!C19 -> 0.35 | D16: ='⚙️ ПАРАМЕТРЫ'!C19+D9 -> 0.38 | E16: ='⚙️ ПАРАМЕТРЫ'!C19+E9 -> 0.4 | F16: ='⚙️ ПАРАМЕТРЫ'!C19+F9 -> 0.43 | G16: ='⚙️ ПАРАМЕТРЫ'!C19+G9 -> 0.47
B17: Аренда, ₸/мес | C17: ='⚙️ ПАРАМЕТРЫ'!C23 -> 70000 | D17: =ROUND('⚙️ ПАРАМЕТРЫ'!C23*(1+D10),0) -> 77000 | E17: =ROUND('⚙️ ПАРАМЕТРЫ'!C23*(1+E10),0) -> 84000 | F17: =ROUND('⚙️ ПАРАМЕТРЫ'!C23*(1+F10),0) -> 91000 | G17: =ROUND('⚙️ ПАРАМЕТРЫ'!C23*(1+G10),0) -> 105000
B18: ФОТ + налоги, ₸/мес | C18: ='📊 ДОПУЩЕНИЯ'!C62 -> 440000 | D18: =ROUND('📊 ДОПУЩЕНИЯ'!C62*(1+D11),0) -> 462000 | E18: =ROUND('📊 ДОПУЩЕНИЯ'!C62*(1+E11),0) -> 484000 | F18: =ROUND('📊 ДОПУЩЕНИЯ'!C62*(1+F11),0) -> 506000 | G18: =ROUND('📊 ДОПУЩЕНИЯ'!C62*(1+G11),0) -> 550000
B20: P&L ПРИ СТРЕССЕ (Год 2, среднемесячно)
B21: Выручка | C21: =AVERAGE('📈 P&L'!O12:Z12) -> 3398220 | D21: =ROUND(C21*(1+D7)*(1+D8),0) -> 2905478 | E21: =ROUND(C21*(1+E7)*(1+E8),0) -> 2446718 | F21: =ROUND(C21*(1+F7)*(1+F8),0) -> 1767074 | G21: =ROUND(C21*(1+G7)*(1+G8),0) -> 1189377
B22: Себестоимость | C22: =ROUND(C21*C16,0) -> 1189377 | D22: =ROUND(D21*D16,0) -> 1104082 | E22: =ROUND(E21*E16,0) -> 978687 | F22: =ROUND(F21*F16,0) -> 759842 | G22: =ROUND(G21*G16,0) -> 559007
B23: Потери/списания | C23: =ROUND(C21*'⚙️ ПАРАМЕТРЫ'!C20,0) -> 101947 | D23: =ROUND(D21*'⚙️ ПАРАМЕТРЫ'!C20,0) -> 87164 | E23: =ROUND(E21*'⚙️ ПАРАМЕТРЫ'!C20,0) -> 73402 | F23: =ROUND(F21*'⚙️ ПАРАМЕТРЫ'!C20,0) -> 53012 | G23: =ROUND(G21*'⚙️ ПАРАМЕТРЫ'!C20,0) -> 35681
B24: ВАЛОВАЯ ПРИБЫЛЬ | C24: =C21-C22-C23 -> 2106896 | D24: =D21-D22-D23 -> 1714232 | E24: =E21-E22-E23 -> 1394629 | F24: =F21-F22-F23 -> 954220 | G24: =G21-G22-G23 -> 594689
B26: ФОТ + налоги работодателя | C26: =C18 -> 440000 | D26: =D18 -> 462000 | E26: =E18 -> 484000 | F26: =F18 -> 506000 | G26: =G18 -> 550000
B27: Аренда | C27: =C17 -> 70000 | D27: =D17 -> 77000 | E27: =E17 -> 84000 | F27: =F17 -> 91000 | G27: =G17 -> 105000
B28: Прочие постоянные | C28: =AVERAGE('📈 P&L'!O25:Z25)+AVERAGE('📈 P&L'!O26:Z26)+AVERAGE('📈 P&L'!O27:Z27)+AVERAGE('📈 P&L'!O28:Z28)+AVERAGE('📈 P&L'!O29:Z29) -> 88820 | D28: =C28 -> 88820 | E28: =C28 -> 88820 | F28: =C28 -> 88820 | G28: =C28 -> 88820
B29: Итого постоянные | C29: =C26+C27+C28 -> 598820 | D29: =D26+D27+D28 -> 627820 | E29: =E26+E27+E28 -> 656820 | F29: =F26+F27+F28 -> 685820 | G29: =G26+G27+G28 -> 743820
B30: EBITDA | C30: =C24-C29 -> 1508076 | D30: =D24-D29 -> 1086412 | E30: =E24-E29 -> 737809 | F30: =F24-F29 -> 268400 | G30: =G24-G29 -> -149131
B31: Амортизация | C31: ='⚙️ ПАРАМЕТРЫ'!C42 -> 17857 | D31: ='⚙️ ПАРАМЕТРЫ'!C42 -> 17857 | E31: ='⚙️ ПАРАМЕТРЫ'!C42 -> 17857 | F31: ='⚙️ ПАРАМЕТРЫ'!C42 -> 17857 | G31: ='⚙️ ПАРАМЕТРЫ'!C42 -> 17857
B32: Проценты по кредиту | C32: =AVERAGE('📈 P&L'!O34:Z34) -> 10847.572 | D32: =C32 -> 10847.572 | E32: =C32 -> 10847.572 | F32: =C32 -> 10847.572 | G32: =C32 -> 10847.572
B33: Налог (УСН 3%) | C33: =ROUND(MAX(C21,0)*'📊 ДОПУЩЕНИЯ'!C58,0) -> 101947 | D33: =ROUND(MAX(D21,0)*'📊 ДОПУЩЕНИЯ'!C58,0) -> 87164 | E33: =ROUND(MAX(E21,0)*'📊 ДОПУЩЕНИЯ'!C58,0) -> 73402 | F33: =ROUND(MAX(F21,0)*'📊 ДОПУЩЕНИЯ'!C58,0) -> 53012 | G33: =ROUND(MAX(G21,0)*'📊 ДОПУЩЕНИЯ'!C58,0) -> 35681
B35: ЧИСТАЯ ПРИБЫЛЬ | C35: =C30-C31-C32-C33 -> 1377424.4 | D35: =D30-D31-D32-D33 -> 970543.43 | E35: =E30-E31-E32-E33 -> 635702.43 | F35: =F30-F31-F32-F33 -> 186683.43 | G35: =G30-G31-G32-G33 -> -213516.57
B37: КЛЮЧЕВЫЕ МЕТРИКИ
B38: Рентабельность чистая | C38: =IFERROR(C35/C21,0) -> 0.40533704 | D38: =IFERROR(D35/D21,0) -> 0.33403916 | E38: =IFERROR(E35/E21,0) -> 0.25981843 | F38: =IFERROR(F35/F21,0) -> 0.10564551 | G38: =IFERROR(G35/G21,0) -> -0.17951967 | I38: Доля чистой прибыли от выручки
B39: Дельта от базы, ₸/мес | C39: - | D39: =D35-C35 -> -406881 | E39: =E35-C35 -> -741722 | F39: =F35-C35 -> -1190741 | G39: =G35-C35 -> -1590941
B40: Дельта от базы, % | C40: - | D40: =IFERROR(D39/C35,0) -> -0.29539261 | E40: =IFERROR(E39/C35,0) -> -0.53848471 | F40: =IFERROR(F39/C35,0) -> -0.8644692 | G40: =IFERROR(G39/C35,0) -> -1.1550115
B41: Окупаемость инвестиций, мес | C41: =IFERROR(ROUND('⚙️ ПАРАМЕТРЫ'!C41/C35,0),"∞") -> 2 | D41: =IFERROR(IF(D35<=0,"∞",ROUND('⚙️ ПАРАМЕТРЫ'!C41/D35,0)),"∞") -> 3 | E41: =IFERROR(IF(E35<=0,"∞",ROUND('⚙️ ПАРАМЕТРЫ'!C41/E35,0)),"∞") -> 4 | F41: =IFERROR(IF(F35<=0,"∞",ROUND('⚙️ ПАРАМЕТРЫ'!C41/F35,0)),"∞") -> 14 | G41: =IFERROR(IF(G35<=0,"∞",ROUND('⚙️ ПАРАМЕТРЫ'!C41/G35,0)),"∞") -> ∞ | I41: Простая окупаемость (инвест. / прибыль)
B42: Запас прочности выручки | C42: =IFERROR(1-(C29+C31+C32+C33)/C24,0) -> 0.65376954 | D42: =IFERROR(1-(D29+D31+D32+D33)/D24,0) -> 0.56616807 | E42: =IFERROR(1-(E29+E31+E32+E33)/E24,0) -> 0.45582189 | F42: =IFERROR(1-(F29+F31+F32+F33)/F24,0) -> 0.19563982 | G42: =IFERROR(1-(G29+G31+G32+G33)/G24,0) -> -0.35903905 | I42: Насколько можно ещё просесть до убытка
B44: ОДНОФАКТОРНЫЙ АНАЛИЗ ЧУВСТВИТЕЛЬНОСТИ (Торнадо)
B45: 💡 Какой фактор сильнее всего влияет на прибыль? Шок −умеренный: каждый фактор отдельно, остальные = база.
B46: Фактор | C46: Шок | D46: Прибыль при шоке | E46: Дельта, ₸ | F46: Дельта, % | G46: Ранг
B47: Трафик − 20% | C47: =E7 -> -0.2 | D47: =ROUND(C21*(1+E7)*(1-C16-'⚙️ ПАРАМЕТРЫ'!C20)-C29-C31-C32-ROUND(C21*(1+E7)*'📊 ДОПУЩЕНИЯ'!C58,0),0) -> 976436 | E47: =D47-C35 -> -400988.43 | F47: =IFERROR(E47/C35,0) -> -0.29111465 | G47: {=SUMPRODUCT((ABS($E$47:$E$51)>ABS(E47))*1)+1} -> 1
B48: Чек − 10% | C48: =E8 -> -0.1 | D48: =ROUND(C21*(1+E8)*(1-C16-'⚙️ ПАРАМЕТРЫ'!C20)-C29-C31-C32-ROUND(C21*(1+E8)*'📊 ДОПУЩЕНИЯ'!C58,0),0) -> 1176930 | E48: =D48-C35 -> -200494.43 | F48: =IFERROR(E48/C35,0) -> -0.14555748 | G48: {=SUMPRODUCT((ABS($E$47:$E$51)>ABS(E48))*1)+1} -> 2
B49: Себестоимость + 5 p.p. | C49: =E9 -> 0.05 | D49: =ROUND(C21*(1-C16-E9-'⚙️ ПАРАМЕТРЫ'!C20)-C29-C31-C32-ROUND(C21*'📊 ДОПУЩЕНИЯ'!C58,0),0) -> 1207514 | E49: =D49-C35 -> -169910.43 | F49: =IFERROR(E49/C35,0) -> -0.12335372 | G49: {=SUMPRODUCT((ABS($E$47:$E$51)>ABS(E49))*1)+1} -> 3
B50: Аренда + 20% | C50: =E10 -> 0.2 | D50: =C35-ROUND('⚙️ ПАРАМЕТРЫ'!C23*E10,0) -> 1363424.4 | E50: =D50-C35 -> -14000 | F50: =IFERROR(E50/C35,0) -> -0.010163897 | G50: {=SUMPRODUCT((ABS($E$47:$E$51)>ABS(E50))*1)+1} -> 5
B51: ФОТ + 10% | C51: =E11 -> 0.1 | D51: =C35-ROUND('📊 ДОПУЩЕНИЯ'!C62*E11,0) -> 1333424.4 | E51: =D51-C35 -> -44000 | F51: =IFERROR(E51/C35,0) -> -0.031943676 | G51: {=SUMPRODUCT((ABS($E$47:$E$51)>ABS(E51))*1)+1} -> 4
B53: ТОЧКА БЕЗУБЫТОЧНОСТИ (БЕЗ СТРЕССА)
B54: 💡 При каком минимуме клиентов кофейня выходит в ноль? Формула: постоянные / (чек × маржа × дни). Маржа = 1 − COGS% − потери% − налог%.
B56: Параметр | C56: Значение | D56: Ед.
B57: Маржа контрибуции на 1 клиента | C57: =ROUND('⚙️ ПАРАМЕТРЫ'!C12*(1-'⚙️ ПАРАМЕТРЫ'!C19-'⚙️ ПАРАМЕТРЫ'!C20-'📊 ДОПУЩЕНИЯ'!C58),0) -> 826 | D57: ₸/клиент | E57: = чек × (1 − COGS% − потери% − налог%)
B58: Постоянные + аморт. + %% в месяц | C58: =C29+C31+C32 -> 627524.57 | D58: ₸/мес
B59: Безубыточность, клиентов/день | C59: =IFERROR(ROUNDUP(C58/(C57*'⚙️ ПАРАМЕТРЫ'!C14),0),"∞") -> 26 | D59: чел/день | E59: = постоянные / (маржа × дни)
B60: Запас до безубыточности | C60: =IFERROR(1-C59/'⚙️ ПАРАМЕТРЫ'!C13,0) -> 0.62857143 | D60: % | E60: Выручка может упасть на столько до нуля прибыли
B62: 🔥 СТРЕСС-СЦЕНАРИЙ БЕЗУБЫТОЧНОСТИ
B63: 💡 При каждом сценарии: минимум клиентов для выхода в ноль с учётом стресс-параметров.
C64: Базовый | D64: Мягкий | E64: Умеренный | F64: Жёсткий | G64: Критический
B65: Маржа/клиент (с уч. стресса), ₸ | C65: =C57 -> 826 | D65: =ROUND('⚙️ ПАРАМЕТРЫ'!C12*(1+D8)*(1-'⚙️ ПАРАМЕТРЫ'!C19-D9-'⚙️ ПАРАМЕТРЫ'!C20-'📊 ДОПУЩЕНИЯ'!C58),0) -> 745 | E65: =ROUND('⚙️ ПАРАМЕТРЫ'!C12*(1+E8)*(1-'⚙️ ПАРАМЕТРЫ'!C19-E9-'⚙️ ПАРАМЕТРЫ'!C20-'📊 ДОПУЩЕНИЯ'!C58),0) -> 680 | F65: =ROUND('⚙️ ПАРАМЕТРЫ'!C12*(1+F8)*(1-'⚙️ ПАРАМЕТРЫ'!C19-F9-'⚙️ ПАРАМЕТРЫ'!C20-'📊 ДОПУЩЕНИЯ'!C58),0) -> 571 | G65: =ROUND('⚙️ ПАРАМЕТРЫ'!C12*(1+G8)*(1-'⚙️ ПАРАМЕТРЫ'!C19-G9-'⚙️ ПАРАМЕТРЫ'!C20-'📊 ДОПУЩЕНИЯ'!C58),0) -> 461
B66: Постоянные при стрессе, ₸/мес | C66: =C58 -> 627524.57 | D66: =D29+D31+D32 -> 656524.57 | E66: =E29+E31+E32 -> 685524.57 | F66: =F29+F31+F32 -> 714524.57 | G66: =G29+G31+G32 -> 772524.57
B67: Безубыт., клиентов/день | C67: =C59 -> 26 | D67: =IFERROR(ROUNDUP(D66/(D65*'⚙️ ПАРАМЕТРЫ'!C14),0),"∞") -> 30 | E67: =IFERROR(ROUNDUP(E66/(E65*'⚙️ ПАРАМЕТРЫ'!C14),0),"∞") -> 34 | F67: =IFERROR(ROUNDUP(F66/(F65*'⚙️ ПАРАМЕТРЫ'!C14),0),"∞") -> 42 | G67: =IFERROR(ROUNDUP(G66/(G65*'⚙️ ПАРАМЕТРЫ'!C14),0),"∞") -> 56
B68: vs Доступно клиентов (с уч. шока) | C68: =C14 -> 70 | D68: =D14 -> 63 | E68: =E14 -> 56 | F68: =F14 -> 46 | G68: =G14 -> 35
B69: ВЕРДИКТ | C69: =IF(C67<=C68,"✅ OK","❌ Убыток") -> ✅ OK | D69: =IF(D67<=D68,"✅ OK","❌ Убыток") -> ✅ OK | E69: =IF(E67<=E68,"✅ OK","❌ Убыток") -> ✅ OK | F69: =IF(F67<=F68,"✅ OK","❌ Убыток") -> ✅ OK | G69: =IF(G67<=G68,"✅ OK","❌ Убыток") -> ❌ Убыток
B71: ZEREK Financial Model | 🔥 СТРЕСС-ТЕСТ | @zerekai_bot
A73: АВТОМАТИЧЕСКИЕ ВЫВОДЫ
B74: 🟢 Базовый: | C74: =IF(C35>0,"Проект жизнеспособен. Рентабельность "&TEXT(C38,"0%")&", окупаемость ~"&C41&" мес.","❌ Проект убыточен даже в базовом сценарии.") -> Проект жизнеспособен. Рентабельность 41%, окупаемость ~2 мес.
B75: 🟡 Мягкий стресс: | C75: =IF(D35>0,"При умеренном снижении спроса проект остаётся прибыльным. Запас: "&TEXT(D41,"0")&" мес. до окупаемости.","⚠️ Уже при мягком стрессе проект убыточен.") -> При умеренном снижении спроса проект остаётся прибыльным. Запас: 3 мес. до окупаемости.
B76: 🟠 Жёсткий стресс: | C76: =IF(F35>0,"При серьёзном стрессе прибыль падает на "&TEXT(ABS(F40),"0%")&". Но бизнес выживает.","❌ В жёстком сценарии бизнес убыточен. Снижайте постоянные расходы.") -> При серьёзном стрессе прибыль падает на 86%. Но бизнес выживает.
B77: 🔴 Критический: | C77: =IF(G35>0,"Даже в критическом сценарии бизнес выживает — вы в безопасности.","❌ Бизнес убыточен. Рекомендация: снизить постоянные расходы или увеличить средний чек.") -> ❌ Бизнес убыточен. Рекомендация: снизить постоянные расходы или увеличить средний чек.
